Workbook
Name BDSL_GJ_L: '[1]Conversion Factors'!$G$20
Name BDSL_GJ_L: '[1]Conversion Factors'!$G$20
Name BDSL_GJ_L: '[1]Conversion Factors'!$G$20
Name BDSL_GJ_L: '[1]Conversion Factors'!$G$20
Name BDSL_GJ_L: 'Conversion Factors'!$G$20
Name BOB_GJ_L: '[1]Conversion Factors'!$G$18
Name BOB_GJ_L: '[1]Conversion Factors'!$G$18
Name BOB_GJ_L: '[1]Conversion Factors'!$G$18
Name BOB_GJ_L: '[1]Conversion Factors'!$G$18
Name BOB_GJ_L: 'Conversion Factors'!$G$18
Name CAD2021_to_2020: '[1]Conversion Factors'!$R$15
Name CAD2021_to_2020: '[1]Conversion Factors'!$R$15
Name CAD2021_to_2020: '[1]Conversion Factors'!$R$15
Name CAD2021_to_2020: '[1]Conversion Factors'!$R$15
Name CAD2021_to_2020: 'Conversion Factors'!$R$15
Name CAD2022_to_2020: '[1]Conversion Factors'!$R$16
Name CAD2022_to_2020: '[1]Conversion Factors'!$R$16
Name CAD2022_to_2020: '[1]Conversion Factors'!$R$16
Name CAD2022_to_2020: '[1]Conversion Factors'!$R$16
Name CAD2022_to_2020: 'Conversion Factors'!$R$16
Name CNG_DGE: 'Conversion Factors'!$D$28
Name DGE_GGE: '[1]Conversion Factors'!$C$19
Name DGE_GGE: '[1]Conversion Factors'!$C$19
Name DGE_GGE: '[1]Conversion Factors'!$C$19
Name DGE_GGE: '[1]Conversion Factors'!$C$19
Name DGE_GGE: 'Conversion Factors'!$C$19
Name DSL_PJ_ML: '[1]Conversion Factors'!$G$15
Name DSL_PJ_ML: '[1]Conversion Factors'!$G$15
Name DSL_PJ_ML: '[1]Conversion Factors'!$G$15
Name DSL_PJ_ML: '[1]Conversion Factors'!$G$15
Name DSL_PJ_ML: 'Conversion Factors'!$G$15
Name E85_PJ_ML: 'Conversion Factors'!$G$16
Name ELC_PJ_MkWh: '[1]Conversion Factors'!$G$17
Name ELC_PJ_MkWh: '[1]Conversion Factors'!$G$17
Name ELC_PJ_MkWh: '[1]Conversion Factors'!$G$17
Name ELC_PJ_MkWh: '[1]Conversion Factors'!$G$17
Name ELC_PJ_MkWh: 'Conversion Factors'!$G$17
Name ETH_GJ_L: '[1]Conversion Factors'!$G$19
Name ETH_GJ_L: '[1]Conversion Factors'!$G$19
Name ETH_GJ_L: '[1]Conversion Factors'!$G$19
Name ETH_GJ_L: '[1]Conversion Factors'!$G$19
Name ETH_GJ_L: 'Conversion Factors'!$G$19
Name GBP2020_to_CAD2020: '[1]Conversion Factors'!$R$17
Name GBP2020_to_CAD2020: '[1]Conversion Factors'!$R$17
Name GBP2020_to_CAD2020: '[1]Conversion Factors'!$R$17
Name GBP2020_to_CAD2020: '[1]Conversion Factors'!$R$17
Name GBP2020_to_CAD2020: 'Conversion Factors'!$R$17
Name GGE_DGE: 'Conversion Factors'!$D$18
Name GSL_PJ_ML: '[1]Conversion Factors'!$G$14
Name GSL_PJ_ML: '[1]Conversion Factors'!$G$14
Name GSL_PJ_ML: '[1]Conversion Factors'!$G$14
Name GSL_PJ_ML: '[1]Conversion Factors'!$G$14
Name GSL_PJ_ML: 'Conversion Factors'!$G$14
Name GWy_PJ: '[1]Conversion Factors'!$G$27
Name GWy_PJ: '[1]Conversion Factors'!$G$27
Name GWy_PJ: '[1]Conversion Factors'!$G$27
Name GWy_PJ: '[1]Conversion Factors'!$G$27
Name GWy_PJ: 'Conversion Factors'!$G$27
Name H2_HHV_by_LHV: '[1]Conversion Factors'!$D$14
Name H2_HHV_by_LHV: '[1]Conversion Factors'!$D$14

Sheet Overview
C1: **********************************************************************************************************************
C2: Canadian Open Energy Model
C3: Transportation Sector Database
C4: Province of Ontario
C6: Sustainable Systems Group
C7: Dept. of Civil and Mineral Engineering
C8: University of Toronto
C10: Authored by: Felipe Rashid Zetter Salcedo
C11: MASc Thesis Project
C12: Last update: August 2024
C14: Supervised by: Prof. Daniel Posen & Prof. Heather McLean
C15: Contact: rashidzetter@gmail.com
... C28: Cell color scheme
A29: Cell | C29: Description
C30: Highlighted values in this color across the model sheets denote those that are used for input parameter calculations. Note that not all the values used for calculations have been highlighted.
C31: Highlighted values in this color denote orphan parameters that are currently not used, but could be in future versions.
C32: Highlighted values in this color denote high uncertainty parameters that need revision.
C34: Sheet descriptions
A35: Sheet | C35: Description
C36: Contains the list of technologies and commodities that will be compiled and used by Temoa.
C37: Harmonized input parameters; ready to be compiled into the SQLite database used by Temoa. The ready-for-input table is located on the far left side of the sheet. At the right side of the ready-for-input table are the calculations.
C38: Compilation of input parameters and the underlying data tables used to run the stochastic aggregation of electric vehicle charging demand with RAMP-mobility.
C39: Compilation of original data tables used for the calculation of harmonized parameters, mostly from the NRCan Energy Use Database, other Canadian sources, and US sources.
C40: Original datasets from other large models, located in separate sheets to differentiate by source, used for the calculation of harmonized parameters.
C41: Contains the conversion factors used across the parameter calculations. Including GREET heating values, unit conversions, currency inflated exchange rates, and inflation indexes.
C42: Contains the list of main database assumptions and all references used.
C44: Data Quality Indicators (DQIs)
C45: Each DQI is given a score of 1 to 5 upon evaluation of data quality, 1 being the best score and 5 being the worse. Based on Table 5-2 from NRC-EME-56367 report.
C47: Reliability: provides indication of quality of data collection and validation methods.
C48: Representativeness: evaluates the robustness of sampling methods and the amount of data points collected.
C49: Temporal: time-related appropiateness measuring the age of the data.
... C51: Technological: measures the gap between goal and scope of the model and the actually-represented technology.

Sheet Technology
A1: tech | B1: flag | C1: sector | D1: description | E1: additional_notes | F1: category | G1: unlim_cap | H1: annual | I1: cf_fixed
A2: T_HDV_T_LH_CHRG_LRGBATT | B2: p | C2: Transport | D2: Charging infrastructure for on-road heavy-duty vehicles long-haul freight trucks large batteries | F2: Charging | G2: 0 | H2: 0
A3: T_HDV_T_LH_CHRG_FSTCHRG | B3: p | C3: Transport | D3: Charging infrastructure for on-road heavy-duty vehicles long-haul freight trucks fast chargers | F3: Charging | G3: 0 | H3: 0
A4: T_HDV_T_LH_CHRG_ERDS1 | B4: p | C4: Transport | D4: Charging infrastructure for on-road heavy-duty vehicles long-haul freight trucks eRoads bin 1 | F4: Charging | G4: 0 | H4: 0
A5: T_HDV_T_LH_CHRG_ERDS2 | B5: p | C5: Transport | D5: Charging infrastructure for on-road heavy-duty vehicles long-haul freight trucks eRoads bin 2 | F5: Charging | G5: 0 | H5: 0
A6: T_HDV_T_LH_CHRG_ERDS3 | B6: p | C6: Transport | D6: Charging infrastructure for on-road heavy-duty vehicles long-haul freight trucks eRoads bin 3 | F6: Charging | G6: 0 | H6: 0
A7: T_HDV_T_LH_CHRG_ERDS4 | B7: p | C7: Transport | D7: Charging infrastructure for on-road heavy-duty vehicles long-haul freight trucks eRoads bin 4 | F7: Charging | G7: 0 | H7: 0
A8: T_HDV_T_LH_CHRG_ERDS5 | B8: p | C8: Transport | D8: Charging infrastructure for on-road heavy-duty vehicles long-haul freight trucks eRoads bin 5 | F8: Charging | G8: 0 | H8: 0
A9: T_H2_HDV_T_LH_REFUEL | B9: p | C9: Transport | D9: Hydrogen refuelling station for on-road heavy-duty vehicles long-haul freight trucks | F9: H2 refuelling | G9: 0 | H9: 0
A10: T_HDV_T_LH_DSL_EX | B10: p | C10: Transport | D10: Existing heavy-duty long-haul freight truck (diesel) | E10: Vehicle class corresponds to “Heavy Trucks” from NRCan Comprehensive Energy Use Database 2024; a truck with a gross weight of more than 33,000 lb (class 8). | F10: Heavy trucks | G10: 0 | H10: 1
A11: T_HDV_T_LH_DSL_N | B11: p | C11: Transport | D11: New heavy-duty long-haul freight truck (diesel) | E11: Vehicle class corresponds to “Heavy Trucks” from NRCan Comprehensive Energy Use Database 2024; a truck with a gross weight of more than 33,000 lb (class 8). | F11: Heavy trucks | G11: 0 | H11: 1
A12: T_HDV_T_LH_FCEV_N | B12: p | C12: Transport | D12: New heavy-duty long-haul freight truck (fuel cell electric, gaseous H2 @ 700 bar) | E12: Vehicle class corresponds to “Heavy Trucks” from NRCan Comprehensive Energy Use Database 2024; a truck with a gross weight of more than 33,000 lb (class 8). | F12: Heavy trucks | G12: 0 | H12: 0
A13: T_HDV_T_LH_BEV_LRGBATT_N | B13: p | C13: Transport | D13: New heavy-duty long-haul freight truck (battery electric) large batteries | E13: Vehicle class corresponds to “Heavy Trucks” from NRCan Comprehensive Energy Use Database 2024; a truck with a gross weight of more than 33,000 lb (class 8). | F13: Heavy trucks | G13: 0 | H13: 0
A14: T_HDV_T_LH_BEV_FSTCHRG_N | B14: p | C14: Transport | D14: New heavy-duty long-haul freight truck (battery electric) fast chargers | E14: Vehicle class corresponds to “Heavy Trucks” from NRCan Comprehensive Energy Use Database 2024; a truck with a gross weight of more than 33,000 lb (class 8). | F14: Heavy trucks | G14: 0 | H14: 0
A15: T_HDV_T_LH_BEV_ERDS1_N | B15: p | C15: Transport | D15: New heavy-duty long-haul freight truck (battery electric) eRoads bin 1 | E15: Vehicle class corresponds to “Heavy Trucks” from NRCan Comprehensive Energy Use Database 2024; a truck with a gross weight of more than 33,000 lb (class 8). | F15: Heavy trucks | G15: 0 | H15: 0
A16: T_HDV_T_LH_BEV_ERDS2_N | B16: p | C16: Transport | D16: New heavy-duty long-haul freight truck (battery electric) eRoads bin 2 | E16: Vehicle class corresponds to “Heavy Trucks” from NRCan Comprehensive Energy Use Database 2024; a truck with a gross weight of more than 33,000 lb (class 8). | F16: Heavy trucks | G16: 0 | H16: 0
A17: T_HDV_T_LH_BEV_ERDS3_N | B17: p | C17: Transport | D17: New heavy-duty long-haul freight truck (battery electric) eRoads bin 3 | E17: Vehicle class corresponds to “Heavy Trucks” from NRCan Comprehensive Energy Use Database 2024; a truck with a gross weight of more than 33,000 lb (class 8). | F17: Heavy trucks | G17: 0 | H17: 0
A18: T_HDV_T_LH_BEV_ERDS4_N | B18: p | C18: Transport | D18: New heavy-duty long-haul freight truck (battery electric) eRoads bin 4 | E18: Vehicle class corresponds to “Heavy Trucks” from NRCan Comprehensive Energy Use Database 2024; a truck with a gross weight of more than 33,000 lb (class 8). | F18: Heavy trucks | G18: 0 | H18: 0
A19: T_HDV_T_LH_BEV_ERDS5_N | B19: p | C19: Transport | D19: New heavy-duty long-haul freight truck (battery electric) eRoads bin 5 | E19: Vehicle class corresponds to “Heavy Trucks” from NRCan Comprehensive Energy Use Database 2024; a truck with a gross weight of more than 33,000 lb (class 8). | F19: Heavy trucks | G19: 0 | H19: 0
A20: T_dummy_tkm_hdv_t_lh | B20: p | C20: Transport | D20: Dummy tech used to release non-profiled vehicles from charging demand distribution | F20: Heavy trucks | G20: 1 | H20: 1

Sheet Commodity
A1: name | B1: flag | C1: description | D1: additional_notes
A2: T_D_tkm_hdv_t_lh | B2: d | C2: Demand for total tonne-kilometers driven by heavy-duty trucks, long-haul | D2: billion tonne-km
A3: T_elc_hdv_t_lh_chrg_lrgbatt | B3: p | C3: Electricity from heavy-duty EV charger, long-haul freight trucks, large batteries | D3: PJ
A4: T_elc_hdv_t_lh_chrg_fstchrg | B4: p | C4: Electricity from heavy-duty EV charger, long-haul freight trucks, fast chargers | D4: PJ
A5: T_elc_hdv_t_lh_chrg_erds1 | B5: p | C5: Electricity from heavy-duty EV charger, long-haul freight trucks, eRoads bin 1 | D5: PJ
A6: T_elc_hdv_t_lh_chrg_erds2 | B6: p | C6: Electricity from heavy-duty EV charger, long-haul freight trucks, eRoads bin 2 | D6: PJ
A7: T_elc_hdv_t_lh_chrg_erds3 | B7: p | C7: Electricity from heavy-duty EV charger, long-haul freight trucks, eRoads bin 3 | D7: PJ
A8: T_elc_hdv_t_lh_chrg_erds4 | B8: p | C8: Electricity from heavy-duty EV charger, long-haul freight trucks, eRoads bin 4 | D8: PJ
A9: T_elc_hdv_t_lh_chrg_erds5 | B9: p | C9: Electricity from heavy-duty EV charger, long-haul freight trucks, eRoads bin 5 | D9: PJ
A10: T_h2_hdv_t_lh | B10: p | C10: Gaseous H2 @ 700 bar for use in heavy-duty vehicles, long-haul freight trucks | D10: PJ
A11: T_annual_tkm_hdv_t_lh | B11: a | C11: Dummy annual commodity (flag='a') used to release non-profiled vehicles from charging demand distribution | D11: billion tonne-km

Sheet ExistingCapacity
F1: vintage | AB1: DQI | AG1: Model input | AI1: Input calculations | AJ1: LDV market share by vehicle class and technology type in Ontario | BG1: ON Ministry of Transportation - 2020 fleet registration data by age and class
A2: tech | B2: region | C2: reference | D2: data_year | E2: units | F2: 2000 | G2: 2001 | H2: 2002 | I2: 2003 | J2: 2004 | K2: 2005 | L2: 2006 | M2: 2007 | N2: 2008 | O2: 2009 | P2: 2010 | Q2: 2011 | R2: 2012 | S2: 2013 | T2: 2014 | U2: 2015 | V2: 2016 | W2: 2017 | X2: 2018 | Y2: 2019 | Z2: 2020 | AA2: notes | AB2: Reliability | AC2: Representativeness | AD2: Temporal | AE2: Geographical | AF2: Technological | AJ2: Vehicle type | AK2: Downscaling Source | AL2: 2005 | AM2: 2006 | AN2: 2007 | AO2: 2008 | AP2: 2009 | AQ2: 2010 | AR2: 2011 | AS2: 2012 | AT2: 2013 | AU2: 2014 | AV2: 2015 | AW2: 2016 | AX2: 2017 | AY2: 2018 | AZ2: 2019 | BA2: 2020 | BB2: 2021 | BC2: 2022 | BD2: 2023 | BE2: Conv. veh. market share change | BG2: Registered class | BH2: 2003 | BI2: 2004 | BJ2: 2005 | BK2: 2006 | BL2: 2007 | BM2: 2008 | BN2: 2009 | BO2: 2010 | BP2: 2011 | BQ2: 2012 | BR2: 2013 | BS2: 2014 | BT2: 2015 | BU2: 2016 | BV2: 2017 | BW2: 2018 | BX2: 2019 | BY2: 2020 | BZ2: 2021
A3: T_HDV_T_DSL_EX | B3: ON | C3: Natural Resources Canada. (2023b). Transportation Sector – Ontario. Government of Canada, Natural Resources Canada. https://oee.nrcan.gc.ca/corporate/statistics/neud/dpa/menus/trends/comprehensive/trends_tran_on.cfm | D3: 2023 | E3: k units | K3: =(1-CFAF!$E$3)*SUMIF($BH$3:$BY$3,K$2,$BH$16:$BY$16) -> 6.2663437 | P3: =(1-CFAF!$E$3)*SUMIF($BH$3:$BY$3,P$2,$BH$16:$BY$16) -> 17.233369 | U3: =(1-CFAF!$E$3)*SUMIF($BH$3:$BY$3,U$2,$BH$16:$BY$16) -> 22.965776 | Z3: =(1-CFAF!$E$3)*SUMIF($BH$3:$BY$3,Z$2,$BH$16:$BY$16) -> 40.184767 | AA3: Vehicle class 2021 fleet stock was distributed across vintages up to 2020 based on commercial vehicle registrations by age (ON Ministry of Transportation, 2023). Ontario long-haul/short-haul split from Canadian Freight Analysis Framework 2017 data. | AB3: 1 | AC3: 1 | AD3: 1 | AE3: 1 | AF3: 1 | BG3: Aggregated vintage | BH3: 2005 | BI3: 2005 | BJ3: =BJ2 -> 2005 | BK3: 2010 | BL3: 2010 | BM3: 2010 | BN3: 2010 | BO3: 2010 | BP3: 2015 | BQ3: 2015 | BR3: 2015 | BS3: 2015 | BT3: 2015 | BU3: 2020 | BV3: 2020 | BW3: 2020 | BX3: 2020 | BY3: 2020
A4: T_HDV_T_LH_DSL_EX | B4: ON | C4: Natural Resources Canada. (2023b). Transportation Sector – Ontario. Government of Canada, Natural Resources Canada. https://oee.nrcan.gc.ca/corporate/statistics/neud/dpa/menus/trends/comprehensive/trends_tran_on.cfm | D4: 2023 | E4: k units | K4: =(CFAF!$E$3)*SUMIF($BH$3:$BY$3,K$2,$BH$16:$BY$16) -> 3.4640036 | P4: =(CFAF!$E$3)*SUMIF($BH$3:$BY$3,P$2,$BH$16:$BY$16) -> 9.5265207 | U4: =(CFAF!$E$3)*SUMIF($BH$3:$BY$3,U$2,$BH$16:$BY$16) -> 12.695367 | Z4: =(CFAF!$E$3)*SUMIF($BH$3:$BY$3,Z$2,$BH$16:$BY$16) -> 22.21394 | AA4: Vehicle class 2021 fleet stock was distributed across vintages up to 2020 based on commercial vehicle registrations by age (ON Ministry of Transportation, 2023). Ontario long-haul/short-haul split from Canadian Freight Analysis Framework 2017 data. | AB4: 1 | AC4: 1 | AD4: 1 | AE4: 1 | AF4: 1 | AJ4: Cars | AK4: (StatCan, 2023) Table: 20-10-0021-01 | AR4: ='Background Data'!AD66-'Background Data'!AD72 -> 247563 | AS4: ='Background Data'!AE66-'Background Data'!AE72 -> 265280 | AT4: ='Background Data'!AF66-'Background Data'!AF72 -> 277662 | AU4: ='Background Data'!AG66-'Background Data'!AG72 -> 277922 | AV4: ='Background Data'!AH66-'Background Data'!AH72 -> 267263 | AW4: ='Background Data'!AI66-'Background Data'!AI72 -> 249770 | AX4: ='Background Data'!AJ66-'Background Data'!AJ72 -> 253252 | AY4: ='Background Data'!AK66-'Background Data'!AK72 -> 240525 | ... BD4: ='Background Data'!AP66-'Background Data'!AP72 -> 110562 | BG4: Vehicle Age (in 2021) | BH4: =2021-BH2 -> 18 | BI4: =2021-BI2 -> 17 | BJ4: =2021-BJ2 -> 16 | BK4: =2021-BK2 -> 15 | BL4: =2021-BL2 -> 14 | BM4: =2021-BM2 -> 13 | BN4: =2021-BN2 -> 12 | BO4: =2021-BO2 -> 11 | ... BY4: =2021-BY2 -> 1 | BZ4: 0
AJ5: Gasoline | AN5: 0.97 | AO5: 0.97 | AP5: 0.97 | AQ5: 0.97 | AR5: ='Background Data'!AD67/AR$4 -> 0.95873778 | AS5: ='Background Data'!AE67/AS$4 -> 0.94412319 | AT5: ='Background Data'!AF67/AT$4 -> 0.94165928 | AU5: ='Background Data'!AG67/AU$4 -> 0.93791783 | AV5: ='Background Data'!AH67/AV$4 -> 0.95077882 | AW5: ='Background Data'!AI67/AW$4 -> 0.96515995 | AX5: ='Background Data'!AJ67/AX$4 -> 0.9530981 | AY5: ='Background Data'!AK67/AY$4 -> 0.92406195 | ... BD5: ='Background Data'!AP67/BD$4 -> 0.80563847 | BE5: =1 - BD5/AZ5 -> 0.13105422 | BG5: Passenger registrations | BK5: 171090 | BL5: 222416 | BM5: 255644 | BN5: 262822 | BO5: 347718 | BP5: 325214 | BQ5: 369730 | BR5: 420215 | BS5: 425526 | BT5: 489953 | BU5: 486871 | BV5: 543758 | BW5: 534711 | BX5: 517396 | BY5: 422696 | BZ5: 430762
AJ6: Diesel | AN6: 0.03 | AO6: 0.03 | AP6: 0.03 | AQ6: 0.03 | AR6: ='Background Data'!AD68/AR$4 -> 0.026461951 | AS6: ='Background Data'!AE68/AS$4 -> 0.028848764 | AT6: ='Background Data'!AF68/AT$4 -> 0.029146948 | AU6: ='Background Data'!AG68/AU$4 -> 0.032861738 | AV6: ='Background Data'!AH68/AV$4 -> 0.023141999 | AW6: ='Background Data'!AI68/AW$4 -> 0.0036073187 | AX6: ='Background Data'!AJ68/AX$4 -> 0.0030207066 | AY6: ='Background Data'!AK68/AY$4 -> 0.0029352458 | ... BD6: ='Background Data'!AP68/BD$4 -> 0 | BG6: Distribution (>2008) | BM6: =BM5/SUM($BM$5:$BZ$5) -> 0.04382707 | BN6: =BN5/SUM($BM$5:$BZ$5) -> 0.045057651 | BO6: =BO5/SUM($BM$5:$BZ$5) -> 0.059612043 | BP6: =BP5/SUM($BM$5:$BZ$5) -> 0.055754004 | BQ6: =BQ5/SUM($BM$5:$BZ$5) -> 0.063385734 | BR6: =BR5/SUM($BM$5:$BZ$5) -> 0.072040776 | BS6: =BS5/SUM($BM$5:$BZ$5) -> 0.072951283 | BT6: =BT5/SUM($BM$5:$BZ$5) -> 0.083996512 | ... BZ6: =BZ5/SUM($BM$5:$BZ$5) -> 0.073848932
AJ7: Battery electric | AN7: 0 | AO7: 0 | AP7: 0 | AQ7: 0 | AR7: ='Background Data'!AD69/AR$4 -> 0.00026255943 | AS7: ='Background Data'!AE69/AS$4 -> 0.00070491556 | AT7: ='Background Data'!AF69/AT$4 -> 0.0022113217 | AU7: ='Background Data'!AG69/AU$4 -> 0.0038715899 | AV7: ='Background Data'!AH69/AV$4 -> 0.0045423422 | AW7: ='Background Data'!AI69/AW$4 -> 0.0037234256 | AX7: ='Background Data'!AJ69/AX$4 -> 0.0099979467 | AY7: ='Background Data'!AK69/AY$4 -> 0.030396009 | ... BD7: ='Background Data'!AP69/BD$4 -> 0.092011722 | BG7: 2021 car fleet (k units) | BM7: ='Background Data'!$X$11*BM6 -> 180.55727 | BN7: ='Background Data'!$X$11*BN6 -> 185.62698 | BO7: ='Background Data'!$X$11*BO6 -> 245.58767 | BP7: ='Background Data'!$X$11*BP6 -> 229.69345 | BQ7: ='Background Data'!$X$11*BQ6 -> 261.13439 | BR7: ='Background Data'!$X$11*BR6 -> 296.79114 | BS7: ='Background Data'!$X$11*BS6 -> 300.54221 | BT7: ='Background Data'!$X$11*BT6 -> 346.04598 | ... BY7: ='Background Data'!$X$11*BY6 -> 298.54343
AJ8: Hybrid electric | AN8: 0 | AO8: 0 | AP8: 0 | AQ8: 0 | AR8: ='Background Data'!AD70/AR$4 -> 0.013879295 | AS8: ='Background Data'!AE70/AS$4 -> 0.024690893 | AT8: ='Background Data'!AF70/AT$4 -> 0.025282538 | AU8: ='Background Data'!AG70/AU$4 -> 0.023046034 | AV8: ='Background Data'!AH70/AV$4 -> 0.018917695 | AW8: ='Background Data'!AI70/AW$4 -> 0.019333787 | AX8: ='Background Data'!AJ70/AX$4 -> 0.019435187 | AY8: ='Background Data'!AK70/AY$4 -> 0.019669473 | ... BD8: ='Background Data'!AP70/BD$4 -> 0.094878891 | BE8: =BD8/AZ8 - 1 -> 1.5317936 | BG8: Distribution (>2006) | BK8: =BK5/SUM($BK$5:$BZ$5) -> 0.027477619 | BL8: =BL5/SUM($BK$5:$BZ$5) -> 0.035720744 | BM8: =BM5/SUM($BK$5:$BZ$5) -> 0.041057271 | BN8: =BN5/SUM($BK$5:$BZ$5) -> 0.042210081 | BO8: =BO5/SUM($BK$5:$BZ$5) -> 0.055844659 | BP8: =BP5/SUM($BK$5:$BZ$5) -> 0.052230443 | BQ8: =BQ5/SUM($BK$5:$BZ$5) -> 0.059379859 | BR8: =BR5/SUM($BK$5:$BZ$5) -> 0.067487917 | ... BZ8: =BZ5/SUM($BK$5:$BZ$5) -> 0.0691818
AJ9: Plug-in hybrid electric | AN9: 0 | AO9: 0 | AP9: 0 | AQ9: 0 | AR9: ='Background Data'!AD71/AR$4 -> 0.00065841826 | AS9: ='Background Data'!AE71/AS$4 -> 0.0016322376 | AT9: ='Background Data'!AF71/AT$4 -> 0.0016999085 | AU9: ='Background Data'!AG71/AU$4 -> 0.0023028044 | AV9: ='Background Data'!AH71/AV$4 -> 0.0026191429 | AW9: ='Background Data'!AI71/AW$4 -> 0.0081755215 | AX9: ='Background Data'!AJ71/AX$4 -> 0.01444806 | AY9: ='Background Data'!AK71/AY$4 -> 0.022937325 | ... BD9: ='Background Data'!AP71/BD$4 -> 0.0074709213 | BG9: 2021 LT fleet (k units) | BK9: ='Background Data'!$X$12*BK8 -> 113.00069 | BL9: ='Background Data'!$X$12*BL8 -> 146.90024 | BM9: ='Background Data'!$X$12*BM8 -> 168.84651 | BN9: ='Background Data'!$X$12*BN8 -> 173.5874 | BO9: ='Background Data'!$X$12*BO8 -> 229.6591 | BP9: ='Background Data'!$X$12*BP8 -> 214.79576 | BQ9: ='Background Data'!$X$12*BQ8 -> 244.19747 | BR9: ='Background Data'!$X$12*BR8 -> 277.54156 | ... BY9: ='Background Data'!$X$12*BY8 -> 279.1802
AJ10: Pickup Trucks (Light/Medium Trucks) | AR10: ='Background Data'!AD73-'Background Data'!AD76-'Background Data'!AD78-'Background Data'!AD79 -> 78026 | AS10: ='Background Data'!AE73-'Background Data'!AE76-'Background Data'!AE78-'Background Data'!AE79 -> 66686 | AT10: ='Background Data'!AF73-'Background Data'!AF76-'Background Data'!AF78-'Background Data'!AF79 -> 80401 | AU10: ='Background Data'!AG73-'Background Data'!AG76-'Background Data'!AG78-'Background Data'!AG79 -> 86768 | AV10: ='Background Data'!AH73-'Background Data'!AH76-'Background Data'!AH78-'Background Data'!AH79 -> 104178 | AW10: ='Background Data'!AI73-'Background Data'!AI76-'Background Data'!AI78-'Background Data'!AI79 -> 126823 | AX10: ='Background Data'!AJ73-'Background Data'!AJ76-'Background Data'!AJ78-'Background Data'!AJ79 -> 144063 | AY10: ='Background Data'!AK73-'Background Data'!AK76-'Background Data'!AK78-'Background Data'!AK79 -> 135361 | ... BA10: ='Background Data'!AM73-'Background Data'!AM76-'Background Data'!AM78-'Background Data'!AM79 -> 127770 | BB10: ='Background Data'!AN73 -'Background Data'!AN79 -> 117894 | BC10: ='Background Data'!AO73 -'Background Data'!AO79 -> 122767 | BD10: ='Background Data'!AP73 -'Background Data'!AP79 -> 127652 | BG10: Commercial registrations | BH10: 26945 | BI10: 30185 | BJ10: 36137 | BK10: 42697 | BL10: 52407 | BM10: 53633 | BN10: 44846 | BO10: 62915 | BP10: 68877 | BQ10: 59224 | BR10: 60904 | BS10: 71922 | BT10: 80891 | BU10: 100677 | BV10: 117816 | BW10: 123742 | BX10: 143314 | BY10: 112553 | BZ10: 129859
AJ11: Gasoline | AL11: The lifetime of cars, light trucks, and medium trucks is assumed to be 14 and 16 years, respectively. Since the available market shares with fuel type resolution are only available from 2011-2021, the remaining market shares of gasoline vehicles are assumed to remain constant based on the 2011 shares. Diesel is assumed to account for the entire remaining share. MDVs are represented with registered vehicles instead, as only diesel and gasoline fuel types are reported. | AR11: ='Background Data'!AD74/AR$10 -> 0.93075385 | AS11: ='Background Data'!AE74/AS$10 -> 0.92463186 | AT11: ='Background Data'!AF74/AT$10 -> 0.93408042 | AU11: ='Background Data'!AG74/AU$10 -> 0.90168034 | AV11: ='Background Data'!AH74/AV$10 -> 0.893394 | AW11: ='Background Data'!AI74/AW$10 -> 0.88861642 | AX11: ='Background Data'!AJ74/AX$10 -> 0.91154564 | AY11: ='Background Data'!AK74/AY$10 -> 0.88623015 | ... BD11: ='Background Data'!AP74/BD$10 -> 0.809059 | BG11: Distribution (>2006) | BK11: =BK10/SUM($BK$10:$BZ$10) -> 0.032193124 | BL11: =BL10/SUM($BK$10:$BZ$10) -> 0.03951437 | BM11: =BM10/SUM($BK$10:$BZ$10) -> 0.040438762 | BN11: =BN10/SUM($BK$10:$BZ$10) -> 0.033813449 | BO11: =BO10/SUM($BK$10:$BZ$10) -> 0.0474373 | BP11: =BP10/SUM($BK$10:$BZ$10) -> 0.05193259 | BQ11: =BQ10/SUM($BK$10:$BZ$10) -> 0.044654322 | BR11: =BR10/SUM($BK$10:$BZ$10) -> 0.045921026 | ... BZ11: =BZ10/SUM($BK$10:$BZ$10) -> 0.097912427
AJ12: Diesel | AR12: ='Background Data'!AD75/AR$10 -> 0.068387461 | AS12: ='Background Data'!AE75/AS$10 -> 0.0744834 | AT12: ='Background Data'!AF75/AT$10 -> 0.065807639 | AU12: ='Background Data'!AG75/AU$10 -> 0.098308132 | AV12: ='Background Data'!AH75/AV$10 -> 0.106606 | AW12: ='Background Data'!AI75/AW$10 -> 0.11138358 | AX12: ='Background Data'!AJ75/AX$10 -> 0.088454357 | AY12: ='Background Data'!AK75/AY$10 -> 0.11376985 | ... BD12: ='Background Data'!AP75/BD$10 -> 0.14190142 | BG12: 2021 LT fleet (k units) | BK12: ='Background Data'!$X$13*BK11 -> 36.996177 | BL12: ='Background Data'!$X$13*BL11 -> 45.409716 | BM12: ='Background Data'!$X$13*BM11 -> 46.472023 | BN12: ='Background Data'!$X$13*BN11 -> 38.858247 | BO12: ='Background Data'!$X$13*BO11 -> 54.514708 | BP12: ='Background Data'!$X$13*BP11 -> 59.680673 | BQ12: ='Background Data'!$X$13*BQ11 -> 51.316523 | BR12: ='Background Data'!$X$13*BR11 -> 52.772213 | ... BY12: ='Background Data'!$X$13*BY11 -> 97.525136
AJ13: Battery electric | AR13: ='Background Data'!AD76/AR$10 -> 0 | AS13: ='Background Data'!AE76/AS$10 -> 0 | AT13: ='Background Data'!AF76/AT$10 -> 0 | AU13: ='Background Data'!AG76/AU$10 -> 0 | AV13: ='Background Data'!AH76/AV$10 -> 0 | AW13: ='Background Data'!AI76/AW$10 -> 0 | AX13: ='Background Data'!AJ76/AX$10 -> 0 | AY13: ='Background Data'!AK76/AY$10 -> 0 | ... BD13: ='Background Data'!AP76/BD$10 -> 0.014171341 | BG13: Distribution (>2004) | BI13: 0.021675299 | BJ13: 0.025949322 | BK13: 0.030659939 | BL13: 0.037632513 | BM13: 0.038512881 | BN13: 0.032203097 | BO13: 0.045178117 | BP13: 0.04945932 | BQ13: 0.042527677 | BR13: 0.043734054 | BS13: 0.051645879 | BT13: 0.058086355 | BU13: 0.072294322 | BV13: 0.084601526 | BW13: 0.088856878 | BX13: 0.10291118 | BY13: 0.080822261 | BZ13: 0.080822261
AJ14: Hybrid electric | AR14: ='Background Data'!AD77/AR$10 -> 0.00085868813 | AS14: ='Background Data'!AE77/AS$10 -> 0.00088474342 | AT14: ='Background Data'!AF77/AT$10 -> 0.00011193891 | AU14: ='Background Data'!AG77/AU$10 -> 1.1524986e-05 | AV14: ='Background Data'!AH77/AV$10 -> 0 | AW14: ='Background Data'!AI77/AW$10 -> 0 | AX14: ='Background Data'!AJ77/AX$10 -> 0 | AY14: ='Background Data'!AK77/AY$10 -> 0 | ... BD14: ='Background Data'!AP77/BD$10 -> 0.034868236 | BG14: 2021 MT fleet (k units) | BI14: ='Background Data'!$X$14*BI13 -> 9.1603716 | BJ14: ='Background Data'!$X$14*BJ13 -> 10.966651 | BK14: ='Background Data'!$X$14*BK13 -> 12.957442 | BL14: ='Background Data'!$X$14*BL13 -> 15.904177 | BM14: ='Background Data'!$X$14*BM13 -> 16.276237 | BN14: ='Background Data'!$X$14*BN13 -> 13.609608 | BO14: ='Background Data'!$X$14*BO13 -> 19.093085 | BP14: ='Background Data'!$X$14*BP13 -> 20.902399 | ... BY14: ='Background Data'!$X$14*BY13 -> 34.156942
AJ15: Plug-in hybrid electric | AR15: ='Background Data'!AD78/AR$10 -> 0 | AS15: ='Background Data'!AE78/AS$10 -> 0 | AT15: ='Background Data'!AF78/AT$10 -> 0 | AU15: ='Background Data'!AG78/AU$10 -> 0 | AV15: ='Background Data'!AH78/AV$10 -> 0 | AW15: ='Background Data'!AI78/AW$10 -> 0 | AX15: ='Background Data'!AJ78/AX$10 -> 0 | AY15: ='Background Data'!AK78/AY$10 -> 0 | ... BD15: ='Background Data'!AP78/BD$10 -> 0 | BG15: Distribution (>2003) | BH15: =BH10/SUM($BH$10:$BZ$10) -> 0.018981448 | BI15: =BI10/SUM($BH$10:$BZ$10) -> 0.021263871 | BJ15: =BJ10/SUM($BH$10:$BZ$10) -> 0.025456766 | BK15: =BK10/SUM($BH$10:$BZ$10) -> 0.030077969 | BL15: =BL10/SUM($BH$10:$BZ$10) -> 0.036918193 | BM15: =BM10/SUM($BH$10:$BZ$10) -> 0.037781851 | BN15: =BN10/SUM($BH$10:$BZ$10) -> 0.031591835 | BO15: =BO10/SUM($BH$10:$BZ$10) -> 0.044320571 | ... BZ15: =BZ10/SUM($BH$10:$BZ$10) -> 0.091479376 | CF15: return 5 * -((vintage - 2000) // -5) + 2000 #
AJ16: Multi-purpose vehicles (Light Trucks) | AR16: ='Background Data'!AD80-'Background Data'!AD86 -> 197405 | AS16: ='Background Data'!AE80-'Background Data'!AE86 -> 199443 | AT16: ='Background Data'!AF80-'Background Data'!AF86 -> 215645 | AU16: ='Background Data'!AG80-'Background Data'!AG86 -> 243844 | AV16: ='Background Data'!AH80-'Background Data'!AH86 -> 284143 | AW16: ='Background Data'!AI80-'Background Data'!AI86 -> 318787 | AX16: ='Background Data'!AJ80-'Background Data'!AJ86 -> 345265 | AY16: ='Background Data'!AK80-'Background Data'!AK86 -> 368223 | ... BD16: ='Background Data'!AP80-'Background Data'!AP86 -> 412101 | BG16: 2021 HT fleet (k units) | BH16: ='Background Data'!$X$15*BH15 -> 2.8111144 | BI16: ='Background Data'!$X$15*BI15 -> 3.1491367 | BJ16: ='Background Data'!$X$15*BJ15 -> 3.7700962 | BK16: ='Background Data'!$X$15*BK15 -> 4.454487 | BL16: ='Background Data'!$X$15*BL15 -> 5.4675106 | BM16: ='Background Data'!$X$15*BM15 -> 5.5954166 | BN16: ='Background Data'!$X$15*BN15 -> 4.6786876 | BO16: ='Background Data'!$X$15*BO15 -> 6.5637879 | ... BY16: ='Background Data'!$X$15*BY15 -> 11.742415
AJ17: Gasoline | AR17: ='Background Data'!AD81/AR$16 -> 0.97816165 | AS17: ='Background Data'!AE81/AS$16 -> 0.97100926 | AT17: ='Background Data'!AF81/AT$16 -> 0.96371351 | AU17: ='Background Data'!AG81/AU$16 -> 0.96030249 | AV17: ='Background Data'!AH81/AV$16 -> 0.96466568 | AW17: ='Background Data'!AI81/AW$16 -> 0.97383206 | AX17: ='Background Data'!AJ81/AX$16 -> 0.97924493 | AY17: ='Background Data'!AK81/AY$16 -> 0.97193548 | ... BD17: ='Background Data'!AP81/BD$16 -> 0.79800583 | BG17: Motorcycle registrations | BJ17: 9068 | BK17: 10820 | BL17: 11655 | BM17: 12072 | BN17: 11711 | BO17: 6270 | BP17: 6679 | BQ17: 7536 | BR17: 8190 | BS17: 8307 | BT17: 8226 | BU17: 8041 | BV17: 8278 | BW17: 8807 | BX17: 8442 | BY17: 6964 | BZ17: 6758 | CF17: vintage
AJ18: Diesel | AR18: ='Background Data'!AD82/AR$16 -> 0.017314658 | AS18: ='Background Data'!AE82/AS$16 -> 0.024473158 | AT18: ='Background Data'!AF82/AT$16 -> 0.032799277 | AU18: ='Background Data'!AG82/AU$16 -> 0.035797477 | AV18: ='Background Data'!AH82/AV$16 -> 0.031610844 | AW18: ='Background Data'!AI82/AW$16 -> 0.013755266 | AX18: ='Background Data'!AJ82/AX$16 -> 0.0059027124 | AY18: ='Background Data'!AK82/AY$16 -> 0.0074357115 | ... BD18: ='Background Data'!AP82/BD$16 -> 0.0044042601 | BG18: Distribution (>2005) | BJ18: =BJ17/SUM($BJ$17:$BZ$17) -> 0.061343219 | BK18: =BK17/SUM($BJ$17:$BZ$17) -> 0.073195151 | BL18: =BL17/SUM($BJ$17:$BZ$17) -> 0.07884376 | BM18: =BM17/SUM($BJ$17:$BZ$17) -> 0.081664682 | BN18: =BN17/SUM($BJ$17:$BZ$17) -> 0.079222589 | BO18: =BO17/SUM($BJ$17:$BZ$17) -> 0.042415305 | BP18: =BP17/SUM($BJ$17:$BZ$17) -> 0.045182108 | BQ18: =BQ17/SUM($BJ$17:$BZ$17) -> 0.050979543 | ... BZ18: =BZ17/SUM($BJ$17:$BZ$17) -> 0.045716528 | CF18: 2003
AJ19: Battery electric | AR19: ='Background Data'!AD83/AR$16 -> 0 | AS19: ='Background Data'!AE83/AS$16 -> 0 | AT19: ='Background Data'!AF83/AT$16 -> 0 | AU19: ='Background Data'!AG83/AU$16 -> 6.1514739e-05 | AV19: ='Background Data'!AH83/AV$16 -> 0.00020764193 | AW19: ='Background Data'!AI83/AW$16 -> 0.0016970579 | AX19: ='Background Data'!AJ83/AX$16 -> 0.0029861121 | AY19: ='Background Data'!AK83/AY$16 -> 0.0024523183 | ... BD19: ='Background Data'!AP83/BD$16 -> 0.062666676 | BG19: 2021 fleet (k units) | BJ19: ='Background Data'!$X$16*BJ18 -> 14.9675 | BK19: ='Background Data'!$X$16*BK18 -> 17.859324 | BL19: ='Background Data'!$X$16*BL18 -> 19.237562 | BM19: ='Background Data'!$X$16*BM18 -> 19.925856 | BN19: ='Background Data'!$X$16*BN18 -> 19.329995 | BO19: ='Background Data'!$X$16*BO18 -> 10.349165 | BP19: ='Background Data'!$X$16*BP18 -> 11.024254 | BQ19: ='Background Data'!$X$16*BQ18 -> 12.438805 | ... BY19: ='Background Data'!$X$16*BY18 -> 11.49467 | CF19: 2004
AJ20: Hybrid electric | AR20: ='Background Data'!AD84/AR$16 -> 0.0045236949 | AS20: ='Background Data'!AE84/AS$16 -> 0.0045175815 | AT20: ='Background Data'!AF84/AT$16 -> 0.0034872128 | AU20: ='Background Data'!AG84/AU$16 -> 0.0037852069 | AV20: ='Background Data'!AH84/AV$16 -> 0.0031638999 | AW20: ='Background Data'!AI84/AW$16 -> 0.0091534473 | AX20: ='Background Data'!AJ84/AX$16 -> 0.01060345 | AY20: ='Background Data'!AK84/AY$16 -> 0.012332201 | ... BD20: ='Background Data'!AP84/BD$16 -> 0.11053601 | BG20: Bus registrations | BN20: 1234 | BO20: 1794 | BP20: 1693 | BQ20: 2090 | BR20: 2352 | BS20: 1971 | BT20: 1816 | BU20: 2327 | BV20: 2802 | BW20: 2500 | BX20: 2995 | BY20: 1830 | BZ20: 1304 | CF20: 2005
AJ21: Plug-in hybrid electric | AR21: ='Background Data'!AD85/AR$16 -> 0 | AS21: ='Background Data'!AE85/AS$16 -> 0 | AT21: ='Background Data'!AF85/AT$16 -> 0 | AU21: ='Background Data'!AG85/AU$16 -> 5.3312774e-05 | AV21: ='Background Data'!AH85/AV$16 -> 0.00035193547 | AW21: ='Background Data'!AI85/AW$16 -> 0.0015621716 | AX21: ='Background Data'!AJ85/AX$16 -> 0.0012627981 | AY21: ='Background Data'!AK85/AY$16 -> 0.0058442846 | ... BD21: ='Background Data'!AP85/BD$16 -> 0.024387225 | BG21: Distribution (>2009) | BN21: =BN20/SUM($BN$20:$BZ$20) -> 0.046203385 | BO21: =BO20/SUM($BN$20:$BZ$20) -> 0.067170885 | BP21: =BP20/SUM($BN$20:$BZ$20) -> 0.063389247 | BQ21: =BQ20/SUM($BN$20:$BZ$20) -> 0.078253707 | BR21: =BR20/SUM($BN$20:$BZ$20) -> 0.088063502 | BS21: =BS20/SUM($BN$20:$BZ$20) -> 0.073798113 | BT21: =BT20/SUM($BN$20:$BZ$20) -> 0.067994608 | BU21: =BU20/SUM($BN$20:$BZ$20) -> 0.087127452 | ... BZ21: =BZ20/SUM($BN$20:$BZ$20) -> 0.048824322 | CF21: 2006
AJ22: Vans (Light Trucks) | AR22: ='Background Data'!AD87-'Background Data'!AD93 -> 54348 | AS22: ='Background Data'!AE87-'Background Data'!AE93 -> 51561 | AT22: ='Background Data'!AF87-'Background Data'!AF93 -> 51829 | AU22: ='Background Data'!AG87-'Background Data'!AG93 -> 55717 | AV22: ='Background Data'!AH87-'Background Data'!AH93 -> 58619 | AW22: ='Background Data'!AI87-'Background Data'!AI93 -> 60304 | AX22: ='Background Data'!AJ87-'Background Data'!AJ93 -> 58851 | AY22: ='Background Data'!AK87-'Background Data'!AK93 -> 54428 | ... BD22: ='Background Data'!AP87-'Background Data'!AP93 -> 26728 | BG22: 2021 BS fleet (k units) | BN22: ='Background Data'!$X17*BN$21 -> 0.58336394 | BO22: ='Background Data'!$X17*BO$21 -> 0.8480996 | BP22: ='Background Data'!$X17*BP$21 -> 0.80035263 | BQ22: ='Background Data'!$X17*BQ$21 -> 0.9880313 | BR22: ='Background Data'!$X17*BR$21 -> 1.1118898 | BS22: ='Background Data'!$X17*BS$21 -> 0.93177497 | BT22: ='Background Data'!$X17*BT$21 -> 0.85849993 | BU22: ='Background Data'!$X17*BU$21 -> 1.1000712 | ... BY22: ='Background Data'!$X17*BY$21 -> 0.86511832 | CF22: 2007
AJ23: Gasoline | AR23: ='Background Data'!AD88/AR$22 -> 0.97468168 | AS23: ='Background Data'!AE88/AS$22 -> 0.97511685 | AT23: ='Background Data'!AF88/AT$22 -> 0.9713095 | AU23: ='Background Data'!AG88/AU$22 -> 0.96772978 | AV23: ='Background Data'!AH88/AV$22 -> 0.95791467 | AW23: ='Background Data'!AI88/AW$22 -> 0.95501128 | AX23: ='Background Data'!AJ88/AX$22 -> 0.95133473 | AY23: ='Background Data'!AK88/AY$22 -> 0.93766076 | ... BD23: ='Background Data'!AP88/BD$22 -> 0.79190362 | BG23: 2021 BT fleet (k units) | BN23: ='Background Data'!$X18*BN$21 -> 0.30508095 | BO23: ='Background Data'!$X18*BO$21 -> 0.44352935 | BP23: ='Background Data'!$X18*BP$21 -> 0.4185592 | BQ23: ='Background Data'!$X18*BQ$21 -> 0.51670923 | BR23: ='Background Data'!$X18*BR$21 -> 0.5814833 | BS23: ='Background Data'!$X18*BS$21 -> 0.48728894 | BT23: ='Background Data'!$X18*BT$21 -> 0.4489684 | BU23: ='Background Data'!$X18*BU$21 -> 0.57530257 | ... BY23: ='Background Data'!$X18*BY$21 -> 0.45242961 | CF23: 2008
AJ24: Diesel | AR24: ='Background Data'!AD89/AR$22 -> 0.02504232 | AS24: ='Background Data'!AE89/AS$22 -> 0.024669809 | AT24: ='Background Data'!AF89/AT$22 -> 0.028690501 | AU24: ='Background Data'!AG89/AU$22 -> 0.032270223 | AV24: ='Background Data'!AH89/AV$22 -> 0.042085331 | AW24: ='Background Data'!AI89/AW$22 -> 0.044972141 | AX24: ='Background Data'!AJ89/AX$22 -> 0.039795416 | AY24: ='Background Data'!AK89/AY$22 -> 0.046262953 | ... BD24: ='Background Data'!AP89/BD$22 -> 0.089419336 | BG24: 2021 BIC fleet (k units) | BN24: ='Background Data'!$X19*BN$21 -> 0.04749708 | BO24: ='Background Data'!$X19*BO$21 -> 0.06905167 | BP24: ='Background Data'!$X19*BP$21 -> 0.065164146 | BQ24: ='Background Data'!$X19*BQ$21 -> 0.080444811 | BR24: ='Background Data'!$X19*BR$21 -> 0.09052928 | BS24: ='Background Data'!$X19*BS$21 -> 0.07586446 | BT24: ='Background Data'!$X19*BT$21 -> 0.069898457 | BU24: ='Background Data'!$X19*BU$21 -> 0.089567021 | ... BY24: ='Background Data'!$X19*BY$21 -> 0.070437322 | CF24: 2009
AJ25: Battery electric | AR25: ='Background Data'!AD90/AR$22 -> 0.00027599912 | AS25: ='Background Data'!AE90/AS$22 -> 0.00021333954 | AT25: ='Background Data'!AF90/AT$22 -> 0 | AU25: ='Background Data'!AG90/AU$22 -> 0 | AV25: ='Background Data'!AH90/AV$22 -> 0 | AW25: ='Background Data'!AI90/AW$22 -> 0 | AX25: ='Background Data'!AJ90/AX$22 -> 0 | AY25: ='Background Data'!AK90/AY$22 -> 0 | ... BD25: ='Background Data'!AP90/BD$22 -> 0.018968872 | CF25: 2010
AJ26: Hybrid electric | AR26: ='Background Data'!AD91/AR$22 -> 0 | AS26: ='Background Data'!AE91/AS$22 -> 0 | AT26: ='Background Data'!AF91/AT$22 -> 0 | AU26: ='Background Data'!AG91/AU$22 -> 0 | AV26: ='Background Data'!AH91/AV$22 -> 0 | AW26: ='Background Data'!AI91/AW$22 -> 0 | AX26: ='Background Data'!AJ91/AX$22 -> 0 | AY26: ='Background Data'!AK91/AY$22 -> 0 | ... BD26: ='Background Data'!AP91/BD$22 -> 0.076511523 | BG26: Fleet stock and flow estimation (in demand units) | CF26: 2011
AJ27: Plug-in hybrid electric | AR27: ='Background Data'!AD92/AR$22 -> 0 | AS27: ='Background Data'!AE92/AS$22 -> 0 | AT27: ='Background Data'!AF92/AT$22 -> 0 | AU27: ='Background Data'!AG92/AU$22 -> 0 | AV27: ='Background Data'!AH92/AV$22 -> 0 | AW27: ='Background Data'!AI92/AW$22 -> 1.6582648e-05 | AX27: ='Background Data'!AJ92/AX$22 -> 0.0088698578 | AY27: ='Background Data'!AK92/AY$22 -> 0.016076284 | ... BD27: ='Background Data'!AP92/BD$22 -> 0.023196648 | BG27: Mode | BH27: 2000 | BI27: 2001 | BJ27: 2002 | BK27: 2003 | BL27: 2004 | BM27: 2005 | BN27: 2006 | BO27: 2007 | BP27: 2008 | BQ27: 2009 | BR27: 2010 | BS27: 2011 | BT27: 2012 | BU27: 2013 | BV27: 2014 | BW27: 2015 | BX27: 2016 | BY27: 2017 | BZ27: 2018 | CA27: 2019 | CB27: 2020 | CC27: % of 2020 demand | CF27: 2012
AJ28: Medium Trucks | AK28: (StatCan, 2023) Table: 23-10-0308-01 | AX28: ='Background Data'!AR74 -> 122905 | AY28: ='Background Data'!AS74 -> 125671 | AZ28: ='Background Data'!AT74 -> 128102 | BA28: ='Background Data'!AU74 -> 138081 | BB28: ='Background Data'!AV74 -> 152693 | BC28: ='Background Data'!AW74 -> 148436 | BD28: ='Background Data'!AX74 -> 147657 | BG28: Passenger airplane | CF28: 2013
AJ29: Gasoline | AL29: =1-AL30 -> 0.4 | AM29: =1-AM30 -> 0.4 | AN29: =1-AN30 -> 0.4 | AO29: =1-AO30 -> 0.4 | AP29: =1-AP30 -> 0.4 | AQ29: =1-AQ30 -> 0.4 | AR29: =1-AR30 -> 0.4 | AS29: =1-AS30 -> 0.4 | ... AW29: =1-AW30 -> 0.4 | AX29: ='Background Data'!AR75/AX$28 -> 0.36206013 | AY29: ='Background Data'!AS75/AY$28 -> 0.3726715 | AZ29: ='Background Data'!AT75/AZ$28 -> 0.38132113 | BA29: ='Background Data'!AU75/BA$28 -> 0.38728717 | BB29: ='Background Data'!AV75/BB$28 -> 0.38496198 | BC29: ='Background Data'!AW75/BC$28 -> 0.39681748 | BD29: ='Background Data'!AX75/BD$28 -> 0.40317086 | BG29: Estimated demand | BH29: ='Background Data'!C86/'Background Data'!C133 -> 34.360329 | BI29: ='Background Data'!D86/'Background Data'!D133 -> 31.904682 | BJ29: ='Background Data'!E86/'Background Data'!E133 -> 22.604161 | BK29: ='Background Data'!F86/'Background Data'!F133 -> 24.092497 | BL29: ='Background Data'!G86/'Background Data'!G133 -> 31.49742 | BM29: ='Background Data'!H86/'Background Data'!H133 -> 42.578942 | BN29: ='Background Data'!I86/'Background Data'!I133 -> 32.525633 | BO29: ='Background Data'!J86/'Background Data'!J133 -> 36.788464 | ... CB29: ='Background Data'!W86/'Background Data'!W133 -> 20.470676 | CF29: 2014
AJ30: Diesel | AL30: 0.6 | AM30: 0.6 | AN30: 0.6 | AO30: 0.6 | AP30: 0.6 | AQ30: 0.6 | AR30: 0.6 | AS30: 0.6 | AT30: 0.6 | AU30: 0.6 | AV30: 0.6 | AW30: 0.6 | AX30: ='Background Data'!AR76/AX$28 -> 0.63789919 | AY30: ='Background Data'!AS76/AY$28 -> 0.62729667 | AZ30: ='Background Data'!AT76/AZ$28 -> 0.61864764 | BA30: ='Background Data'!AU76/BA$28 -> 0.61266213 | BB30: ='Background Data'!AV76/BB$28 -> 0.61497253 | BC30: ='Background Data'!AW76/BC$28 -> 0.60310841 | BD30: ='Background Data'!AX76/BD$28 -> 0.59662596 | BG30: Linear retirement | BH30: =BH29*'Background Data'!$BD$31 -> 1.4316804 | BI30: =BI29*'Background Data'!$BD$31 -> 1.3293617 | BJ30: =BJ29*'Background Data'!$BD$31 -> 0.94184003 | BK30: =BK29*'Background Data'!$BD$31 -> 1.003854 | BL30: =BL29*'Background Data'!$BD$31 -> 1.3123925 | BM30: =BM29*'Background Data'!$BD$31 -> 1.7741226 | BN30: =BN29*'Background Data'!$BD$31 -> 1.3552347 | BO30: =BO29*'Background Data'!$BD$31 -> 1.5328527 | ... CB30: =CB29*'Background Data'!$BD$31 -> 0.85294483 | CF30: 2015
AJ31: Light Passenger Trucks | AK31: (StatCan, 2023) Table: 20-10-0021-01 | AR31: =AR10+AR16+AR22 -> 329779 | AS31: =AS10+AS16+AS22 -> 317690 | AT31: =AT10+AT16+AT22 -> 347875 | AU31: =AU10+AU16+AU22 -> 386329 | AV31: =AV10+AV16+AV22 -> 446940 | AW31: =AW10+AW16+AW22 -> 505914 | AX31: =AX10+AX16+AX22 -> 548179 | AY31: =AY10+AY16+AY22 -> 558012 | ... BD31: =BD10+BD16+BD22 -> 566481 | BG31: Est. new stock | BI31: =BI29-(BH29-BH30) -> -1.0239663 | BJ31: =BJ29-(BI29-BI30) -> -7.9711595 | BK31: =BK29-(BJ29-BJ30) -> 2.4301766 | BL31: =BL29-(BK29-BK30) -> 8.4087768 | BM31: =BM29-(BL29-BL30) -> 12.393915 | BN31: =BN29-(BM29-BM30) -> -8.2791868 | BO31: =BO29-(BN29-BN30) -> 5.618066 | BP31: =BP29-(BO29-BO30) -> 8.9683463 | ... CB31: =CB29-(CA29-CA30) -> -47.177502 | CC31: =SUMIF(BI31:CB31, ">0", BI31:CB31)/CA29 -> 1.271064 | CF31: 2016
AJ32: Gasoline | AL32: 0.95 | AM32: 0.95 | AN32: 0.95 | AO32: 0.95 | AP32: 0.95 | AQ32: 0.95 | AR32: =('Background Data'!AD74+'Background Data'!AD81+'Background Data'!AD88)/(AR$10+AR$16+AR$22) -> 0.96637142 | AS32: =('Background Data'!AE74+'Background Data'!AE81+'Background Data'!AE88)/(AS$10+AS$16+AS$22) -> 0.96194089 | AT32: =('Background Data'!AF74+'Background Data'!AF81+'Background Data'!AF88)/(AT$10+AT$16+AT$22) -> 0.95799641 | AU32: =('Background Data'!AG74+'Background Data'!AG81+'Background Data'!AG88)/(AU$10+AU$16+AU$22) -> 0.94820736 | AV32: =('Background Data'!AH74+'Background Data'!AH81+'Background Data'!AH88)/(AV$10+AV$16+AV$22) -> 0.94716741 | AW32: =('Background Data'!AI74+'Background Data'!AI81+'Background Data'!AI88)/(AW$10+AW$16+AW$22) -> 0.95022672 | AX32: =('Background Data'!AJ74+'Background Data'!AJ81+'Background Data'!AJ88)/(AX$10+AX$16+AX$22) -> 0.958457 | AY32: =('Background Data'!AK74+'Background Data'!AK81+'Background Data'!AK88)/(AY$10+AY$16+AY$22) -> 0.9478022 | ... BD32: =('Background Data'!AP74+'Background Data'!AP81+'Background Data'!AP88)/(BD$10+BD$16+BD$22) -> 0.80020866 | BE32: =1 - SUM(BD32:BD33)/SUM(AZ32:AZ33) -> 0.14681698 | BG32: Freight airplane | CF32: 2017
AJ33: Diesel | AL33: 0.03 | AM33: 0.03 | AN33: 0.03 | AO33: 0.03 | AP33: 0.03 | AQ33: 0.03 | AR33: =('Background Data'!AD75+'Background Data'!AD82+'Background Data'!AD89)/(AR$10+AR$16+AR$22) -> 0.030672056 | AS33: =('Background Data'!AE75+'Background Data'!AE82+'Background Data'!AE89)/(AS$10+AS$16+AS$22) -> 0.035002676 | AT33: =('Background Data'!AF75+'Background Data'!AF82+'Background Data'!AF89)/(AT$10+AT$16+AT$22) -> 0.039816026 | AU33: =('Background Data'!AG75+'Background Data'!AG82+'Background Data'!AG89)/(AU$10+AU$16+AU$22) -> 0.049328422 | AV33: =('Background Data'!AH75+'Background Data'!AH82+'Background Data'!AH89)/(AV$10+AV$16+AV$22) -> 0.050465387 | AW33: =('Background Data'!AI75+'Background Data'!AI82+'Background Data'!AI89)/(AW$10+AW$16+AW$22) -> 0.041949818 | AX33: =('Background Data'!AJ75+'Background Data'!AJ82+'Background Data'!AJ89)/(AX$10+AX$16+AX$22) -> 0.031236147 | AY33: =('Background Data'!AK75+'Background Data'!AK82+'Background Data'!AK89)/(AY$10+AY$16+AY$22) -> 0.037017125 | ... BD33: =('Background Data'!AP75+'Background Data'!AP82+'Background Data'!AP89)/(BD$10+BD$16+BD$22) -> 0.03939938 | BG33: Estimated demand | BH33: ='Background Data'!C87/'Background Data'!C134 -> 0.71092627 | BI33: ='Background Data'!D87/'Background Data'!D134 -> 0.62047248 | BJ33: ='Background Data'!E87/'Background Data'!E134 -> 0.45496306 | BK33: ='Background Data'!F87/'Background Data'!F134 -> 0.46098915 | BL33: ='Background Data'!G87/'Background Data'!G134 -> 0.57398482 | BM33: ='Background Data'!H87/'Background Data'!H134 -> 0.81283196 | BN33: ='Background Data'!I87/'Background Data'!I134 -> 0.55785607 | BO33: ='Background Data'!J87/'Background Data'!J134 -> 0.43074539 | ... CB33: ='Background Data'!W87/'Background Data'!W134 -> 0.77473367 | CF33: 2018
AJ34: Battery electric | AL34: 0 | AM34: 0 | AN34: 0 | AO34: 0 | AP34: 0 | AQ34: 0 | AR34: =('Background Data'!AD83+'Background Data'!AD90+'Background Data'!AD76)/(AR$10+AR$16+AR$22) -> 4.5485007e-05 | AS34: =('Background Data'!AE83+'Background Data'!AE90+'Background Data'!AE76)/(AS$10+AS$16+AS$22) -> 3.4624949e-05 | AT34: =('Background Data'!AF83+'Background Data'!AF90+'Background Data'!AF76)/(AT$10+AT$16+AT$22) -> 0 | AU34: =('Background Data'!AG83+'Background Data'!AG90+'Background Data'!AG76)/(AU$10+AU$16+AU$22) -> 3.882701e-05 | AV34: =('Background Data'!AH83+'Background Data'!AH90+'Background Data'!AH76)/(AV$10+AV$16+AV$22) -> 0.00013200877 | AW34: =('Background Data'!AI83+'Background Data'!AI90+'Background Data'!AI76)/(AW$10+AW$16+AW$22) -> 0.0010693517 | AX34: =('Background Data'!AJ83+'Background Data'!AJ90+'Background Data'!AJ76)/(AX$10+AX$16+AX$22) -> 0.0018807725 | AY34: =('Background Data'!AK83+'Background Data'!AK90+'Background Data'!AK76)/(AY$10+AY$16+AY$22) -> 0.0016182448 | ... BD34: =('Background Data'!AP83+'Background Data'!AP90+'Background Data'!AP76)/(BD$10+BD$16+BD$22) -> 0.049676865 | BG34: Linear retirement | BH34: =BH33*'Background Data'!$BD$31 -> 0.029621928 | BI34: =BI33*'Background Data'!$BD$31 -> 0.02585302 | BJ34: =BJ33*'Background Data'!$BD$31 -> 0.018956794 | BK34: =BK33*'Background Data'!$BD$31 -> 0.019207881 | BL34: =BL33*'Background Data'!$BD$31 -> 0.023916034 | BM34: =BM33*'Background Data'!$BD$31 -> 0.033867998 | BN34: =BN33*'Background Data'!$BD$31 -> 0.023244003 | BO34: =BO33*'Background Data'!$BD$31 -> 0.017947725 | ... CB34: =CB33*'Background Data'!$BD$31 -> 0.03228057 | CF34: 2019
AJ35: Hybrid electric | AL35: 0 | AM35: 0 | AN35: 0 | AO35: 0 | AP35: 0 | AQ35: 0 | AR35: =('Background Data'!AD77+'Background Data'!AD84+'Background Data'!AD91)/(AR$10+AR$16+AR$22) -> 0.0029110404 | AS35: =('Background Data'!AE77+'Background Data'!AE84+'Background Data'!AE91)/(AS$10+AS$16+AS$22) -> 0.0030218137 | AT35: =('Background Data'!AF77+'Background Data'!AF84+'Background Data'!AF91)/(AT$10+AT$16+AT$22) -> 0.0021875674 | AU35: =('Background Data'!AG77+'Background Data'!AG84+'Background Data'!AG91)/(AU$10+AU$16+AU$22) -> 0.0023917438 | AV35: =('Background Data'!AH77+'Background Data'!AH84+'Background Data'!AH91)/(AV$10+AV$16+AV$22) -> 0.0020114557 | AW35: =('Background Data'!AI77+'Background Data'!AI84+'Background Data'!AI91)/(AW$10+AW$16+AW$22) -> 0.0057677787 | AX35: =('Background Data'!AJ77+'Background Data'!AJ84+'Background Data'!AJ91)/(AX$10+AX$16+AX$22) -> 0.0066784755 | AY35: =('Background Data'!AK77+'Background Data'!AK84+'Background Data'!AK91)/(AY$10+AY$16+AY$22) -> 0.0081378178 | ... BD35: =('Background Data'!AP77+'Background Data'!AP84+'Background Data'!AP91)/(BD$10+BD$16+BD$22) -> 0.091879516 | BE35: =BD35/AZ35 - 1 -> 7.0303894 | BG35: Est. new stock | BI35: =BI33-(BH33-BH34) -> -0.060831864 | BJ35: =BJ33-(BI33-BI34) -> -0.1396564 | BK35: =BK33-(BJ33-BJ34) -> 0.024982882 | BL35: =BL33-(BK33-BK34) -> 0.13220355 | BM35: =BM33-(BL33-BL34) -> 0.26276318 | BN35: =BN33-(BM33-BM34) -> -0.2211079 | BO35: =BO33-(BN33-BN34) -> -0.10386667 | BP35: =BP33-(BO33-BO34) -> 0.069226305 | ... CB35: =CB33-(CA33-CA34) -> -0.14238774 | CC35: =SUMIF(BI35:CB35, ">0", BI35:CB35)/CA33 -> 1.3737558 | CF35: 2020
AJ36: Plug-in hybrid electric | AL36: 0 | AM36: 0 | AN36: 0 | AO36: 0 | AP36: 0 | AQ36: 0 | AR36: =('Background Data'!AD85+'Background Data'!AD92)/(AR$10+AR$16+AR$22) -> 0 | AS36: =('Background Data'!AE85+'Background Data'!AE92)/(AS$10+AS$16+AS$22) -> 0 | AT36: =('Background Data'!AF85+'Background Data'!AF92)/(AT$10+AT$16+AT$22) -> 0 | AU36: =('Background Data'!AG85+'Background Data'!AG92)/(AU$10+AU$16+AU$22) -> 3.3650075e-05 | AV36: =('Background Data'!AH85+'Background Data'!AH92)/(AV$10+AV$16+AV$22) -> 0.00022374368 | AW36: =('Background Data'!AI85+'Background Data'!AI92)/(AW$10+AW$16+AW$22) -> 0.00098633365 | AX36: =('Background Data'!AJ85+'Background Data'!AJ92)/(AX$10+AX$16+AX$22) -> 0.0017476043 | AY36: =('Background Data'!AK85+'Background Data'!AK92)/(AY$10+AY$16+AY$22) -> 0.0054246145 | ... BD36: =('Background Data'!AP85+'Background Data'!AP92)/(BD$10+BD$16+BD$22) -> 0.018835583 | BG36: Passenger rail | CF36: 2021
AJ37: Light Freight Trucks | AR37: =AR10+AR22 -> 132374 | AS37: =AS10+AS22 -> 118247 | AT37: =AT10+AT22 -> 132230 | AU37: =AU10+AU22 -> 142485 | AV37: =AV10+AV22 -> 162797 | AW37: =AW10+AW22 -> 187127 | AX37: =AX10+AX22 -> 202914 | AY37: =AY10+AY22 -> 189789 | ... BD37: =BD10+BD22 -> 154380 | BG37: Estimated demand | BH37: ='Background Data'!C88/'Background Data'!C135 -> 0.39191099 | BI37: ='Background Data'!D88/'Background Data'!D135 -> 0.37543435 | BJ37: ='Background Data'!E88/'Background Data'!E135 -> 0.39191487 | BK37: ='Background Data'!F88/'Background Data'!F135 -> 0.30574408 | BL37: ='Background Data'!G88/'Background Data'!G135 -> 0.33238694 | BM37: ='Background Data'!H88/'Background Data'!H135 -> 0.34874055 | BN37: ='Background Data'!I88/'Background Data'!I135 -> 0.30994271 | BO37: ='Background Data'!J88/'Background Data'!J135 -> 0.30205213 | ... CB37: ='Background Data'!W88/'Background Data'!W135 -> 0.049202172
AJ38: Gasoline | AL38: 0.95 | AM38: 0.95 | AN38: 0.95 | AO38: 0.95 | AP38: 0.95 | AQ38: 0.95 | AR38: =('Background Data'!AD74+'Background Data'!AD88)/(AR$10+AR$22) -> 0.94878904 | AS38: =('Background Data'!AE74+'Background Data'!AE88)/(AS$10+AS$22) -> 0.94664558 | AT38: =('Background Data'!AF74+'Background Data'!AF88)/(AT$10+AT$22) -> 0.94867277 | AU38: =('Background Data'!AG74+'Background Data'!AG88)/(AU$10+AU$22) -> 0.92750816 | AV38: =('Background Data'!AH74+'Background Data'!AH88)/(AV$10+AV$22) -> 0.91662623 | AW38: =('Background Data'!AI74+'Background Data'!AI88)/(AW$10+AW$22) -> 0.91001299 | AX38: =('Background Data'!AJ74+'Background Data'!AJ88)/(AX$10+AX$22) -> 0.92308564 | AY38: =('Background Data'!AK74+'Background Data'!AK88)/(AY$10+AY$22) -> 0.90097951 | ... BD38: =('Background Data'!AP74+'Background Data'!AP88)/(BD$10+BD$22) -> 0.80608887 | BE38: =1 - SUM(BD38:BD39)/SUM(AZ38:AZ39) -> 0.060651129 | BG38: Linear retirement | BH38: =BH37*'Background Data'!$BD$32 -> 0.0130637 | BI38: =BI37*'Background Data'!$BD$32 -> 0.012514478 | BJ38: =BJ37*'Background Data'!$BD$32 -> 0.013063829 | BK38: =BK37*'Background Data'!$BD$32 -> 0.010191469 | BL38: =BL37*'Background Data'!$BD$32 -> 0.011079565 | BM38: =BM37*'Background Data'!$BD$32 -> 0.011624685 | BN38: =BN37*'Background Data'!$BD$32 -> 0.010331424 | BO38: =BO37*'Background Data'!$BD$32 -> 0.010068404 | ... CB38: =CB37*'Background Data'!$BD$32 -> 0.0016400724
AJ39: Diesel | AL39: 0.04 | AM39: 0.04 | AN39: 0.04 | AO39: 0.04 | AP39: 0.04 | AQ39: 0.04 | AR39: =('Background Data'!AD75+'Background Data'!AD89)/(AR$10+AR$22) -> 0.050591506 | AS39: =('Background Data'!AE75+'Background Data'!AE89)/(AS$10+AS$22) -> 0.052762438 | AT39: =('Background Data'!AF75+'Background Data'!AF89)/(AT$10+AT$22) -> 0.05125917 | AU39: =('Background Data'!AG75+'Background Data'!AG89)/(AU$10+AU$22) -> 0.072484823 | AV39: =('Background Data'!AH75+'Background Data'!AH89)/(AV$10+AV$22) -> 0.083373772 | AW39: =('Background Data'!AI75+'Background Data'!AI89)/(AW$10+AW$22) -> 0.08998167 | AX39: =('Background Data'!AJ75+'Background Data'!AJ89)/(AX$10+AX$22) -> 0.074341839 | AY39: =('Background Data'!AK75+'Background Data'!AK89)/(AY$10+AY$22) -> 0.094410108 | ... BD39: =('Background Data'!AP75+'Background Data'!AP89)/(BD$10+BD$22) -> 0.13281513 | BG39: Est. new stock | BI39: =BI37-(BH37-BH38) -> -0.0034129392 | BJ39: =BJ37-(BI37-BI38) -> 0.028995001 | BK39: =BK37-(BJ37-BJ38) -> -0.073106965 | BL39: =BL37-(BK37-BK38) -> 0.036834328 | BM39: =BM37-(BL37-BL38) -> 0.027433181 | BN39: =BN37-(BM37-BM38) -> -0.027173159 | BO39: =BO37-(BN37-BN38) -> 0.0024408414 | BP39: =BP37-(BO37-BO38) -> 0.017684556 | ... CB39: =CB37-(CA37-CA38) -> -0.28893492 | CC39: =SUMIF(BI39:CB39, ">0", BI39:CB39)/CA37 -> 0.97616904
AJ40: Battery electric | AL40: 0 | AM40: 0 | AN40: 0 | AO40: 0 | AP40: 0 | AQ40: 0 | AR40: =('Background Data'!AD76+'Background Data'!AD90)/(AR$10+AR$22) -> 0.0001133153 | AS40: =('Background Data'!AE76+'Background Data'!AE90)/(AS$10+AS$22) -> 9.3025616e-05 | AT40: =('Background Data'!AF76+'Background Data'!AF90)/(AT$10+AT$22) -> 0 | AU40: =('Background Data'!AG76+'Background Data'!AG90)/(AU$10+AU$22) -> 0 | AV40: =('Background Data'!AH76+'Background Data'!AH90)/(AV$10+AV$22) -> 0 | AW40: =('Background Data'!AI76+'Background Data'!AI90)/(AW$10+AW$22) -> 0 | AX40: =('Background Data'!AJ76+'Background Data'!AJ90)/(AX$10+AX$22) -> 0 | AY40: =('Background Data'!AK76+'Background Data'!AK90)/(AY$10+AY$22) -> 0 | ... BD40: =('Background Data'!AP76+'Background Data'!AP90)/(BD$10+BD$22) -> 0.015001943 | BG40: Freight rail
AJ41: Hybrid electric | AL41: 0 | AM41: 0 | AN41: 0 | AO41: 0 | AP41: 0 | AQ41: 0 | AR41: =('Background Data'!AD77+'Background Data'!AD91)/(AR$10+AR$22) -> 0.00050614169 | AS41: =('Background Data'!AE77+'Background Data'!AE91)/(AS$10+AS$22) -> 0.00049895558 | AT41: =('Background Data'!AF77+'Background Data'!AF91)/(AT$10+AT$22) -> 6.8063223e-05 | AU41: =('Background Data'!AG77+'Background Data'!AG91)/(AU$10+AU$22) -> 7.0182826e-06 | AV41: =('Background Data'!AH77+'Background Data'!AH91)/(AV$10+AV$22) -> 0 | AW41: =('Background Data'!AI77+'Background Data'!AI91)/(AW$10+AW$22) -> 0 | AX41: =('Background Data'!AJ77+'Background Data'!AJ91)/(AX$10+AX$22) -> 0 | AY41: =('Background Data'!AK77+'Background Data'!AK91)/(AY$10+AY$22) -> 0 | ... BD41: =('Background Data'!AP77+'Background Data'!AP91)/(BD$10+BD$22) -> 0.042077989 | BG41: Estimated demand | BH41: ='Background Data'!C89/'Background Data'!C136 -> 81.623993 | BI41: ='Background Data'!D89/'Background Data'!D136 -> 78.132625 | BJ41: ='Background Data'!E89/'Background Data'!E136 -> 77.994611 | BK41: ='Background Data'!F89/'Background Data'!F136 -> 67.874006 | BL41: ='Background Data'!G89/'Background Data'!G136 -> 79.282881 | BM41: ='Background Data'!H89/'Background Data'!H136 -> 83.06337 | BN41: ='Background Data'!I89/'Background Data'!I136 -> 75.318126 | BO41: ='Background Data'!J89/'Background Data'!J136 -> 74.594366 | ... CB41: ='Background Data'!W89/'Background Data'!W136 -> 87.834899
AJ42: Plug-in hybrid electric | AL42: 0 | AM42: 0 | AN42: 0 | AO42: 0 | AP42: 0 | AQ42: 0 | AR42: =('Background Data'!AD78+'Background Data'!AD92)/(AR$10+AR$22) -> 0 | AS42: =('Background Data'!AE78+'Background Data'!AE92)/(AS$10+AS$22) -> 0 | AT42: =('Background Data'!AF78+'Background Data'!AF92)/(AT$10+AT$22) -> 0 | AU42: =('Background Data'!AG78+'Background Data'!AG92)/(AU$10+AU$22) -> 0 | AV42: =('Background Data'!AH78+'Background Data'!AH92)/(AV$10+AV$22) -> 0 | AW42: =('Background Data'!AI78+'Background Data'!AI92)/(AW$10+AW$22) -> 5.3439643e-06 | AX42: =('Background Data'!AJ78+'Background Data'!AJ92)/(AX$10+AX$22) -> 0.0025725184 | AY42: =('Background Data'!AK78+'Background Data'!AK92)/(AY$10+AY$22) -> 0.0046103831 | ... BD42: =('Background Data'!AP78+'Background Data'!AP92)/(BD$10+BD$22) -> 0.0040160643 | BG42: Linear retirement | BH42: =BH41*'Background Data'!$BD$32 -> 2.7207998 | BI42: =BI41*'Background Data'!$BD$32 -> 2.6044208 | BJ42: =BJ41*'Background Data'!$BD$32 -> 2.5998204 | BK42: =BK41*'Background Data'!$BD$32 -> 2.2624669 | BL42: =BL41*'Background Data'!$BD$32 -> 2.6427627 | BM42: =BM41*'Background Data'!$BD$32 -> 2.768779 | BN42: =BN41*'Background Data'!$BD$32 -> 2.5106042 | BO42: =BO41*'Background Data'!$BD$32 -> 2.4864789 | ... CB42: =CB41*'Background Data'!$BD$32 -> 2.92783
BG43: Est. new stock | BI43: =BI41-(BH41-BH42) -> -0.77056841 | BJ43: =BJ41-(BI41-BI42) -> 2.4664069 | BK43: =BK41-(BJ41-BJ42) -> -7.5207846 | BL43: =BL41-(BK41-BK42) -> 13.671342 | BM43: =BM41-(BL41-BL42) -> 6.4232511 | BN43: =BN41-(BM41-BM42) -> -4.9764644 | BO43: =BO41-(BN41-BN42) -> 1.7868439 | BP43: =BP41-(BO41-BO42) -> -5.210744 | ... CB43: =CB41-(CA41-CA42) -> -0.40686748 | CC43: =SUMIF(BI43:CB43, ">0", BI43:CB43)/CA41 -> 1.0036884
AJ44: Bus vehicle class activity estimation in Ontario (bkm) | BG44: Marine freight - MDO
AJ45: Vehicle type | AK45: Downscaling Source | AL45: 2005 | AM45: 2006 | AN45: 2007 | AO45: 2008 | AP45: 2009 | AQ45: 2010 | AR45: 2011 | AS45: 2012 | AT45: 2013 | AU45: 2014 | AV45: 2015 | AW45: 2016 | AX45: 2017 | AY45: 2018 | AZ45: 2019 | BA45: 2020 | BB45: 2021 | BG45: Estimated demand | BH45: ='Background Data'!C91/('Background Data'!C137*HFO_MDO) -> 8.9753255 | BI45: ='Background Data'!D91/('Background Data'!D137*HFO_MDO) -> 6.7994501 | BJ45: ='Background Data'!E91/('Background Data'!E137*HFO_MDO) -> 8.2604236 | BK45: ='Background Data'!F91/('Background Data'!F137*HFO_MDO) -> 9.4749664 | BL45: ='Background Data'!G91/('Background Data'!G137*HFO_MDO) -> 8.5280252 | BM45: ='Background Data'!H91/('Background Data'!H137*HFO_MDO) -> 9.0080446 | BN45: ='Background Data'!I91/('Background Data'!I137*HFO_MDO) -> 10.043178 | BO45: ='Background Data'!J91/('Background Data'!J137*HFO_MDO) -> 6.3480937 | ... CB45: ='Background Data'!W91/('Background Data'!W137*HFO_MDO) -> 2.020402
AJ46: School Buses | AK46: (GREET2023) Fuel Economy input data | AL46: Lifetime of buses is assumed to be 11 years for CNG fuel type and 13 years for the rest of technologies, sourced from StatCan Table: 34-10-0254-01. Fuel type distributions are estimated based on the activity per year, calculated with the energy use and efficiencies. | AO46: =SUM(AO47:AO49) -> #REF! | AP46: =SUM(AP47:AP49) -> #REF! | AQ46: =SUM(AQ47:AQ49) -> #REF! | AR46: =SUM(AR47:AR49) -> #REF! | AS46: =SUM(AS47:AS49) -> #REF! | AT46: =SUM(AT47:AT49) -> #REF! | AU46: =SUM(AU47:AU49) -> #REF! | AV46: =SUM(AV47:AV49) -> #REF! | ... BB46: =SUM(BB47:BB49) -> #REF! | BG46: Linear retirement | BH46: =BH45*'Background Data'!$BD$33 -> 0.29917752 | BI46: =BI45*'Background Data'!$BD$33 -> 0.22664834 | BJ46: =BJ45*'Background Data'!$BD$33 -> 0.27534745 | BK46: =BK45*'Background Data'!$BD$33 -> 0.31583221 | BL46: =BL45*'Background Data'!$BD$33 -> 0.28426751 | BM46: =BM45*'Background Data'!$BD$33 -> 0.30026815 | BN46: =BN45*'Background Data'!$BD$33 -> 0.3347726 | BO46: =BO45*'Background Data'!$BD$33 -> 0.21160312 | ... CB46: =CB45*'Background Data'!$BD$33 -> 0.067346733
AJ47: Gasoline | AO47: =Efficiency!#REF!*'Background Data'!K70 -> #REF! | AP47: =Efficiency!#REF!*'Background Data'!L70 -> #REF! | AQ47: =Efficiency!#REF!*'Background Data'!M70 -> #REF! | AR47: =Efficiency!#REF!*'Background Data'!N70 -> #REF! | AS47: =Efficiency!#REF!*'Background Data'!O70 -> #REF! | AT47: =Efficiency!#REF!*'Background Data'!P70 -> #REF! | AU47: =Efficiency!#REF!*'Background Data'!Q70 -> #REF! | AV47: =Efficiency!#REF!*'Background Data'!R70 -> #REF! | ... BB47: =Efficiency!#REF!*'Background Data'!X70 -> #REF! | BG47: Est. new stock | BI47: =BI45-(BH45-BH46) -> -1.8766979 | BJ47: =BJ45-(BI45-BI46) -> 1.6876217 | BK47: =BK45-(BJ45-BJ46) -> 1.4898903 | BL47: =BL45-(BK45-BK46) -> -0.63110905 | BM47: =BM45-(BL45-BL46) -> 0.76428697 | BN47: =BN45-(BM45-BM46) -> 1.3354014 | BO47: =BO45-(BN45-BN46) -> -3.3603116 | BP47: =BP45-(BO45-BO46) -> 0.99220817 | ... CB47: =CB45-(CA45-CA46) -> 0.85822308 | CC47: =SUMIF(BI47:CB47, ">0", BI47:CB47)/CA45 -> 10.085253
AJ48: Diesel | AO48: =Efficiency!#REF!*'Background Data'!K71 -> #REF! | AP48: =Efficiency!#REF!*'Background Data'!L71 -> #REF! | AQ48: =Efficiency!#REF!*'Background Data'!M71 -> #REF! | AR48: =Efficiency!#REF!*'Background Data'!N71 -> #REF! | AS48: =Efficiency!#REF!*'Background Data'!O71 -> #REF! | AT48: =Efficiency!#REF!*'Background Data'!P71 -> #REF! | AU48: =Efficiency!#REF!*'Background Data'!Q71 -> #REF! | AV48: =Efficiency!#REF!*'Background Data'!R71 -> #REF! | ... BB48: =Efficiency!#REF!*'Background Data'!X71 -> #REF! | BG48: Marine freight - HFO
AJ49: CNG | AO49: =Efficiency!#REF!*'Background Data'!K69 -> #REF! | AP49: =Efficiency!#REF!*'Background Data'!L69 -> #REF! | AQ49: =Efficiency!#REF!*'Background Data'!M69 -> #REF! | AR49: =Efficiency!#REF!*'Background Data'!N69 -> #REF! | AS49: =Efficiency!#REF!*'Background Data'!O69 -> #REF! | AT49: =Efficiency!#REF!*'Background Data'!P69 -> #REF! | AU49: =Efficiency!#REF!*'Background Data'!Q69 -> #REF! | AV49: =Efficiency!#REF!*'Background Data'!R69 -> #REF! | ... BB49: =Efficiency!#REF!*'Background Data'!X69 -> #REF! | BG49: Estimated demand | BH49: ='Background Data'!C92/'Background Data'!C137 -> 19.906642 | BI49: ='Background Data'!D92/'Background Data'!D137 -> 20.677249 | BJ49: ='Background Data'!E92/'Background Data'!E137 -> 21.035515 | BK49: ='Background Data'!F92/'Background Data'!F137 -> 22.581508 | BL49: ='Background Data'!G92/'Background Data'!G137 -> 22.285269 | BM49: ='Background Data'!H92/'Background Data'!H137 -> 20.980464 | BN49: ='Background Data'!I92/'Background Data'!I137 -> 23.211201 | BO49: ='Background Data'!J92/'Background Data'!J137 -> 18.401948 | ... CB49: ='Background Data'!W92/'Background Data'!W137 -> 36.734148
AJ50: Urban Transit Buses | AO50: =SUM(AO51:AO54) -> #REF! | AP50: =SUM(AP51:AP54) -> #REF! | AQ50: =SUM(AQ51:AQ54) -> #REF! | AR50: =SUM(AR51:AR54) -> #REF! | AS50: =SUM(AS51:AS54) -> #REF! | AT50: =SUM(AT51:AT54) -> #REF! | AU50: =SUM(AU51:AU54) -> #REF! | AV50: =SUM(AV51:AV54) -> #REF! | ... BB50: =SUM(BB51:BB54) -> #REF! | BG50: Linear retirement | BH50: =BH49*'Background Data'!$BD$33 -> 0.66355473 | BI50: =BI49*'Background Data'!$BD$33 -> 0.68924164 | BJ50: =BJ49*'Background Data'!$BD$33 -> 0.70118384 | BK50: =BK49*'Background Data'!$BD$33 -> 0.75271695 | BL50: =BL49*'Background Data'!$BD$33 -> 0.7428423 | BM50: =BM49*'Background Data'!$BD$33 -> 0.6993488 | BN50: =BN49*'Background Data'!$BD$33 -> 0.77370669 | BO50: =BO49*'Background Data'!$BD$33 -> 0.61339826 | ... CB50: =CB49*'Background Data'!$BD$33 -> 1.2244716
AJ51: Gasoline | AO51: =Efficiency!#REF!*'Background Data'!K76 -> #REF! | AP51: =Efficiency!#REF!*'Background Data'!L76 -> #REF! | AQ51: =Efficiency!#REF!*'Background Data'!M76 -> #REF! | AR51: =Efficiency!#REF!*'Background Data'!N76 -> #REF! | AS51: =Efficiency!#REF!*'Background Data'!O76 -> #REF! | AT51: =Efficiency!#REF!*'Background Data'!P76 -> #REF! | AU51: =Efficiency!#REF!*'Background Data'!Q76 -> #REF! | AV51: =Efficiency!#REF!*'Background Data'!R76 -> #REF! | ... BB51: =Efficiency!#REF!*'Background Data'!X76 -> #REF! | BG51: Est. new stock | BI51: =BI49-(BH49-BH50) -> 1.434162 | BJ51: =BJ49-(BI49-BI50) -> 1.0475074 | BK51: =BK49-(BJ49-BJ50) -> 2.2471771 | BL51: =BL49-(BK49-BK50) -> 0.45647772 | BM51: =BM49-(BL49-BL50) -> -0.56196288 | BN51: =BN49-(BM49-BM50) -> 2.9300854 | BO51: =BO49-(BN49-BN50) -> -4.0355462 | BP51: =BP49-(BO49-BO50) -> 0.07313576 | ... CB51: =CB49-(CA49-CA50) -> -7.6051402 | CC51: =SUMIF(BI51:CB51, ">0", BI51:CB51)/CA49 -> 1.2283594
AJ52: Diesel | AO52: =Efficiency!#REF!*'Background Data'!K77 -> #REF! | AP52: =Efficiency!#REF!*'Background Data'!L77 -> #REF! | AQ52: =Efficiency!#REF!*'Background Data'!M77 -> #REF! | AR52: =Efficiency!#REF!*'Background Data'!N77 -> #REF! | AS52: =Efficiency!#REF!*'Background Data'!O77 -> #REF! | AT52: =Efficiency!#REF!*'Background Data'!P77 -> #REF! | AU52: =Efficiency!#REF!*'Background Data'!Q77 -> #REF! | AV52: =Efficiency!#REF!*'Background Data'!R77 -> #REF! | ... BB52: =Efficiency!#REF!*'Background Data'!X77 -> #REF!
AJ53: CNG | AO53: =Efficiency!#REF!*'Background Data'!K75 -> #REF! | AP53: =Efficiency!#REF!*'Background Data'!L75 -> #REF! | AQ53: =Efficiency!#REF!*'Background Data'!M75 -> #REF! | AR53: =Efficiency!#REF!*'Background Data'!N75 -> #REF! | AS53: =Efficiency!#REF!*'Background Data'!O75 -> #REF! | AT53: =Efficiency!#REF!*'Background Data'!P75 -> #REF! | AU53: =Efficiency!#REF!*'Background Data'!Q75 -> #REF! | AV53: =Efficiency!#REF!*'Background Data'!R75 -> #REF! | ... BB53: =Efficiency!#REF!*'Background Data'!X75 -> #REF!
AJ54: Electricity | AO54: =Efficiency!#REF!*'Background Data'!K74 -> #REF! | AP54: =Efficiency!#REF!*'Background Data'!L74 -> #REF! | AQ54: =Efficiency!#REF!*'Background Data'!M74 -> #REF! | AR54: =Efficiency!#REF!*'Background Data'!N74 -> #REF! | AS54: =Efficiency!#REF!*'Background Data'!O74 -> #REF! | AT54: =Efficiency!#REF!*'Background Data'!P74 -> #REF! | AU54: =Efficiency!#REF!*'Background Data'!Q74 -> #REF! | AV54: =Efficiency!#REF!*'Background Data'!R74 -> #REF! | ... BB54: =Efficiency!#REF!*'Background Data'!X74 -> #REF!
AJ55: Inter-city Buses | AO55: =SUM(AO56:AO57) -> #REF! | AP55: =SUM(AP56:AP57) -> #REF! | AQ55: =SUM(AQ56:AQ57) -> #REF! | AR55: =SUM(AR56:AR57) -> #REF! | AS55: =SUM(AS56:AS57) -> #REF! | AT55: =SUM(AT56:AT57) -> #REF! | AU55: =SUM(AU56:AU57) -> #REF! | AV55: =SUM(AV56:AV57) -> #REF! | ... BB55: =SUM(BB56:BB57) -> #REF!
AJ56: Gasoline | AO56: ='Background Data'!K81*Efficiency!#REF! -> #REF! | AP56: ='Background Data'!L81*Efficiency!#REF! -> #REF! | AQ56: ='Background Data'!M81*Efficiency!#REF! -> #REF! | AR56: ='Background Data'!N81*Efficiency!#REF! -> #REF! | AS56: ='Background Data'!O81*Efficiency!#REF! -> #REF! | AT56: ='Background Data'!P81*Efficiency!#REF! -> #REF! | AU56: ='Background Data'!Q81*Efficiency!#REF! -> #REF! | AV56: ='Background Data'!R81*Efficiency!#REF! -> #REF! | ... BB56: ='Background Data'!X81*Efficiency!#REF! -> #REF!
AJ57: Diesel | AO57: ='Background Data'!K82*Efficiency!#REF! -> #REF! | AP57: ='Background Data'!L82*Efficiency!#REF! -> #REF! | AQ57: ='Background Data'!M82*Efficiency!#REF! -> #REF! | AR57: ='Background Data'!N82*Efficiency!#REF! -> #REF! | AS57: ='Background Data'!O82*Efficiency!#REF! -> #REF! | AT57: ='Background Data'!P82*Efficiency!#REF! -> #REF! | AU57: ='Background Data'!Q82*Efficiency!#REF! -> #REF! | AV57: ='Background Data'!R82*Efficiency!#REF! -> #REF! | ... BB57: ='Background Data'!X82*Efficiency!#REF! -> #REF!
AJ59: 2021 Min Capacity Constraint (k units) - based on 2021 sales and 2023 fuel type shares | AN59: Vehicle sales per year in ON (k units) | AR59: Historical fleet sales growth rates (2000-2020) | AY59: Vehicle fleet stock per year in ON (k units) | BC59: Historical fleet stock growth rates (2000-2020)
AJ60: Vehicle class | AK60: 2021 | AL60: 2021 (rounded) | AN60: Vehicle class | AO60: Max sales | AP60: Avg sales | AR60: Vehicle class | AS60: Annual | AT60: CAGR (5-year) | AU60: CAGR (4-year) | AY60: Vehicle class | AZ60: Max stock | BA60: Avg stock | BC60: Vehicle class | BD60: Annual | BE60: CAGR (5-year) | BF60: CAGR (4-year)
AJ61: Cars | AN61: Cars | AO61: =MAX('Background Data'!C5:X5) -> 368.369 | AP61: =AVERAGE('Background Data'!R5:V5) -> 259.6304 | AQ61: =AP61*0.001 -> 0.2596304 | AR61: Cars | AS61: {=AVERAGE('Background Data'!N5:V5/'Background Data'!M5:U5)} -> 0.98656875 | AT61: =(('Background Data'!V5*AS61)/'Background Data'!C5)^(1/4) -> 0.88264625 | AU61: =('Background Data'!V5/'Background Data'!G5)^(1/4) -> 0.9270537 | AY61: Cars | AZ61: =MAX('Background Data'!C11:X11) -> 4689.124 | BA61: =AVERAGE('Background Data'!R11:W11) -> 4527.7965 | BB61: =BA61*0.001 -> 4.5277965 | BC61: Cars | BD61: {=AVERAGE('Background Data'!N11:V11/'Background Data'!M11:U11)} -> 1.0083267 | BE61: =(('Background Data'!V11*BD61)/'Background Data'!C11)^(1/4) -> 1.0311341 | BF61: =('Background Data'!V11/'Background Data'!G11)^(1/4) -> 1.0197585
AJ62: Gasoline | AK62: ='Background Data'!$X$5*BD5 -> 128.85704 | AL62: =ROUND(AK62, 1) -> 128.9 | AN62: Light Passenger Trucks | AO62: =MAX('Background Data'!C6:X6) -> 413.919 | AP62: =AVERAGE('Background Data'!R6:V6) -> 384.2008 | AQ62: =AP62*0.001 -> 0.3842008 | AR62: Light Passenger Trucks | AS62: {=AVERAGE('Background Data'!N6:V6/'Background Data'!M6:U6)} -> 1.0682485 | AT62: =(('Background Data'!V6*AS62)/'Background Data'!C6)^(1/4) -> 1.2085377 | AU62: =('Background Data'!V6/'Background Data'!G6)^(1/4) -> 1.1999695 | AY62: Light Passenger Trucks | AZ62: =MAX('Background Data'!C12:X12) -> 4177.325 | BA62: =AVERAGE('Background Data'!R12:W12) -> 3730.6113 | BB62: =BA62*0.001 -> 3.7306113 | BC62: Light Passenger Trucks | BD62: {=AVERAGE('Background Data'!N12:V12/'Background Data'!M12:U12)} -> 1.0585644 | BE62: =(('Background Data'!V12*BD62)/'Background Data'!C12)^(1/4) -> 1.2729968 | BF62: =('Background Data'!V12/'Background Data'!G12)^(1/4) -> 1.1990306
AJ63: Diesel | AK63: ='Background Data'!$X$5*BD6 -> 0 | AL63: =ROUND(AK63, 1) -> 0 | AN63: Light Freight Trucks | AO63: =MAX('Background Data'!C7:X7) -> 115.151 | AP63: =AVERAGE('Background Data'!R7:V7) -> 107.1094 | AQ63: =AP63*0.001 -> 0.1071094 | AR63: Light Freight Trucks | AS63: {=AVERAGE('Background Data'!N7:V7/'Background Data'!M7:U7)} -> 1.0680685 | AT63: =(('Background Data'!V7*AS63)/'Background Data'!C7)^(1/4) -> 1.2027669 | AU63: =('Background Data'!V7/'Background Data'!G7)^(1/4) -> 1.1991637 | AY63: Light Freight Trucks | AZ63: =MAX('Background Data'!C13:X13) -> 1161.293 | BA63: =AVERAGE('Background Data'!R13:W13) -> 1039.4625 | BB63: =BA63*0.001 -> 1.0394625 | BC63: Light Freight Trucks | BD63: {=AVERAGE('Background Data'!N13:V13/'Background Data'!M13:U13)} -> 1.0583621 | BE63: =(('Background Data'!V13*BD63)/'Background Data'!C13)^(1/4) -> 1.2669068 | BF63: =('Background Data'!V13/'Background Data'!G13)^(1/4) -> 1.1982255
AJ64: Battery electric | AK64: ='Background Data'!$X$5*BD7 -> 14.716723 | AL64: =ROUND(AK64, 1) -> 14.7 | AN64: Medium Trucks | AO64: =MAX('Background Data'!C8:X8) -> 46.912 | AP64: =AVERAGE('Background Data'!R8:V8) -> 40.6016 | AQ64: =AP64*0.001 -> 0.0406016 | AR64: Medium Trucks | AS64: {=AVERAGE('Background Data'!N8:V8/'Background Data'!M8:U8)} -> 1.0612786 | AT64: =(('Background Data'!V8*AS64)/'Background Data'!C8)^(1/4) -> 1.1827206 | AU64: =('Background Data'!V8/'Background Data'!G8)^(1/4) -> 1.1879326 | AY64: Medium Trucks | AZ64: =MAX('Background Data'!C14:X14) -> 422.618 | BA64: =AVERAGE('Background Data'!R14:W14) -> 390.9375 | BB64: =BA64*0.001 -> 0.3909375 | BC64: Medium Trucks | BD64: {=AVERAGE('Background Data'!N14:V14/'Background Data'!M14:U14)} -> 1.0293658 | BE64: =(('Background Data'!V14*BD64)/'Background Data'!C14)^(1/4) -> 1.1983414 | BF64: =('Background Data'!V14/'Background Data'!G14)^(1/4) -> 1.1520929
AJ65: Hybrid electric | AK65: ='Background Data'!$X$5*BD8 -> 15.175309 | AL65: =ROUND(AK65, 1) -> 15.2 | AN65: Heavy Trucks | AO65: =MAX('Background Data'!C9:X9) -> 14.052 | AP65: =AVERAGE('Background Data'!R9:V9) -> 11.939 | AQ65: =AP65*0.001 -> 0.011939 | AR65: Heavy Trucks | AS65: {=AVERAGE('Background Data'!N9:V9/'Background Data'!M9:U9)} -> 1.0942954 | AT65: =(('Background Data'!V9*AS65)/'Background Data'!C9)^(1/4) -> 1.0625146 | AU65: =('Background Data'!V9/'Background Data'!G9)^(1/4) -> 1.0481034 | AY65: Heavy Trucks | AZ65: =MAX('Background Data'!C15:X15) -> 148.098 | BA65: =AVERAGE('Background Data'!R15:W15) -> 128.21733 | BB65: =BA65*0.001 -> 0.12821733 | BC65: Heavy Trucks | BD65: {=AVERAGE('Background Data'!N15:V15/'Background Data'!M15:U15)} -> 1.0197721 | BE65: =(('Background Data'!V15*BD65)/'Background Data'!C15)^(1/4) -> 1.0801835 | BF65: =('Background Data'!V15/'Background Data'!G15)^(1/4) -> 1.0536094
AJ66: Plug-in hybrid electric | AK66: ='Background Data'!$X$5*BD9 -> 1.194929 | AL66: =ROUND(AK66, 1) -> 1.2
AJ67: Light Passenger Trucks
AJ68: Gasoline | AK68: ='Background Data'!$X$6*BD32 -> 292.53148 | AL68: =ROUND(AK68, 1) -> 292.5 | AN68: CANOE Vanilla v3 net capacity by vehicle class (k units) - to represent the market pull for technology growth constraint formulation
AJ69: Diesel | AK69: ='Background Data'!$X$6*BD33 -> 14.403192 | AL69: =ROUND(AK69, 1) -> 14.4 | AN69: Vehicle class | AO69: 2021 | AP69: 2025 | AQ69: 2030 | AR69: 2035 | AS69: 2040 | AT69: 2045 | AU69: 2050
AJ70: Battery electric | AK70: ='Background Data'!$X$6*BD34 -> 18.160322 | AL70: =ROUND(AK70, 1) -> 18.2 | AN70: Cars | AO70: 4271.4806 | AP70: 5644.0668 | AQ70: 5701.7853 | AR70: 6157.3914 | AS70: 6473.9099 | AT70: 7120.6518 | AU70: 7510.7558
AJ71: Hybrid electric | AK71: ='Background Data'!$X$6*BD35 -> 33.588303 | AL71: =ROUND(AK71, 1) -> 33.6 | AN71: Light Passenger Trucks | AO71: 4112.3768 | AP71: 5461.9251 | AQ71: 5930.8507 | AR71: 6727.212 | AS71: 6689.3596 | AT71: 7021.8978 | AU71: 8114.6414
AJ72: Plug-in hybrid electric | AK72: ='Background Data'!$X$6*BD36 -> 6.8857053 | AL72: =ROUND(AK72, 1) -> 6.9 | AN72: Light Freight Trucks | AO72: 1149.2282 | AP72: 1500.698 | AQ72: 1579.0152 | AR72: 1927.7705 | AS72: 1830.9603 | AT72: 1892.8558 | AU72: 2285.3227
AJ73: Light Freight Trucks | AN73: Medium Trucks | AO73: 432.7472 | AP73: 494.75147 | AQ73: 530.02353 | AR73: 608.17328 | AS73: 595.21845 | AT73: 644.84678 | AU73: 714.80373
AJ74: Gasoline | AK74: ='Background Data'!$X$7*BD38 -> 82.346009 | AL74: =ROUND(AK74, 1) -> 82.3 | AN74: Heavy Trucks | AO74: 150.52779 | AP74: 153.33294 | AQ74: 159.61207 | AR74: 176.24472 | AS74: 177.53503 | AT74: 193.55123 | AU74: 210.2877
AJ75: Diesel | AK75: ='Background Data'!$X$7*BD39 -> 13.56773 | AL75: =ROUND(AK75, 1) -> 13.6
AJ76: Battery electric | AK76: ='Background Data'!$X$7*BD40 -> 1.5325235 | AL76: =ROUND(AK76, 1) -> 1.5
AJ77: Hybrid electric | AK77: ='Background Data'!$X$7*BD41 -> 4.298477 | AL77: =ROUND(AK77, 1) -> 4.3
AJ78: Plug-in hybrid electric | AK78: ='Background Data'!$X$7*BD42 -> 0.41026104 | AL78: =ROUND(AK78, 1) -> 0.4
AJ79: Medium Trucks
AJ80: Gasoline | AK80: ='Background Data'!$X$8*BB29 -> 18.059337 | AL80: =ROUND(AK80, 1) -> 18.1
AJ81: Diesel | AK81: ='Background Data'!$X$8*BB30 -> 28.849591 | AL81: =ROUND(AK81, 1) -> 28.8
AJ82: Heavy Trucks - Diesel | AK82: ='Background Data'!X9 -> 12.577 | AL82: =ROUND(AK82, 1) -> 12.6
AJ84: 2021 Min New Capacity Constraint (% share) - based on 2023 fuel type shares | AN84: 2021 Min Net Capacity Constraint (% share) - based on 2023 fuel type shares | AR84: Vanilla4 - 2021 technology mix calibration
AJ85: Vehicle class | AK85: real 2023 | AL85: 2023 (rounded) | AN85: Vehicle class | AO85: real 2023 | AP85: 2023 (rounded) | AR85: Vanilla4 ex cap | AS85: Vanilla4 2021 new cap | AT85: calibrated sales shares | AU85: calibrated net cap shares
AJ86: Cars | AN86: Cars | AR86: Cars | AS86: 457.18334
AJ87: Gasoline | AK87: =BD5 -> 0.80563847 | AL87: =ROUND(AK87, 4) -> 0.8056 | AN87: Gasoline | AO87: ='Background Data'!AX40/'Background Data'!AX$39 -> 0.94710333 | AP87: =ROUND(AO87, 4) -> 0.9471 | AR87: 3608.754 | AS87: =$AS$86*AT87 -> 420.60867 | AT87: 0.92 | AU87: =(AR87+AS87)/SUM($AR$87:$AS$91) -> 0.94304636 | AV87: =AU87-AP87 -> -0.0040536437
AJ88: Diesel | AK88: =BD6 -> 0 | AL88: =ROUND(AK88, 4) -> 0 | AN88: Diesel | AO88: ='Background Data'!AX41/'Background Data'!AX$39 -> 0.011792363 | AP88: =ROUND(AO88, 4) -> 0.0118 | AR88: 62.31464 | AS88: =$AS$86*AT88 -> 0 | AT88: 0 | AU88: =(AR88+AS88)/SUM($AR$87:$AS$91) -> 0.01458434 | AV88: =AU88-AP88 -> 0.0027843398
AJ89: Battery electric | AK89: =BD7 -> 0.092011722 | AL89: =ROUND(AK89, 4) -> 0.092 | AN89: Battery | AO89: ='Background Data'!AX42/'Background Data'!AX$39 -> 0.013570738 | AP89: =ROUND(AO89, 4) -> 0.0136 | AR89: 40.81691 | AS89: =$AS$86*AT89 -> 18.287333 | AT89: 0.04 | AU89: =(AR89+AS89)/SUM($AR$87:$AS$91) -> 0.013832967 | AV89: =AU89-AP89 -> 0.00023296715
AJ90: Hybrid electric | AK90: =BD8 -> 0.094878891 | AL90: =ROUND(AK90, 4) -> 0.0949 | AN90: Hybrid | AO90: ='Background Data'!AX43/'Background Data'!AX$39 -> 0.022345647 | AP90: =ROUND(AO90, 4) -> 0.0223 | AR90: 78.2174 | AS90: =$AS$86*AT90 -> 18.287333 | AT90: 0.04 | AU90: =(AR90+AS90)/SUM($AR$87:$AS$91) -> 0.022586311 | AV90: =AU90-AP90 -> 0.00028631072
AJ91: Plug-in hybrid electric | AK91: =BD9 -> 0.0074709213 | AL91: =ROUND(AK91, 4) -> 0.0075 | AN91: Plug-in hybrid | AO91: ='Background Data'!AX44/'Background Data'!AX$39 -> 0.0051855962 | AP91: =ROUND(AO91, 4) -> 0.0052 | AR91: 25.42273 | AS91: =$AS$86*AT91 -> 0 | AT91: 0 | AU91: =(AR91+AS91)/SUM($AR$87:$AS$91) -> 0.0059500261 | AV91: =AU91-AP91 -> 0.00075002606
AJ92: Light Passenger Trucks | AN92: Light Passenger Trucks | AR92: Light Passenger Trucks | AS92: 301.1476 | AT92: =SUM(AT87:AT91) -> 1 | AV92: {=SUM(ABS(AV87:AV91))} -> 0.0081072874
AJ93: Gasoline | AK93: =BD32 -> 0.80020866 | AL93: =ROUND(AK93, 4) -> 0.8002 | AN93: Gasoline | AO93: =('Background Data'!AX33-'Background Data'!AX40)/('Background Data'!AX$32-'Background Data'!AX$39) -> 0.94046614 | AP93: =ROUND(AO93, 4) -> 0.9405 | AR93: 3641.7629 | AS93: =$AS$92*AT93 -> 216.82627 | AT93: 0.72 | AU93: =(AR93+AS93)/SUM($AR$93:$AS$97) -> 0.93826718 | AV93: =AU93-AP93 -> -0.0022328231
AJ94: Diesel | AK94: =BD33 -> 0.03939938 | AL94: =ROUND(AK94, 4) -> 0.0394 | AN94: Diesel | AO94: =('Background Data'!AX34-'Background Data'!AX41)/('Background Data'!AX$32-'Background Data'!AX$39) -> 0.02750149 | AP94: =ROUND(AO94, 4) -> 0.0275 | AR94: 139.43601 | AS94: =$AS$92*AT94 -> 0 | AT94: 0 | AU94: =(AR94+AS94)/SUM($AR$93:$AS$97) -> 0.033905717 | AV94: =AU94-AP94 -> 0.0064057168
AJ95: Battery electric | AK95: =BD34 -> 0.049676865 | AL95: =ROUND(AK95, 4) -> 0.0497 | AN95: Battery | AO95: =('Background Data'!AX35-'Background Data'!AX42)/('Background Data'!AX$32-'Background Data'!AX$39) -> 0.0085068775 | AP95: =ROUND(AO95, 4) -> 0.0085 | AR95: 4.44838 | AS95: =$AS$92*AT95 -> 24.091808 | AT95: 0.08 | AU95: =(AR95+AS95)/SUM($AR$93:$AS$97) -> 0.0069399256 | AV95: =AU95-AP95 -> -0.0015600744
AJ96: Hybrid electric | AK96: =BD35 -> 0.091879516 | AL96: =ROUND(AK96, 4) -> 0.0919 | AN96: Hybrid | AO96: =('Background Data'!AX36-'Background Data'!AX43)/('Background Data'!AX$32-'Background Data'!AX$39) -> 0.020096831 | AP96: =ROUND(AO96, 4) -> 0.0201 | AR96: 21.15926 | AS96: =$AS$92*AT96 -> 54.206568 | AT96: 0.18 | AU96: =(AR96+AS96)/SUM($AR$93:$AS$97) -> 0.018326202 | AV96: =AU96-AP96 -> -0.0017737984
AJ97: Plug-in hybrid electric | AK97: =BD36 -> 0.018835583 | AL97: =ROUND(AK97, 4) -> 0.0188 | AN97: Plug-in hybrid | AO97: =('Background Data'!AX37-'Background Data'!AX44)/('Background Data'!AX$32-'Background Data'!AX$39) -> 0.0033992991 | AP97: =ROUND(AO97, 4) -> 0.0034 | AR97: 4.50898 | AS97: =$AS$92*AT97 -> 6.022952 | AT97: 0.02 | AU97: =(AR97+AS97)/SUM($AR$93:$AS$97) -> 0.0025609791 | AV97: =AU97-AP97 -> -0.00083902092
AJ98: Light Freight Trucks | AN98: Light Freight Trucks | AR98: Light Freight Trucks | AS98: 114.75486 | AT98: =SUM(AT93:AT97) -> 1 | AV98: {=SUM(ABS(AV93:AV97))} -> 0.012811434
AJ99: Gasoline | AK99: =BD38 -> 0.80608887 | AL99: =ROUND(AK99, 4) -> 0.8061 | AN99: Gasoline | AO99: =('Background Data'!AX54+'Background Data'!AX61)/('Background Data'!AX$53+'Background Data'!AX$60) -> 0.92897021 | AP99: =ROUND(AO99, 4) -> 0.929 | AR99: 959.8256 | AS99: =$AS$98*AT99 -> 103.85315 | AT99: 0.905 | AU99: =(AR99+AS99)/SUM($AR$99:$AS$103) -> 0.92558568 | AV99: =AU99-AP99 -> -0.0034143216
AJ100: Diesel | AK100: =BD39 -> 0.13281513 | AL100: =ROUND(AK100, 4) -> 0.1328 | AN100: Diesel | AO100: =('Background Data'!AX55+'Background Data'!AX62)/('Background Data'!AX$53+'Background Data'!AX$60) -> 0.060252833 | AP100: =ROUND(AO100, 4) -> 0.0603 | AR100: 73.65206 | AS100: =$AS$98*AT100 -> 0 | AT100: 0 | AU100: =(AR100+AS100)/SUM($AR$99:$AS$103) -> 0.064090114 | AV100: =AU100-AP100 -> 0.0037901138
AJ101: Battery electric | AK101: =BD40 -> 0.015001943 | AL101: =ROUND(AK101, 4) -> 0.015 | AN101: Battery | AO101: =('Background Data'!AX56+'Background Data'!AX63)/('Background Data'!AX$53+'Background Data'!AX$60) -> 0.0010925403 | AP101: =ROUND(AO101, 4) -> 0.0011 | AR101: 0 | AS101: =$AS$98*AT101 -> 1.1475486 | AT101: 0.01 | AU101: =(AR101+AS101)/SUM($AR$99:$AS$103) -> 0.00099856703 | AV101: =AU101-AP101 -> -0.00010143297
AJ102: Hybrid electric | AK102: =BD41 -> 0.042077989 | AL102: =ROUND(AK102, 4) -> 0.0421 | AN102: Hybrid | AO102: =('Background Data'!AX57+'Background Data'!AX64)/('Background Data'!AX$53+'Background Data'!AX$60) -> 0.0083337001 | AP102: =ROUND(AO102, 4) -> 0.0083 | AR102: 0.06582 | AS102: =$AS$98*AT102 -> 9.1803886 | AT102: 0.08 | AU102: =(AR102+AS102)/SUM($AR$99:$AS$103) -> 0.0080458111 | AV102: =AU102-AP102 -> -0.00025418887
...

Sheet Demand
F1: Real 2019 demand | G1: Real 2020 demand | H1: Real 2021 demand | I1: period | Q1: DQI | V1: Model input | X1: Input calculations
A2: commodity | B2: region | C2: reference | D2: data_year | E2: units | I2: 2021 | J2: 2025 | K2: 2030 | L2: 2035 | M2: 2040 | N2: 2045 | O2: 2050 | P2: notes | Q2: Reliability | R2: Representativeness | S2: Temporal | T2: Geographical | U2: Technological
A3: T_D_tkm_hdv_t | B3: ON | C3: Natural Resources Canada. (2023b). Transportation Sector – Ontario. Government of Canada, Natural Resources Canada. https://oee.nrcan.gc.ca/corporate/statistics/neud/dpa/menus/trends/comprehensive/trends_tran_on.cfm | D3: 2023 | E3: btkm | F3: =(1-CFAF!$E$4)*'Background Data'!V26/1000 -> 21.925632 | G3: =(1-CFAF!$E$4)*'Background Data'!W26/1000 -> 19.760978 | H3: =(1-CFAF!$E$4)*'Background Data'!X26/1000 -> 22.165595 | I3: =H3 -> 22.165595 | J3: =$I3*Z$31 -> 24.087223 | K3: =$I3*AA$31 -> 26.811786 | L3: =$I3*AB$31 -> 28.88059 | M3: =$I3*AC$31 -> 30.961234 | N3: =$I3*AD$31 -> 33.011298 | O3: =$I3*AE$31 -> 35.34836 | P3: Based on the findings from Sonia Yet et al. 2022, demand projections are indexed through projected national GDP growth (2019=100), using estimates from the Current Measures Scenario of the Canada's Energy Futures 2023. Initial demand is obtained from 2021 subsector activity, which was impacted by the COVID-19 pandemic. Ontario long-haul/short-haul split from Canadian Freight Analysis Framework 2017 data. | Q3: 2 | R3: 1 | S3: 1 | T3: 1 | U3: 1
A4: T_D_tkm_hdv_t_lh | B4: ON | C4: Natural Resources Canada. (2023b). Transportation Sector – Ontario. Government of Canada, Natural Resources Canada. https://oee.nrcan.gc.ca/corporate/statistics/neud/dpa/menus/trends/comprehensive/trends_tran_on.cfm | D4: 2023 | E4: btkm | F4: =(CFAF!$E$4)*'Background Data'!V26/1000 -> 69.052095 | G4: =(CFAF!$E$4)*'Background Data'!W26/1000 -> 62.234781 | H4: =(CFAF!$E$4)*'Background Data'!X26/1000 -> 69.807827 | I4: =H4 -> 69.807827 | J4: =$I4*Z$31 -> 75.859762 | K4: =$I4*AA$31 -> 84.440437 | L4: =$I4*AB$31 -> 90.955884 | M4: =$I4*AC$31 -> 97.508618 | N4: =$I4*AD$31 -> 103.96504 | O4: =$I4*AE$31 -> 111.32533 | P4: Based on the findings from Sonia Yet et al. 2022, demand projections are indexed through projected national GDP growth (2019=100), using estimates from the Current Measures Scenario of the Canada's Energy Futures 2023. Initial demand is obtained from 2021 subsector activity, which was impacted by the COVID-19 pandemic. Ontario long-haul/short-haul split from Canadian Freight Analysis Framework 2017 data. | Q4: 2 | R4: 1 | S4: 1 | T4: 1 | U4: 1
Y11: CEF 2023 Current Policies Scenario - National Macro Indicators
Y12: Macroindicator | Z12: 2019 | AA12: 2020 | AB12: 2021 | AC12: 2025 | AD12: 2030 | AE12: 2035 | AF12: 2040 | AG12: 2045 | AH12: 2050
Y13: Real Gross Domestic Product ($2012 Millions) | Z13: 2109991 | AA13: 2002923 | AB13: 2103305 | AC13: 2292915 | AD13: 2552272 | AE13: 2749206 | AF13: 2947267 | AG13: 3142417 | AH13: 3364887
Y14: Population (thousands) | Z14: 37601.2 | AA14: 38007.2 | AB14: 38226.5 | AC14: 40909.9 | AD14: 43353.6 | AE14: 45341.8 | AF14: 46928.7 | AG14: 48323.3 | AH14: 49635.1
Y15: Gross Domestic Product Deflator (2012=100) | Z15: 109.6 | AA15: 110.3 | AB15: 119.3 | AC15: 138.4 | AD15: 154.6 | AE15: 170.5 | AF15: 187.6 | AG15: 206.4 | AH15: 227.3
Y16: Consumer Price Index (2002=100) | Z16: 136 | AA16: 137 | AB16: 141.6 | AC16: 164.7 | AD16: 184 | AE16: 203.1 | AF16: 223.8 | AG16: 246.5 | AH16: 271.2
Y17: Canada-US Exchange Rate (C$/US$) | Z17: 1.33 | AA17: 1.34 | AB17: 1.25 | AC17: 1.3 | AD17: 1.27 | AE17: 1.27 | AF17: 1.29 | AG17: 1.3 | AH17: 1.28
Y19: CEF 2023 Current Policies Scenario - GDP and population growth index (2020=100) in Canada
Y20: Indicator | Z20: 2021 | AA20: 2025 | AB20: 2030 | AC20: 2035 | AD20: 2040 | AE20: 2045 | AF20: 2050
Y21: GDP growth | Z21: =AB13/$AA13 -> 1.0501178 | AA21: =AC13/$AA13 -> 1.1447844 | AB21: =AD13/$AA13 -> 1.2742736 | AC21: =AE13/$AA13 -> 1.3725969 | AD21: =AF13/$AA13 -> 1.4714829 | AE21: =AG13/$AA13 -> 1.5689155 | AF21: =AH13/$AA13 -> 1.6799882
Y22: Population growth | Z22: =AB14/$AA14 -> 1.00577 | AA22: =AC14/$AA14 -> 1.0763724 | AB22: =AD14/$AA14 -> 1.1406681 | AC22: =AE14/$AA14 -> 1.1929792 | AD22: =AF14/$AA14 -> 1.2347318 | AE22: =AG14/$AA14 -> 1.2714249 | AF22: =AH14/$AA14 -> 1.3059394
Y24: CEF 2023 Current Policies Scenario - GDP and population growth index (2021=100) in Canada
Y25: Indicator | Z25: 2025 | AA25: 2030 | AB25: 2035 | AC25: 2040 | AD25: 2045 | AE25: 2050
Y26: GDP growth | Z26: =AC13/$AB13 -> 1.0901486 | AA26: =AD13/$AB13 -> 1.2134579 | AB26: =AE13/$AB13 -> 1.3070886 | AC26: =AF13/$AB13 -> 1.4012552 | AD26: =AG13/$AB13 -> 1.4940377 | AE26: =AH13/$AB13 -> 1.5998093
Y27: Population growth | Z27: =AC14/$AB14 -> 1.0701974 | AA27: =AD14/$AB14 -> 1.1341242 | AB27: =AE14/$AB14 -> 1.1861353 | AC27: =AF14/$AB14 -> 1.2276484 | AD27: =AG14/$AB14 -> 1.2641309 | AE27: =AH14/$AB14 -> 1.2984474
Y29: CEF 2023 Current Policies Scenario - GDP and population growth index (2019=100) in Canada
Y30: Indicator | Z30: 2025 | AA30: 2030 | AB30: 2035 | AC30: 2040 | AD30: 2045 | AE30: 2050
Y31: GDP growth | Z31: =AC13/$Z13 -> 1.0866942 | AA31: =AD13/$Z13 -> 1.2096127 | AB31: =AE13/$Z13 -> 1.3029468 | AC31: =AF13/$Z13 -> 1.396815 | AD31: =AG13/$Z13 -> 1.4893035 | AE31: =AH13/$Z13 -> 1.59474
Y32: Population growth | Z32: =AC14/$Z14 -> 1.0879945 | AA32: =AD14/$Z14 -> 1.1529845 | AB32: =AE14/$Z14 -> 1.2058605 | AC32: =AF14/$Z14 -> 1.2480639 | AD32: =AG14/$Z14 -> 1.2851531 | AE32: =AH14/$Z14 -> 1.3200403

Sheet LifetimeTech
A1: region | B1: tech | C1: lifetime | D1: notes | E1: reference | F1: data_year
A2: ON | B2: T_HDV_T_LH_CHRG_LRGBATT | C2: 15 | D2: Lifetime obtained from the Open Energy Outlook 2022. | E2: DeCarolis, J. F., Jaramillo, P., Johnson, J. X., McCollum, D. L., Trutnevyte, E., Daniels, D. C., Akn-Olcum, G., Bergerson, J., Cho, S., Choi, J.-H., Craig, M. T., de Queiroz, A. R., Eshraghi, H., Galik, C. S., Gutowski, T. G., Haapala, K. R., Hodge, B.-M., Hoque, S., Jenkins, J. D., ... Zhou, Y. (2020). Open Energy OutlookLeveraging Open-Source Tools for Collaborative Macro-energy System Modeling Efforts. Joule, 4(12), 25232526. https://doi.org/10.1016/j.joule.2020.11.002 | F2: 2022
A3: ON | B3: T_HDV_T_LH_CHRG_FSTCHRG | C3: 15 | D3: Lifetime obtained from the Open Energy Outlook 2022. | E3: DeCarolis, J. F., Jaramillo, P., Johnson, J. X., McCollum, D. L., Trutnevyte, E., Daniels, D. C., Akn-Olcum, G., Bergerson, J., Cho, S., Choi, J.-H., Craig, M. T., de Queiroz, A. R., Eshraghi, H., Galik, C. S., Gutowski, T. G., Haapala, K. R., Hodge, B.-M., Hoque, S., Jenkins, J. D., ... Zhou, Y. (2020). Open Energy OutlookLeveraging Open-Source Tools for Collaborative Macro-energy System Modeling Efforts. Joule, 4(12), 25232526. https://doi.org/10.1016/j.joule.2020.11.002 | F3: 2022
A4: ON | B4: T_HDV_T_LH_CHRG_ERDS1 | C4: 20 | D4: eRoads lifetime placeholder value
A5: ON | B5: T_HDV_T_LH_CHRG_ERDS2 | C5: 20 | D5: eRoads lifetime placeholder value
A6: ON | B6: T_HDV_T_LH_CHRG_ERDS3 | C6: 20 | D6: eRoads lifetime placeholder value
A7: ON | B7: T_HDV_T_LH_CHRG_ERDS4 | C7: 20 | D7: eRoads lifetime placeholder value
A8: ON | B8: T_HDV_T_LH_CHRG_ERDS5 | C8: 20 | D8: eRoads lifetime placeholder value
A9: ON | B9: T_H2_HDV_T_LH_REFUEL | C9: 10 | D9: Obtained from Hydrogen Delivery Scenario Analysis Model (HDSAM) v4.5: heavy-duty refueling station (gaseous H2) economic assumptions - dispenser lifetime | E9: Argonne National Laboratory, Amgad Elgowainy, & Krishna Reddi. (2022). Hydrogen Delivery Scenario Analysis Model (HDSAM) v4.5. Hydrogen Delivery Infrastructure Analysis. https://hdsam.es.anl.gov/index.php | F9: 2022
A10: ON | B10: T_HDV_T_LH_DSL_EX | C10: 19 | D10: Median lifetime based on input survival rates of "Heavy-duty trucks" vehicle class from MOVES4 model. | E10: EPA. (2023). Population and Activity of Onroad Vehicles in MOVES4 (EPA-420-R-23-005). https://www.epa.gov/system/files/documents/2023-08/420r23005.pdf | F10: 2023
A11: ON | B11: T_HDV_T_LH_DSL_N | C11: 19 | D11: Median lifetime based on input survival rates of "Heavy-duty trucks" vehicle class from MOVES4 model. | E11: EPA. (2023). Population and Activity of Onroad Vehicles in MOVES4 (EPA-420-R-23-005). https://www.epa.gov/system/files/documents/2023-08/420r23005.pdf | F11: 2023
A12: ON | B12: T_HDV_T_LH_FCEV_N | C12: 19 | D12: Median lifetime based on input survival rates of "Heavy-duty trucks" vehicle class from MOVES4 model. | E12: EPA. (2023). Population and Activity of Onroad Vehicles in MOVES4 (EPA-420-R-23-005). https://www.epa.gov/system/files/documents/2023-08/420r23005.pdf | F12: 2023
A13: ON | B13: T_HDV_T_LH_BEV_LRGBATT_N | C13: 19 | D13: Median lifetime based on input survival rates of "Heavy-duty trucks" vehicle class from MOVES4 model. | E13: EPA. (2023). Population and Activity of Onroad Vehicles in MOVES4 (EPA-420-R-23-005). https://www.epa.gov/system/files/documents/2023-08/420r23005.pdf | F13: 2023
A14: ON | B14: T_HDV_T_LH_BEV_FSTCHRG_N | C14: 19 | D14: Median lifetime based on input survival rates of "Heavy-duty trucks" vehicle class from MOVES4 model. | E14: EPA. (2023). Population and Activity of Onroad Vehicles in MOVES4 (EPA-420-R-23-005). https://www.epa.gov/system/files/documents/2023-08/420r23005.pdf | F14: 2023
A15: ON | B15: T_HDV_T_LH_BEV_ERDS1_N | C15: 19 | D15: Median lifetime based on input survival rates of "Heavy-duty trucks" vehicle class from MOVES4 model. | E15: EPA. (2023). Population and Activity of Onroad Vehicles in MOVES4 (EPA-420-R-23-005). https://www.epa.gov/system/files/documents/2023-08/420r23005.pdf | F15: 2023
A16: ON | B16: T_HDV_T_LH_BEV_ERDS2_N | C16: 19 | D16: Median lifetime based on input survival rates of "Heavy-duty trucks" vehicle class from MOVES4 model. | E16: EPA. (2023). Population and Activity of Onroad Vehicles in MOVES4 (EPA-420-R-23-005). https://www.epa.gov/system/files/documents/2023-08/420r23005.pdf | F16: 2023
A17: ON | B17: T_HDV_T_LH_BEV_ERDS3_N | C17: 19 | D17: Median lifetime based on input survival rates of "Heavy-duty trucks" vehicle class from MOVES4 model. | E17: EPA. (2023). Population and Activity of Onroad Vehicles in MOVES4 (EPA-420-R-23-005). https://www.epa.gov/system/files/documents/2023-08/420r23005.pdf | F17: 2023
A18: ON | B18: T_HDV_T_LH_BEV_ERDS4_N | C18: 19 | D18: Median lifetime based on input survival rates of "Heavy-duty trucks" vehicle class from MOVES4 model. | E18: EPA. (2023). Population and Activity of Onroad Vehicles in MOVES4 (EPA-420-R-23-005). https://www.epa.gov/system/files/documents/2023-08/420r23005.pdf | F18: 2023
A19: ON | B19: T_HDV_T_LH_BEV_ERDS5_N | C19: 19 | D19: Median lifetime based on input survival rates of "Heavy-duty trucks" vehicle class from MOVES4 model. | E19: EPA. (2023). Population and Activity of Onroad Vehicles in MOVES4 (EPA-420-R-23-005). https://www.epa.gov/system/files/documents/2023-08/420r23005.pdf | F19: 2023

Sheet Efficiency
A1: This table is also used to dictate when novel technologies are introduced. | G1: vintage | AK1: DQI | AP1: Model input | AR1: Input calculations
A2: tech | B2: input_comm | C2: output_comm | D2: region | E2: reference | F2: data_year | G2: 2000 | H2: 2001 | I2: 2002 | J2: 2003 | K2: 2004 | L2: 2005 | M2: 2006 | N2: 2007 | O2: 2008 | P2: 2009 | Q2: 2010 | R2: 2011 | S2: 2012 | T2: 2013 | U2: 2014 | V2: 2015 | W2: 2016 | X2: 2017 | Y2: 2018 | Z2: 2019 | AA2: 2020 | AB2: 2021 | AC2: 2025 | AD2: 2030 | AE2: 2035 | AF2: 2040 | AG2: 2045 | AH2: 2050 | AI2: New/existing (2021/2020) | AJ2: notes | AK2: Reliability | AL2: Representativeness | AM2: Temporal | AN2: Geographical | AO2: Technological
A3: T_HDV_T_LH_CHRG_LRGBATT | B3: T_elc | C3: T_elc_hdv_t_lh_chrg_lrgbatt | D3: ON | E3: ICCT. (2022, February). Assessing charging infrastructure needs in Québec. International Council on Clean Transportation. https://theicct.org/publication/lvs-ci-quebec-can-en-feb22/ | F3: 2022 | AB3: 0.9 | AC3: 0.9 | AD3: 0.9 | AE3: 0.9 | AF3: 0.9 | AG3: 0.9 | AH3: 0.9 | AJ3: PJ/PJ | AT3: Islam et al. 2023 (ANL/TAPS-23/3) - MHDV Avg. Fuel Efficiency projections (bkm/PJ) | BE3: Fuel efficiency index of new MHDVs
A4: T_HDV_T_LH_CHRG_FSTCHRG | B4: T_elc | C4: T_elc_hdv_t_lh_chrg_fstchrg | D4: ON | E4: ICCT. (2022, February). Assessing charging infrastructure needs in Québec. International Council on Clean Transportation. https://theicct.org/publication/lvs-ci-quebec-can-en-feb22/ | F4: 2022 | AB4: 0.9 | AC4: 0.9 | AD4: 0.9 | AE4: 0.9 | AF4: 0.9 | AG4: 0.9 | AH4: 0.9 | AJ4: PJ/PJ | AT4: Vehicle-class aggregated MHDV fuel efficiency (bkm/PJ)* | BE4: Vehicle-class aggregated MHDV fuel efficiency index by fuel type (2023 = 1)
A5: T_HDV_T_LH_CHRG_ERDS1 | B5: T_elc | C5: T_elc_hdv_t_lh_chrg_erds1 | D5: ON | E5: ICCT. (2022, February). Assessing charging infrastructure needs in Québec. International Council on Clean Transportation. https://theicct.org/publication/lvs-ci-quebec-can-en-feb22/ | F5: 2022 | AB5: 0.9 | AC5: 0.9 | AD5: 0.9 | AE5: 0.9 | AF5: 0.9 | AG5: 0.9 | AH5: 0.9 | AJ5: PJ/PJ | AT5: Vehicle Type | AU5: 2023 | AV5: 2025 | AW5: 2030 | AX5: 2035 | AY5: 2040† | AZ5: 2045† | BA5: 2050 | BB5: Change (2023-2050) | BE5: Vehicle Type | BF5: 2021 | BG5: 2025 | BH5: 2030 | BI5: 2035 | BJ5: 2040 | BK5: 2045 | BL5: 2050
A6: T_HDV_T_LH_CHRG_ERDS2 | B6: T_elc | C6: T_elc_hdv_t_lh_chrg_erds2 | D6: ON | E6: ICCT. (2022, February). Assessing charging infrastructure needs in Québec. International Council on Clean Transportation. https://theicct.org/publication/lvs-ci-quebec-can-en-feb22/ | F6: 2022 | AB6: 0.9 | AC6: 0.9 | AD6: 0.9 | AE6: 0.9 | AF6: 0.9 | AG6: 0.9 | AH6: 0.9 | AJ6: PJ/PJ | AS6: 8 | AT6: Class 8 (day cab) | BE6: Heavy-duty Trucks (Class 8) non long-haul
A7: T_HDV_T_LH_CHRG_ERDS3 | B7: T_elc | C7: T_elc_hdv_t_lh_chrg_erds3 | D7: ON | E7: ICCT. (2022, February). Assessing charging infrastructure needs in Québec. International Council on Clean Transportation. https://theicct.org/publication/lvs-ci-quebec-can-en-feb22/ | F7: 2022 | AB7: 0.9 | AC7: 0.9 | AD7: 0.9 | AE7: 0.9 | AF7: 0.9 | AG7: 0.9 | AH7: 0.9 | AJ7: PJ/PJ | AS7: 8 | AT7: CI | AU7: {=1/AVERAGE(_xlfn._xlws.FILTER('Autonomie 2023 MHDV'!$AR:$AR,(NOT(ISERROR(SEARCH("_ci_", 'Autonomie 2023 MHDV'!$G:$G))))*('Autonomie 2023 MHDV'!$A:$A="Conv")*('Autonomie 2023 MHDV'!$B:$B=AU$5)*('Autonomie 2023 MHDV'!$F:$F=$AS7)*('Autonomie 2023 MHDV'!$E:$E="DayCab")))} -> 0.072747719 | AV7: {=1/AVERAGE(_xlfn._xlws.FILTER('Autonomie 2023 MHDV'!$AR:$AR,(NOT(ISERROR(SEARCH("_ci_", 'Autonomie 2023 MHDV'!$G:$G))))*('Autonomie 2023 MHDV'!$A:$A="Conv")*('Autonomie 2023 MHDV'!$B:$B=AV$5)*('Autonomie 2023 MHDV'!$F:$F=$AS7)*('Autonomie 2023 MHDV'!$E:$E="DayCab")))} -> 0.079536359 | AW7: {=1/AVERAGE(_xlfn._xlws.FILTER('Autonomie 2023 MHDV'!$AR:$AR,(NOT(ISERROR(SEARCH("_ci_", 'Autonomie 2023 MHDV'!$G:$G))))*('Autonomie 2023 MHDV'!$A:$A="Conv")*('Autonomie 2023 MHDV'!$B:$B=AW$5)*('Autonomie 2023 MHDV'!$F:$F=$AS7)*('Autonomie 2023 MHDV'!$E:$E="DayCab")))} -> 0.086025655 | AX7: {=1/AVERAGE(_xlfn._xlws.FILTER('Autonomie 2023 MHDV'!$AR:$AR,(NOT(ISERROR(SEARCH("_ci_", 'Autonomie 2023 MHDV'!$G:$G))))*('Autonomie 2023 MHDV'!$A:$A="Conv")*('Autonomie 2023 MHDV'!$B:$B=AX$5)*('Autonomie 2023 MHDV'!$F:$F=$AS7)*('Autonomie 2023 MHDV'!$E:$E="DayCab")))} -> 0.092192876 | AY7: =($BA7-$AX7)/3 + AX7 -> 0.09462238 | AZ7: =($BA7-$AX7)/3 + AY7 -> 0.097051883 | BA7: {=1/AVERAGE(_xlfn._xlws.FILTER('Autonomie 2023 MHDV'!$AR:$AR,(NOT(ISERROR(SEARCH("_ci_", 'Autonomie 2023 MHDV'!$G:$G))))*('Autonomie 2023 MHDV'!$A:$A="Conv")*('Autonomie 2023 MHDV'!$B:$B=BA$5)*('Autonomie 2023 MHDV'!$F:$F=$AS7)*('Autonomie 2023 MHDV'!$E:$E="DayCab")))} -> 0.099481387 | BB7: =(BA7-AU7)/AU7 -> 0.36748462 | BE7: DSL | BF7: =AU7/$AU7 -> 1 | BG7: =AV7/$AU7 -> 1.0933176 | BH7: =AW7/$AU7 -> 1.1825203 | BI7: =AX7/$AU7 -> 1.2672958 | BJ7: =AY7/$AU7 -> 1.3006921 | BK7: =AZ7/$AU7 -> 1.3340883 | BL7: =BA7/$AU7 -> 1.3674846
A8: T_HDV_T_LH_CHRG_ERDS4 | B8: T_elc | C8: T_elc_hdv_t_lh_chrg_erds4 | D8: ON | E8: ICCT. (2022, February). Assessing charging infrastructure needs in Québec. International Council on Clean Transportation. https://theicct.org/publication/lvs-ci-quebec-can-en-feb22/ | F8: 2022 | AB8: 0.9 | AC8: 0.9 | AD8: 0.9 | AE8: 0.9 | AF8: 0.9 | AG8: 0.9 | AH8: 0.9 | AJ8: PJ/PJ | AS8: 8 | AT8: ParHEV | AU8: {=1/AVERAGE(_xlfn._xlws.FILTER('Autonomie 2023 MHDV'!$AR:$AR,(NOT(ISERROR(SEARCH("_ci_", 'Autonomie 2023 MHDV'!$G:$G))))*('Autonomie 2023 MHDV'!$A:$A=$AT8)*('Autonomie 2023 MHDV'!$B:$B=AU$5)*('Autonomie 2023 MHDV'!$F:$F=$AS8)*('Autonomie 2023 MHDV'!$E:$E="DayCab")))} -> 0.076500979 | AV8: {=1/AVERAGE(_xlfn._xlws.FILTER('Autonomie 2023 MHDV'!$AR:$AR,(NOT(ISERROR(SEARCH("_ci_", 'Autonomie 2023 MHDV'!$G:$G))))*('Autonomie 2023 MHDV'!$A:$A=$AT8)*('Autonomie 2023 MHDV'!$B:$B=AV$5)*('Autonomie 2023 MHDV'!$F:$F=$AS8)*('Autonomie 2023 MHDV'!$E:$E="DayCab")))} -> 0.085097106 | AW8: {=1/AVERAGE(_xlfn._xlws.FILTER('Autonomie 2023 MHDV'!$AR:$AR,(NOT(ISERROR(SEARCH("_ci_", 'Autonomie 2023 MHDV'!$G:$G))))*('Autonomie 2023 MHDV'!$A:$A=$AT8)*('Autonomie 2023 MHDV'!$B:$B=AW$5)*('Autonomie 2023 MHDV'!$F:$F=$AS8)*('Autonomie 2023 MHDV'!$E:$E="DayCab")))} -> 0.093110823 | AX8: {=1/AVERAGE(_xlfn._xlws.FILTER('Autonomie 2023 MHDV'!$AR:$AR,(NOT(ISERROR(SEARCH("_ci_", 'Autonomie 2023 MHDV'!$G:$G))))*('Autonomie 2023 MHDV'!$A:$A=$AT8)*('Autonomie 2023 MHDV'!$B:$B=AX$5)*('Autonomie 2023 MHDV'!$F:$F=$AS8)*('Autonomie 2023 MHDV'!$E:$E="DayCab")))} -> 0.1015245 | AY8: =($BA8-$AX8)/3 + AX8 -> 0.10502594 | AZ8: =($BA8-$AX8)/3 + AY8 -> 0.10852739 | BA8: {=1/AVERAGE(_xlfn._xlws.FILTER('Autonomie 2023 MHDV'!$AR:$AR,(NOT(ISERROR(SEARCH("_ci_", 'Autonomie 2023 MHDV'!$G:$G))))*('Autonomie 2023 MHDV'!$A:$A=$AT8)*('Autonomie 2023 MHDV'!$B:$B=BA$5)*('Autonomie 2023 MHDV'!$F:$F=$AS8)*('Autonomie 2023 MHDV'!$E:$E="DayCab")))} -> 0.11202883 | BB8: =(BA8-AU8)/AU8 -> 0.46441042 | BE8: ParHEV† | BF8: =AU8/AU$7 -> 1.0515928 | BG8: =AV8/AV$7 -> 1.0699145 | BH8: =AW8/AW$7 -> 1.0823611 | BI8: =AX8/AX$7 -> 1.1012185 | BJ8: =AY8/AY$7 -> 1.1099482 | BK8: =AZ8/AZ$7 -> 1.1182409 | BL8: =BA8/BA$7 -> 1.1261286
A9: T_HDV_T_LH_CHRG_ERDS5 | B9: T_elc | C9: T_elc_hdv_t_lh_chrg_erds5 | D9: ON | E9: ICCT. (2022, February). Assessing charging infrastructure needs in Québec. International Council on Clean Transportation. https://theicct.org/publication/lvs-ci-quebec-can-en-feb22/ | F9: 2022 | AB9: 0.9 | AC9: 0.9 | AD9: 0.9 | AE9: 0.9 | AF9: 0.9 | AG9: 0.9 | AH9: 0.9 | AJ9: PJ/PJ | AS9: 8 | AT9: SeriesPHEV | AU9: {=1/AVERAGE(_xlfn._xlws.FILTER('Autonomie 2023 MHDV'!$AR:$AR,(NOT(ISERROR(SEARCH("_ci_", 'Autonomie 2023 MHDV'!$G:$G))))*('Autonomie 2023 MHDV'!$A:$A=$AT9)*('Autonomie 2023 MHDV'!$B:$B=AU$5)*('Autonomie 2023 MHDV'!$F:$F=$AS9)*('Autonomie 2023 MHDV'!$E:$E="DayCab")))} -> 0.1279824 | AV9: {=1/AVERAGE(_xlfn._xlws.FILTER('Autonomie 2023 MHDV'!$AR:$AR,(NOT(ISERROR(SEARCH("_ci_", 'Autonomie 2023 MHDV'!$G:$G))))*('Autonomie 2023 MHDV'!$A:$A=$AT9)*('Autonomie 2023 MHDV'!$B:$B=AV$5)*('Autonomie 2023 MHDV'!$F:$F=$AS9)*('Autonomie 2023 MHDV'!$E:$E="DayCab")))} -> 0.14175712 | AW9: {=1/AVERAGE(_xlfn._xlws.FILTER('Autonomie 2023 MHDV'!$AR:$AR,(NOT(ISERROR(SEARCH("_ci_", 'Autonomie 2023 MHDV'!$G:$G))))*('Autonomie 2023 MHDV'!$A:$A=$AT9)*('Autonomie 2023 MHDV'!$B:$B=AW$5)*('Autonomie 2023 MHDV'!$F:$F=$AS9)*('Autonomie 2023 MHDV'!$E:$E="DayCab")))} -> 0.15516338 | AX9: {=1/AVERAGE(_xlfn._xlws.FILTER('Autonomie 2023 MHDV'!$AR:$AR,(NOT(ISERROR(SEARCH("_ci_", 'Autonomie 2023 MHDV'!$G:$G))))*('Autonomie 2023 MHDV'!$A:$A=$AT9)*('Autonomie 2023 MHDV'!$B:$B=AX$5)*('Autonomie 2023 MHDV'!$F:$F=$AS9)*('Autonomie 2023 MHDV'!$E:$E="DayCab")))} -> 0.17125469 | AY9: =($BA9-$AX9)/3 + AX9 -> 0.17826793 | AZ9: =($BA9-$AX9)/3 + AY9 -> 0.18528116 | BA9: {=1/AVERAGE(_xlfn._xlws.FILTER('Autonomie 2023 MHDV'!$AR:$AR,(NOT(ISERROR(SEARCH("_ci_", 'Autonomie 2023 MHDV'!$G:$G))))*('Autonomie 2023 MHDV'!$A:$A=$AT9)*('Autonomie 2023 MHDV'!$B:$B=BA$5)*('Autonomie 2023 MHDV'!$F:$F=$AS9)*('Autonomie 2023 MHDV'!$E:$E="DayCab")))} -> 0.1922944 | BB9: =(BA9-AU9)/AU9 -> 0.50250655 | BE9: SeriesPHEV† | BF9: =AU9/AU$7 -> 1.7592635 | BG9: =AV9/AV$7 -> 1.7822933 | BH9: =AW9/AW$7 -> 1.8036873 | BI9: =AX9/AX$7 -> 1.8575697 | BJ9: =AY9/AY$7 -> 1.8839933 | BK9: =AZ9/AZ$7 -> 1.909094 | BL9: =BA9/BA$7 -> 1.9329686
A10: T_H2_HDV_T_LH_REFUEL | B10: h2_700 | C10: T_h2_hdv_t_lh | D10: ON | E10: DeCarolis, J. F., Jaramillo, P., Johnson, J. X., McCollum, D. L., Trutnevyte, E., Daniels, D. C., Akın-Olçum, G., Bergerson, J., Cho, S., Choi, J.-H., Craig, M. T., de Queiroz, A. R., Eshraghi, H., Galik, C. S., Gutowski, T. G., Haapala, K. R., Hodge, B.-M., Hoque, S., Jenkins, J. D., … Zhou, Y. (2020). Open Energy Outlook—Leveraging Open-Source Tools for Collaborative Macro-energy System Modeling Efforts. Joule, 4(12), 2523–2526. https://doi.org/10.1016/j.joule.2020.11.002 | F10: 2022 | AB10: 0.995 | AC10: 0.995 | AD10: 0.995 | AE10: 0.995 | AF10: 0.995 | AG10: 0.995 | AH10: 0.995 | AJ10: PJ/PJ | AS10: 8 | AT10: BEV | AU10: {=1/AVERAGE(_xlfn._xlws.FILTER('Autonomie 2023 MHDV'!$AR:$AR,('Autonomie 2023 MHDV'!$A:$A=$AT10)*('Autonomie 2023 MHDV'!$B:$B=AU$5)*('Autonomie 2023 MHDV'!$F:$F=$AS10)*('Autonomie 2023 MHDV'!$E:$E="DayCab")))} -> 0.18934303 | AV10: {=1/AVERAGE(_xlfn._xlws.FILTER('Autonomie 2023 MHDV'!$AR:$AR,('Autonomie 2023 MHDV'!$A:$A=$AT10)*('Autonomie 2023 MHDV'!$B:$B=AV$5)*('Autonomie 2023 MHDV'!$F:$F=$AS10)*('Autonomie 2023 MHDV'!$E:$E="DayCab")))} -> 0.20894387 | AW10: {=1/AVERAGE(_xlfn._xlws.FILTER('Autonomie 2023 MHDV'!$AR:$AR,('Autonomie 2023 MHDV'!$A:$A=$AT10)*('Autonomie 2023 MHDV'!$B:$B=AW$5)*('Autonomie 2023 MHDV'!$F:$F=$AS10)*('Autonomie 2023 MHDV'!$E:$E="DayCab")))} -> 0.22948098 | AX10: {=1/AVERAGE(_xlfn._xlws.FILTER('Autonomie 2023 MHDV'!$AR:$AR,('Autonomie 2023 MHDV'!$A:$A=$AT10)*('Autonomie 2023 MHDV'!$B:$B=AX$5)*('Autonomie 2023 MHDV'!$F:$F=$AS10)*('Autonomie 2023 MHDV'!$E:$E="DayCab")))} -> 0.25431196 | AY10: =($BA10-$AX10)/3 + AX10 -> 0.26523583 | AZ10: =($BA10-$AX10)/3 + AY10 -> 0.2761597 | BA10: {=1/AVERAGE(_xlfn._xlws.FILTER('Autonomie 2023 MHDV'!$AR:$AR,('Autonomie 2023 MHDV'!$A:$A=$AT10)*('Autonomie 2023 MHDV'!$B:$B=BA$5)*('Autonomie 2023 MHDV'!$F:$F=$AS10)*('Autonomie 2023 MHDV'!$E:$E="DayCab")))} -> 0.28708358 | BB10: =(BA10-AU10)/AU10 -> 0.51620886 | BE10: BEV† | BF10: =AU10/AU$7 -> 2.6027349 | BG10: =AV10/AV$7 -> 2.6270233 | BH10: =AW10/AW$7 -> 2.6675877 | BI10: =AX10/AX$7 -> 2.7584773 | BJ10: =AY10/AY$7 -> 2.8030983 | BK10: =AZ10/AZ$7 -> 2.8454853 | BL10: =BA10/BA$7 -> 2.8858019
A11: T_HDV_T_LH_DSL_EX | B11: T_dsl | C11: T_D_tkm_hdv_t_lh | D11: ON | E11: Natural Resources Canada. (2023b). Transportation Sector – Ontario. Government of Canada, Natural Resources Canada. https://oee.nrcan.gc.ca/corporate/statistics/neud/dpa/menus/trends/comprehensive/trends_tran_on.cfm | F11: 2023 | L11: =AY$31/('Background Data'!H$118*GSL_PJ_ML*10) -> 0.60223669 | Q11: =BD$31/('Background Data'!M$118*GSL_PJ_ML*10) -> 0.55452089 | V11: =BI$31/('Background Data'!R$118*GSL_PJ_ML*10) -> 0.701195 | AA11: =BN$31/('Background Data'!Y$118*GSL_PJ_ML*10) -> 0.66666253 | AJ11: [btkm/PJ] | AS11: 8 | AT11: FCEV | AU11: {=1/AVERAGE(_xlfn._xlws.FILTER('Autonomie 2023 MHDV'!$AR:$AR,('Autonomie 2023 MHDV'!$A:$A=$AT11)*('Autonomie 2023 MHDV'!$B:$B=AU$5)*('Autonomie 2023 MHDV'!$F:$F=$AS11)*('Autonomie 2023 MHDV'!$E:$E="DayCab")))} -> 0.089161606 | AV11: {=1/AVERAGE(_xlfn._xlws.FILTER('Autonomie 2023 MHDV'!$AR:$AR,('Autonomie 2023 MHDV'!$A:$A=$AT11)*('Autonomie 2023 MHDV'!$B:$B=AV$5)*('Autonomie 2023 MHDV'!$F:$F=$AS11)*('Autonomie 2023 MHDV'!$E:$E="DayCab")))} -> 0.10130028 | AW11: {=1/AVERAGE(_xlfn._xlws.FILTER('Autonomie 2023 MHDV'!$AR:$AR,('Autonomie 2023 MHDV'!$A:$A=$AT11)*('Autonomie 2023 MHDV'!$B:$B=AW$5)*('Autonomie 2023 MHDV'!$F:$F=$AS11)*('Autonomie 2023 MHDV'!$E:$E="DayCab")))} -> 0.11373726 | AX11: {=1/AVERAGE(_xlfn._xlws.FILTER('Autonomie 2023 MHDV'!$AR:$AR,('Autonomie 2023 MHDV'!$A:$A=$AT11)*('Autonomie 2023 MHDV'!$B:$B=AX$5)*('Autonomie 2023 MHDV'!$F:$F=$AS11)*('Autonomie 2023 MHDV'!$E:$E="DayCab")))} -> 0.12672458 | AY11: =($BA11-$AX11)/3 + AX11 -> 0.13361957 | AZ11: =($BA11-$AX11)/3 + AY11 -> 0.14051456 | BA11: {=1/AVERAGE(_xlfn._xlws.FILTER('Autonomie 2023 MHDV'!$AR:$AR,('Autonomie 2023 MHDV'!$A:$A=$AT11)*('Autonomie 2023 MHDV'!$B:$B=BA$5)*('Autonomie 2023 MHDV'!$F:$F=$AS11)*('Autonomie 2023 MHDV'!$E:$E="DayCab")))} -> 0.14740955 | BB11: =(BA11-AU11)/AU11 -> 0.65328501 | BE11: FCEV† | BF11: =AU11/AU$7 -> 1.2256275 | BG11: =AV11/AV$7 -> 1.2736349 | BH11: =AW11/AW$7 -> 1.3221319 | BI11: =AX11/AX$7 -> 1.3745593 | BJ11: =AY11/AY$7 -> 1.4121349 | BK11: =AZ11/AZ$7 -> 1.4478293 | BL11: =BA11/BA$7 -> 1.4817802 | BS11: Apply payload capacity penalties
A12: T_HDV_T_LH_DSL_N | B12: T_dsl | C12: T_D_tkm_hdv_t_lh | D12: ON | E12: Argonne National Laboratory, Islam, E. S., Prada, D. N., Vijayagopal, R., Mansour, C., Philips, P., Kim, N., Alhajjar, M., & Rousseau, A. (2023, October). Detailed Simulation Study to Evaluate Future Transportation Decarbonization Potential. Vehicle & Mobility Systems Department - Argonne National Laboratory. https://vms.taps.anl.gov/research-highlights/vehicle-technologies/u-s-doe-vto-hfto-r-d-benefits/ | F12: 2023 | AB12: =$AA$11*BF$14 -> 0.66666253 | AC12: =$AA$11*BG$14 -> 0.73396574 | AD12: =$AA$11*BH$14 -> 0.80695035 | AE12: =$AA$11*BI$14 -> 0.87156327 | AF12: =$AA$11*BJ$14 -> 0.90825718 | AG12: =$AA$11*BK$14 -> 0.94495109 | AH12: =$AA$11*BL$14 -> 0.981645 | AJ12: [btkm/PJ] Vehicle class fuel efficiency aggregated from Islam et al. 2023 low uncertainty projections by Class 8 truck types. Aggregation was done with StatCan Table: 23-10-0219-01 shipment type shares (local vs. long distance). Values were harmonized using provincial load factors. Energy consumption based on drive cycle combinations as prescribed in the EPA final rule regulatory documents for MHDVs (EPA & NHTSA, 2016). | AK12: 3 | AL12: 1 | AM12: 1 | AN12: 3 | AO12: 1 | AS12: 8 | AT12: FCHEV | AU12: {=1/AVERAGE(_xlfn._xlws.FILTER('Autonomie 2023 MHDV'!$AR:$AR,('Autonomie 2023 MHDV'!$A:$A=$AT12)*('Autonomie 2023 MHDV'!$B:$B=AU$5)*('Autonomie 2023 MHDV'!$F:$F=$AS12)*('Autonomie 2023 MHDV'!$E:$E="DayCab")))} -> 0.086660184 | AV12: {=1/AVERAGE(_xlfn._xlws.FILTER('Autonomie 2023 MHDV'!$AR:$AR,('Autonomie 2023 MHDV'!$A:$A=$AT12)*('Autonomie 2023 MHDV'!$B:$B=AV$5)*('Autonomie 2023 MHDV'!$F:$F=$AS12)*('Autonomie 2023 MHDV'!$E:$E="DayCab")))} -> 0.098110615 | AW12: {=1/AVERAGE(_xlfn._xlws.FILTER('Autonomie 2023 MHDV'!$AR:$AR,('Autonomie 2023 MHDV'!$A:$A=$AT12)*('Autonomie 2023 MHDV'!$B:$B=AW$5)*('Autonomie 2023 MHDV'!$F:$F=$AS12)*('Autonomie 2023 MHDV'!$E:$E="DayCab")))} -> 0.1100387 | AX12: {=1/AVERAGE(_xlfn._xlws.FILTER('Autonomie 2023 MHDV'!$AR:$AR,('Autonomie 2023 MHDV'!$A:$A=$AT12)*('Autonomie 2023 MHDV'!$B:$B=AX$5)*('Autonomie 2023 MHDV'!$F:$F=$AS12)*('Autonomie 2023 MHDV'!$E:$E="DayCab")))} -> 0.12562335 | AY12: =($BA12-$AX12)/3 + AX12 -> 0.13262014 | AZ12: =($BA12-$AX12)/3 + AY12 -> 0.13961693 | BA12: {=1/AVERAGE(_xlfn._xlws.FILTER('Autonomie 2023 MHDV'!$AR:$AR,('Autonomie 2023 MHDV'!$A:$A=$AT12)*('Autonomie 2023 MHDV'!$B:$B=BA$5)*('Autonomie 2023 MHDV'!$F:$F=$AS12)*('Autonomie 2023 MHDV'!$E:$E="DayCab")))} -> 0.14661372 | BB12: =(BA12-AU12)/AU12 -> 0.69182327 | BE12: FCHEV† | BF12: =AU12/AU$7 -> 1.1912426 | BG12: =AV12/AV$7 -> 1.2335316 | BH12: =AW12/AW$7 -> 1.2791382 | BI12: =AX12/AX$7 -> 1.3626145 | BJ12: =AY12/AY$7 -> 1.4015726 | BK12: =AZ12/AZ$7 -> 1.4385803 | BL12: =BA12/BA$7 -> 1.4737804 | BS12: Heavy-duty Trucks (Class 8) long-haul
A13: T_HDV_T_LH_BEV_LRGBATT_N | B13: T_elc_hdv_t_lh_chrg_lrgbatt | C13: T_annual_tkm_hdv_t_lh | D13: ON | E13: Argonne National Laboratory, Islam, E. S., Prada, D. N., Vijayagopal, R., Mansour, C., Philips, P., Kim, N., Alhajjar, M., & Rousseau, A. (2023, October). Detailed Simulation Study to Evaluate Future Transportation Decarbonization Potential. Vehicle & Mobility Systems Department - Argonne National Laboratory. https://vms.taps.anl.gov/research-highlights/vehicle-technologies/u-s-doe-vto-hfto-r-d-benefits/ | F13: 2023 | AB13: =$AA$11*BT14 -> 1.5213343 | AC13: =$AA$11*BU14 -> 1.5362862 | AD13: =$AA$11*BV14 -> 1.5488096 | AE13: =$AA$11*BW14 -> 1.6032121 | AF13: =$AA$11*BX14 -> 1.6111943 | AG13: =$AA$11*BY14 -> 1.6185566 | AH13: =$AA$11*BZ14 -> 1.6253684 | AJ13: [btkm/PJ] Vehicle class fuel efficiency aggregated from Islam et al. 2023 low uncertainty projections by Class 8 truck types. Aggregation was done with StatCan Table: 23-10-0219-01 shipment type shares (local vs. long distance). Values were harmonized using provincial load factors. Energy consumption based on drive cycle combinations as prescribed in the EPA final rule regulatory documents for MHDVs (EPA & NHTSA, 2016). | AK13: 3 | AL13: 1 | AM13: 1 | AN13: 3 | AO13: 1 | AS13: 8 | AT13: Class 8 (sleeper cab) | BE13: Heavy-duty Trucks (Class 8) long-haul | BT13: 2021 | BU13: 2025 | BV13: 2030 | BW13: 2035 | BX13: 2040 | BY13: 2045 | BZ13: 2050
A14: T_HDV_T_LH_BEV_FSTCHRG_N | B14: T_elc_hdv_t_lh_chrg_fstchrg | C14: T_annual_tkm_hdv_t_lh | D14: ON | E14: Argonne National Laboratory, Islam, E. S., Prada, D. N., Vijayagopal, R., Mansour, C., Philips, P., Kim, N., Alhajjar, M., & Rousseau, A. (2023, October). Detailed Simulation Study to Evaluate Future Transportation Decarbonization Potential. Vehicle & Mobility Systems Department - Argonne National Laboratory. https://vms.taps.anl.gov/research-highlights/vehicle-technologies/u-s-doe-vto-hfto-r-d-benefits/ | F14: 2023 | AB14: =$AA$11*BT15 -> 1.5213343 | AC14: =$AA$11*BU15 -> 1.5362862 | AD14: =$AA$11*BV15 -> 1.5488096 | AE14: =$AA$11*BW15 -> 1.6032121 | AF14: =$AA$11*BX15 -> 1.6111943 | AG14: =$AA$11*BY15 -> 1.6185566 | AH14: =$AA$11*BZ15 -> 1.6253684 | AJ14: [btkm/PJ] | AS14: 8 | AT14: CI | AU14: {=1/AVERAGE(_xlfn._xlws.FILTER('Autonomie 2023 MHDV'!$AR:$AR,(NOT(ISERROR(SEARCH("_ci_", 'Autonomie 2023 MHDV'!$G:$G))))*('Autonomie 2023 MHDV'!$A:$A="Conv")*('Autonomie 2023 MHDV'!$B:$B=AU$5)*('Autonomie 2023 MHDV'!$F:$F=$AS14)*('Autonomie 2023 MHDV'!$E:$E="Sleeper")))} -> 0.07688578 | AV14: {=1/AVERAGE(_xlfn._xlws.FILTER('Autonomie 2023 MHDV'!$AR:$AR,(NOT(ISERROR(SEARCH("_ci_", 'Autonomie 2023 MHDV'!$G:$G))))*('Autonomie 2023 MHDV'!$A:$A="Conv")*('Autonomie 2023 MHDV'!$B:$B=AV$5)*('Autonomie 2023 MHDV'!$F:$F=$AS14)*('Autonomie 2023 MHDV'!$E:$E="Sleeper")))} -> 0.084647818 | AW14: {=1/AVERAGE(_xlfn._xlws.FILTER('Autonomie 2023 MHDV'!$AR:$AR,(NOT(ISERROR(SEARCH("_ci_", 'Autonomie 2023 MHDV'!$G:$G))))*('Autonomie 2023 MHDV'!$A:$A="Conv")*('Autonomie 2023 MHDV'!$B:$B=AW$5)*('Autonomie 2023 MHDV'!$F:$F=$AS14)*('Autonomie 2023 MHDV'!$E:$E="Sleeper")))} -> 0.093065088 | AX14: {=1/AVERAGE(_xlfn._xlws.FILTER('Autonomie 2023 MHDV'!$AR:$AR,(NOT(ISERROR(SEARCH("_ci_", 'Autonomie 2023 MHDV'!$G:$G))))*('Autonomie 2023 MHDV'!$A:$A="Conv")*('Autonomie 2023 MHDV'!$B:$B=AX$5)*('Autonomie 2023 MHDV'!$F:$F=$AS14)*('Autonomie 2023 MHDV'!$E:$E="Sleeper")))} -> 0.10051686 | AY14: =($BA14-$AX14)/3 + AX14 -> 0.10474874 | AZ14: =($BA14-$AX14)/3 + AY14 -> 0.10898063 | BA14: {=1/AVERAGE(_xlfn._xlws.FILTER('Autonomie 2023 MHDV'!$AR:$AR,(NOT(ISERROR(SEARCH("_ci_", 'Autonomie 2023 MHDV'!$G:$G))))*('Autonomie 2023 MHDV'!$A:$A="Conv")*('Autonomie 2023 MHDV'!$B:$B=BA$5)*('Autonomie 2023 MHDV'!$F:$F=$AS14)*('Autonomie 2023 MHDV'!$E:$E="Sleeper")))} -> 0.11321252 | BB14: =(BA14-AU14)/AU14 -> 0.47247664 | BE14: DSL | BF14: =AU14/$AU14 -> 1 | BG14: =AV14/$AU14 -> 1.1009554 | BH14: =AW14/$AU14 -> 1.210433 | BI14: =AX14/$AU14 -> 1.307353 | BJ14: =AY14/$AU14 -> 1.3623942 | BK14: =AZ14/$AU14 -> 1.4174354 | BL14: =BA14/$AU14 -> 1.4724766 | BS14: T_HDV_T_LH_BEV_LRGBATT_N | BT14: =BF$17/'Payload capacity penalty'!C10 -> 2.2820156 | BU14: =BG$17/'Payload capacity penalty'!D10 -> 2.3044436 | BV14: =BH$17/'Payload capacity penalty'!E10 -> 2.3232288 | BW14: =BI$17/'Payload capacity penalty'!F10 -> 2.4048331 | BX14: =BJ$17/'Payload capacity penalty'!G10 -> 2.4168065 | BY14: =BK$17/'Payload capacity penalty'!H10 -> 2.4278499 | BZ14: =BL$17/'Payload capacity penalty'!I10 -> 2.4380678
A15: T_HDV_T_LH_BEV_ERDS1_N | B15: T_elc_hdv_t_lh_chrg_erds1 | C15: T_annual_tkm_hdv_t_lh | D15: ON | E15: Argonne National Laboratory, Islam, E. S., Prada, D. N., Vijayagopal, R., Mansour, C., Philips, P., Kim, N., Alhajjar, M., & Rousseau, A. (2023, October). Detailed Simulation Study to Evaluate Future Transportation Decarbonization Potential. Vehicle & Mobility Systems Department - Argonne National Laboratory. https://vms.taps.anl.gov/research-highlights/vehicle-technologies/u-s-doe-vto-hfto-r-d-benefits/ | F15: 2023 | AB15: =$AA$11*BT16 -> 1.5213343 | AC15: =$AA$11*BU16 -> 1.5362862 | AD15: =$AA$11*BV16 -> 1.5488096 | AE15: =$AA$11*BW16 -> 1.6032121 | AF15: =$AA$11*BX16 -> 1.6111943 | AG15: =$AA$11*BY16 -> 1.6185566 | AH15: =$AA$11*BZ16 -> 1.6253684 | AJ15: [btkm/PJ] | AS15: 8 | AT15: ParHEV | AU15: {=1/AVERAGE(_xlfn._xlws.FILTER('Autonomie 2023 MHDV'!$AR:$AR,(NOT(ISERROR(SEARCH("_ci_", 'Autonomie 2023 MHDV'!$G:$G))))*('Autonomie 2023 MHDV'!$A:$A=$AT15)*('Autonomie 2023 MHDV'!$B:$B=AU$5)*('Autonomie 2023 MHDV'!$F:$F=$AS15)*('Autonomie 2023 MHDV'!$E:$E="Sleeper")))} -> 0.077231327 | AV15: {=1/AVERAGE(_xlfn._xlws.FILTER('Autonomie 2023 MHDV'!$AR:$AR,(NOT(ISERROR(SEARCH("_ci_", 'Autonomie 2023 MHDV'!$G:$G))))*('Autonomie 2023 MHDV'!$A:$A=$AT15)*('Autonomie 2023 MHDV'!$B:$B=AV$5)*('Autonomie 2023 MHDV'!$F:$F=$AS15)*('Autonomie 2023 MHDV'!$E:$E="Sleeper")))} -> 0.085586243 | AW15: {=1/AVERAGE(_xlfn._xlws.FILTER('Autonomie 2023 MHDV'!$AR:$AR,(NOT(ISERROR(SEARCH("_ci_", 'Autonomie 2023 MHDV'!$G:$G))))*('Autonomie 2023 MHDV'!$A:$A=$AT15)*('Autonomie 2023 MHDV'!$B:$B=AW$5)*('Autonomie 2023 MHDV'!$F:$F=$AS15)*('Autonomie 2023 MHDV'!$E:$E="Sleeper")))} -> 0.095490496 | AX15: {=1/AVERAGE(_xlfn._xlws.FILTER('Autonomie 2023 MHDV'!$AR:$AR,(NOT(ISERROR(SEARCH("_ci_", 'Autonomie 2023 MHDV'!$G:$G))))*('Autonomie 2023 MHDV'!$A:$A=$AT15)*('Autonomie 2023 MHDV'!$B:$B=AX$5)*('Autonomie 2023 MHDV'!$F:$F=$AS15)*('Autonomie 2023 MHDV'!$E:$E="Sleeper")))} -> 0.10436469 | AY15: =($BA15-$AX15)/3 + AX15 -> 0.10951711 | AZ15: =($BA15-$AX15)/3 + AY15 -> 0.11466953 | BA15: {=1/AVERAGE(_xlfn._xlws.FILTER('Autonomie 2023 MHDV'!$AR:$AR,(NOT(ISERROR(SEARCH("_ci_", 'Autonomie 2023 MHDV'!$G:$G))))*('Autonomie 2023 MHDV'!$A:$A=$AT15)*('Autonomie 2023 MHDV'!$B:$B=BA$5)*('Autonomie 2023 MHDV'!$F:$F=$AS15)*('Autonomie 2023 MHDV'!$E:$E="Sleeper")))} -> 0.11982195 | BB15: =(BA15-AU15)/AU15 -> 0.55146819 | BE15: ParHEV† | BF15: =AU15/AU$14 -> 1.0044943 | BG15: =AV15/AV$14 -> 1.0110862 | BH15: =AW15/AW$14 -> 1.0260614 | BI15: =AX15/AX$14 -> 1.0382804 | BJ15: =AY15/AY$14 -> 1.0455219 | BK15: =AZ15/AZ$14 -> 1.052201 | BL15: =BA15/BA$14 -> 1.0583807 | BS15: T_HDV_T_LH_BEV_FSTCHRG_N | BT15: =BF$17/'Payload capacity penalty'!C11 -> 2.2820156 | BU15: =BG$17/'Payload capacity penalty'!D11 -> 2.3044436 | BV15: =BH$17/'Payload capacity penalty'!E11 -> 2.3232288 | BW15: =BI$17/'Payload capacity penalty'!F11 -> 2.4048331 | BX15: =BJ$17/'Payload capacity penalty'!G11 -> 2.4168065 | BY15: =BK$17/'Payload capacity penalty'!H11 -> 2.4278499 | BZ15: =BL$17/'Payload capacity penalty'!I11 -> 2.4380678
A16: T_HDV_T_LH_BEV_ERDS2_N | B16: T_elc_hdv_t_lh_chrg_erds2 | C16: T_annual_tkm_hdv_t_lh | D16: ON | E16: Argonne National Laboratory, Islam, E. S., Prada, D. N., Vijayagopal, R., Mansour, C., Philips, P., Kim, N., Alhajjar, M., & Rousseau, A. (2023, October). Detailed Simulation Study to Evaluate Future Transportation Decarbonization Potential. Vehicle & Mobility Systems Department - Argonne National Laboratory. https://vms.taps.anl.gov/research-highlights/vehicle-technologies/u-s-doe-vto-hfto-r-d-benefits/ | F16: 2023 | AB16: =$AA$11*BT17 -> 1.5213343 | AC16: =$AA$11*BU17 -> 1.5362862 | AD16: =$AA$11*BV17 -> 1.5488096 | AE16: =$AA$11*BW17 -> 1.6032121 | AF16: =$AA$11*BX17 -> 1.6111943 | AG16: =$AA$11*BY17 -> 1.6185566 | AH16: =$AA$11*BZ17 -> 1.6253684 | AJ16: [btkm/PJ] | AS16: 8 | AT16: SeriesPHEV | AU16: {=1/AVERAGE(_xlfn._xlws.FILTER('Autonomie 2023 MHDV'!$AR:$AR,(NOT(ISERROR(SEARCH("_ci_", 'Autonomie 2023 MHDV'!$G:$G))))*('Autonomie 2023 MHDV'!$A:$A=$AT16)*('Autonomie 2023 MHDV'!$B:$B=AU$5)*('Autonomie 2023 MHDV'!$F:$F=$AS16)*('Autonomie 2023 MHDV'!$E:$E="Sleeper")))} -> 0.11877116 | AV16: {=1/AVERAGE(_xlfn._xlws.FILTER('Autonomie 2023 MHDV'!$AR:$AR,(NOT(ISERROR(SEARCH("_ci_", 'Autonomie 2023 MHDV'!$G:$G))))*('Autonomie 2023 MHDV'!$A:$A=$AT16)*('Autonomie 2023 MHDV'!$B:$B=AV$5)*('Autonomie 2023 MHDV'!$F:$F=$AS16)*('Autonomie 2023 MHDV'!$E:$E="Sleeper")))} -> 0.13122322 | AW16: {=1/AVERAGE(_xlfn._xlws.FILTER('Autonomie 2023 MHDV'!$AR:$AR,(NOT(ISERROR(SEARCH("_ci_", 'Autonomie 2023 MHDV'!$G:$G))))*('Autonomie 2023 MHDV'!$A:$A=$AT16)*('Autonomie 2023 MHDV'!$B:$B=AW$5)*('Autonomie 2023 MHDV'!$F:$F=$AS16)*('Autonomie 2023 MHDV'!$E:$E="Sleeper")))} -> 0.14600125 | AX16: {=1/AVERAGE(_xlfn._xlws.FILTER('Autonomie 2023 MHDV'!$AR:$AR,(NOT(ISERROR(SEARCH("_ci_", 'Autonomie 2023 MHDV'!$G:$G))))*('Autonomie 2023 MHDV'!$A:$A=$AT16)*('Autonomie 2023 MHDV'!$B:$B=AX$5)*('Autonomie 2023 MHDV'!$F:$F=$AS16)*('Autonomie 2023 MHDV'!$E:$E="Sleeper")))} -> 0.16255392 | AY16: =($BA16-$AX16)/3 + AX16 -> 0.17035768 | AZ16: =($BA16-$AX16)/3 + AY16 -> 0.17816144 | BA16: {=1/AVERAGE(_xlfn._xlws.FILTER('Autonomie 2023 MHDV'!$AR:$AR,(NOT(ISERROR(SEARCH("_ci_", 'Autonomie 2023 MHDV'!$G:$G))))*('Autonomie 2023 MHDV'!$A:$A=$AT16)*('Autonomie 2023 MHDV'!$B:$B=BA$5)*('Autonomie 2023 MHDV'!$F:$F=$AS16)*('Autonomie 2023 MHDV'!$E:$E="Sleeper")))} -> 0.18596519 | BB16: =(BA16-AU16)/AU16 -> 0.56574362 | BE16: SeriesPHEV† | BF16: =AU16/AU$14 -> 1.5447741 | BG16: =AV16/AV$14 -> 1.5502257 | BH16: =AW16/AW$14 -> 1.5688079 | BI16: =AX16/AX$14 -> 1.6171807 | BJ16: =AY16/AY$14 -> 1.6263458 | BK16: =AZ16/AZ$14 -> 1.6347991 | BL16: =BA16/BA$14 -> 1.6426204 | BS16: T_HDV_T_LH_BEV_ERDS1_N | BT16: =BF$17/'Payload capacity penalty'!C12 -> 2.2820156 | BU16: =BG$17/'Payload capacity penalty'!D12 -> 2.3044436 | BV16: =BH$17/'Payload capacity penalty'!E12 -> 2.3232288 | BW16: =BI$17/'Payload capacity penalty'!F12 -> 2.4048331 | BX16: =BJ$17/'Payload capacity penalty'!G12 -> 2.4168065 | BY16: =BK$17/'Payload capacity penalty'!H12 -> 2.4278499 | BZ16: =BL$17/'Payload capacity penalty'!I12 -> 2.4380678
A17: T_HDV_T_LH_BEV_ERDS3_N | B17: T_elc_hdv_t_lh_chrg_erds3 | C17: T_annual_tkm_hdv_t_lh | D17: ON | E17: Argonne National Laboratory, Islam, E. S., Prada, D. N., Vijayagopal, R., Mansour, C., Philips, P., Kim, N., Alhajjar, M., & Rousseau, A. (2023, October). Detailed Simulation Study to Evaluate Future Transportation Decarbonization Potential. Vehicle & Mobility Systems Department - Argonne National Laboratory. https://vms.taps.anl.gov/research-highlights/vehicle-technologies/u-s-doe-vto-hfto-r-d-benefits/ | F17: 2023 | AB17: =$AA$11*BT18 -> 1.5213343 | AC17: =$AA$11*BU18 -> 1.5362862 | AD17: =$AA$11*BV18 -> 1.5488096 | AE17: =$AA$11*BW18 -> 1.6032121 | AF17: =$AA$11*BX18 -> 1.6111943 | AG17: =$AA$11*BY18 -> 1.6185566 | AH17: =$AA$11*BZ18 -> 1.6253684 | AJ17: [btkm/PJ] | AS17: 8 | AT17: BEV | AU17: {=1/AVERAGE(_xlfn._xlws.FILTER('Autonomie 2023 MHDV'!$AR:$AR,('Autonomie 2023 MHDV'!$A:$A=$AT17)*('Autonomie 2023 MHDV'!$B:$B=AU$5)*('Autonomie 2023 MHDV'!$F:$F=$AS17)*('Autonomie 2023 MHDV'!$E:$E="Sleeper")))} -> 0.17545455 | AV17: {=1/AVERAGE(_xlfn._xlws.FILTER('Autonomie 2023 MHDV'!$AR:$AR,('Autonomie 2023 MHDV'!$A:$A=$AT17)*('Autonomie 2023 MHDV'!$B:$B=AV$5)*('Autonomie 2023 MHDV'!$F:$F=$AS17)*('Autonomie 2023 MHDV'!$E:$E="Sleeper")))} -> 0.19506612 | AW17: {=1/AVERAGE(_xlfn._xlws.FILTER('Autonomie 2023 MHDV'!$AR:$AR,('Autonomie 2023 MHDV'!$A:$A=$AT17)*('Autonomie 2023 MHDV'!$B:$B=AW$5)*('Autonomie 2023 MHDV'!$F:$F=$AS17)*('Autonomie 2023 MHDV'!$E:$E="Sleeper")))} -> 0.2162115 | AX17: {=1/AVERAGE(_xlfn._xlws.FILTER('Autonomie 2023 MHDV'!$AR:$AR,('Autonomie 2023 MHDV'!$A:$A=$AT17)*('Autonomie 2023 MHDV'!$B:$B=AX$5)*('Autonomie 2023 MHDV'!$F:$F=$AS17)*('Autonomie 2023 MHDV'!$E:$E="Sleeper")))} -> 0.24172627 | AY17: =($BA17-$AX17)/3 + AX17 -> 0.25315744 | AZ17: =($BA17-$AX17)/3 + AY17 -> 0.26458861 | BA17: {=1/AVERAGE(_xlfn._xlws.FILTER('Autonomie 2023 MHDV'!$AR:$AR,('Autonomie 2023 MHDV'!$A:$A=$AT17)*('Autonomie 2023 MHDV'!$B:$B=BA$5)*('Autonomie 2023 MHDV'!$F:$F=$AS17)*('Autonomie 2023 MHDV'!$E:$E="Sleeper")))} -> 0.27601979 | BB17: =(BA17-AU17)/AU17 -> 0.57316975 | BE17: BEV† | BF17: =AU17/AU$14 -> 2.2820156 | BG17: =AV17/AV$14 -> 2.3044436 | BH17: =AW17/AW$14 -> 2.3232288 | BI17: =AX17/AX$14 -> 2.4048331 | BJ17: =AY17/AY$14 -> 2.4168065 | BK17: =AZ17/AZ$14 -> 2.4278499 | BL17: =BA17/BA$14 -> 2.4380678 | BS17: T_HDV_T_LH_BEV_ERDS2_N | BT17: =BF$17/'Payload capacity penalty'!C13 -> 2.2820156 | BU17: =BG$17/'Payload capacity penalty'!D13 -> 2.3044436 | BV17: =BH$17/'Payload capacity penalty'!E13 -> 2.3232288 | BW17: =BI$17/'Payload capacity penalty'!F13 -> 2.4048331 | BX17: =BJ$17/'Payload capacity penalty'!G13 -> 2.4168065 | BY17: =BK$17/'Payload capacity penalty'!H13 -> 2.4278499 | BZ17: =BL$17/'Payload capacity penalty'!I13 -> 2.4380678
A18: T_HDV_T_LH_BEV_ERDS4_N | B18: T_elc_hdv_t_lh_chrg_erds4 | C18: T_annual_tkm_hdv_t_lh | D18: ON | E18: Argonne National Laboratory, Islam, E. S., Prada, D. N., Vijayagopal, R., Mansour, C., Philips, P., Kim, N., Alhajjar, M., & Rousseau, A. (2023, October). Detailed Simulation Study to Evaluate Future Transportation Decarbonization Potential. Vehicle & Mobility Systems Department - Argonne National Laboratory. https://vms.taps.anl.gov/research-highlights/vehicle-technologies/u-s-doe-vto-hfto-r-d-benefits/ | F18: 2023 | AB18: =$AA$11*BT19 -> 1.5213343 | AC18: =$AA$11*BU19 -> 1.5362862 | AD18: =$AA$11*BV19 -> 1.5488096 | AE18: =$AA$11*BW19 -> 1.6032121 | AF18: =$AA$11*BX19 -> 1.6111943 | AG18: =$AA$11*BY19 -> 1.6185566 | AH18: =$AA$11*BZ19 -> 1.6253684 | AJ18: [btkm/PJ] | AS18: 8 | AT18: FCEV | AU18: {=1/AVERAGE(_xlfn._xlws.FILTER('Autonomie 2023 MHDV'!$AR:$AR,('Autonomie 2023 MHDV'!$A:$A=$AT18)*('Autonomie 2023 MHDV'!$B:$B=AU$5)*('Autonomie 2023 MHDV'!$F:$F=$AS18)*('Autonomie 2023 MHDV'!$E:$E="Sleeper")))} -> 0.087698061 | AV18: {=1/AVERAGE(_xlfn._xlws.FILTER('Autonomie 2023 MHDV'!$AR:$AR,('Autonomie 2023 MHDV'!$A:$A=$AT18)*('Autonomie 2023 MHDV'!$B:$B=AV$5)*('Autonomie 2023 MHDV'!$F:$F=$AS18)*('Autonomie 2023 MHDV'!$E:$E="Sleeper")))} -> 0.099869277 | AW18: {=1/AVERAGE(_xlfn._xlws.FILTER('Autonomie 2023 MHDV'!$AR:$AR,('Autonomie 2023 MHDV'!$A:$A=$AT18)*('Autonomie 2023 MHDV'!$B:$B=AW$5)*('Autonomie 2023 MHDV'!$F:$F=$AS18)*('Autonomie 2023 MHDV'!$E:$E="Sleeper")))} -> 0.11245014 | AX18: {=1/AVERAGE(_xlfn._xlws.FILTER('Autonomie 2023 MHDV'!$AR:$AR,('Autonomie 2023 MHDV'!$A:$A=$AT18)*('Autonomie 2023 MHDV'!$B:$B=AX$5)*('Autonomie 2023 MHDV'!$F:$F=$AS18)*('Autonomie 2023 MHDV'!$E:$E="Sleeper")))} -> 0.1255883 | AY18: =($BA18-$AX18)/3 + AX18 -> 0.13253586 | AZ18: =($BA18-$AX18)/3 + AY18 -> 0.13948342 | BA18: {=1/AVERAGE(_xlfn._xlws.FILTER('Autonomie 2023 MHDV'!$AR:$AR,('Autonomie 2023 MHDV'!$A:$A=$AT18)*('Autonomie 2023 MHDV'!$B:$B=BA$5)*('Autonomie 2023 MHDV'!$F:$F=$AS18)*('Autonomie 2023 MHDV'!$E:$E="Sleeper")))} -> 0.14643098 | BB18: =(BA18-AU18)/AU18 -> 0.66971744 | BE18: FCEV† | BF18: =AU18/AU$14 -> 1.1406278 | BG18: =AV18/AV$14 -> 1.179821 | BH18: =AW18/AW$14 -> 1.2082956 | BI18: =AX18/AX$14 -> 1.2494253 | BJ18: =AY18/AY$14 -> 1.265274 | BK18: =AZ18/AZ$14 -> 1.2798919 | BL18: =BA18/BA$14 -> 1.2934169 | BS18: T_HDV_T_LH_BEV_ERDS3_N | BT18: =BF$17/'Payload capacity penalty'!C14 -> 2.2820156 | BU18: =BG$17/'Payload capacity penalty'!D14 -> 2.3044436 | BV18: =BH$17/'Payload capacity penalty'!E14 -> 2.3232288 | BW18: =BI$17/'Payload capacity penalty'!F14 -> 2.4048331 | BX18: =BJ$17/'Payload capacity penalty'!G14 -> 2.4168065 | BY18: =BK$17/'Payload capacity penalty'!H14 -> 2.4278499 | BZ18: =BL$17/'Payload capacity penalty'!I14 -> 2.4380678
A19: T_HDV_T_LH_BEV_ERDS5_N | B19: T_elc_hdv_t_lh_chrg_erds5 | C19: T_annual_tkm_hdv_t_lh | D19: ON | E19: Argonne National Laboratory, Islam, E. S., Prada, D. N., Vijayagopal, R., Mansour, C., Philips, P., Kim, N., Alhajjar, M., & Rousseau, A. (2023, October). Detailed Simulation Study to Evaluate Future Transportation Decarbonization Potential. Vehicle & Mobility Systems Department - Argonne National Laboratory. https://vms.taps.anl.gov/research-highlights/vehicle-technologies/u-s-doe-vto-hfto-r-d-benefits/ | F19: 2023 | AB19: =$AA$11*BT20 -> 1.5213343 | AC19: =$AA$11*BU20 -> 1.5362862 | AD19: =$AA$11*BV20 -> 1.5488096 | AE19: =$AA$11*BW20 -> 1.6032121 | AF19: =$AA$11*BX20 -> 1.6111943 | AG19: =$AA$11*BY20 -> 1.6185566 | AH19: =$AA$11*BZ20 -> 1.6253684 | AJ19: [btkm/PJ] | AS19: 8 | AT19: FCHEV | AU19: {=1/AVERAGE(_xlfn._xlws.FILTER('Autonomie 2023 MHDV'!$AR:$AR,('Autonomie 2023 MHDV'!$A:$A=$AT19)*('Autonomie 2023 MHDV'!$B:$B=AU$5)*('Autonomie 2023 MHDV'!$F:$F=$AS19)*('Autonomie 2023 MHDV'!$E:$E="Sleeper")))} -> 0.08508394 | AV19: {=1/AVERAGE(_xlfn._xlws.FILTER('Autonomie 2023 MHDV'!$AR:$AR,('Autonomie 2023 MHDV'!$A:$A=$AT19)*('Autonomie 2023 MHDV'!$B:$B=AV$5)*('Autonomie 2023 MHDV'!$F:$F=$AS19)*('Autonomie 2023 MHDV'!$E:$E="Sleeper")))} -> 0.096666379 | AW19: {=1/AVERAGE(_xlfn._xlws.FILTER('Autonomie 2023 MHDV'!$AR:$AR,('Autonomie 2023 MHDV'!$A:$A=$AT19)*('Autonomie 2023 MHDV'!$B:$B=AW$5)*('Autonomie 2023 MHDV'!$F:$F=$AS19)*('Autonomie 2023 MHDV'!$E:$E="Sleeper")))} -> 0.10880513 | AX19: {=1/AVERAGE(_xlfn._xlws.FILTER('Autonomie 2023 MHDV'!$AR:$AR,('Autonomie 2023 MHDV'!$A:$A=$AT19)*('Autonomie 2023 MHDV'!$B:$B=AX$5)*('Autonomie 2023 MHDV'!$F:$F=$AS19)*('Autonomie 2023 MHDV'!$E:$E="Sleeper")))} -> 0.12156223 | AY19: =($BA19-$AX19)/3 + AX19 -> 0.12836806 | AZ19: =($BA19-$AX19)/3 + AY19 -> 0.13517388 | BA19: {=1/AVERAGE(_xlfn._xlws.FILTER('Autonomie 2023 MHDV'!$AR:$AR,('Autonomie 2023 MHDV'!$A:$A=$AT19)*('Autonomie 2023 MHDV'!$B:$B=BA$5)*('Autonomie 2023 MHDV'!$F:$F=$AS19)*('Autonomie 2023 MHDV'!$E:$E="Sleeper")))} -> 0.1419797 | BB19: =(BA19-AU19)/AU19 -> 0.6687015 | BE19: FCHEV† | BF19: =AU19/AU$14 -> 1.1066278 | BG19: =AV19/AV$14 -> 1.1419831 | BH19: =AW19/AW$14 -> 1.1691294 | BI19: =AX19/AX$14 -> 1.2093716 | BJ19: =AY19/AY$14 -> 1.2254854 | BK19: =AZ19/AZ$14 -> 1.2403477 | BL19: =BA19/BA$14 -> 1.254099 | BS19: T_HDV_T_LH_BEV_ERDS4_N | BT19: =BF$17/'Payload capacity penalty'!C15 -> 2.2820156 | BU19: =BG$17/'Payload capacity penalty'!D15 -> 2.3044436 | BV19: =BH$17/'Payload capacity penalty'!E15 -> 2.3232288 | BW19: =BI$17/'Payload capacity penalty'!F15 -> 2.4048331 | BX19: =BJ$17/'Payload capacity penalty'!G15 -> 2.4168065 | BY19: =BK$17/'Payload capacity penalty'!H15 -> 2.4278499 | BZ19: =BL$17/'Payload capacity penalty'!I15 -> 2.4380678
A20: T_HDV_T_LH_FCEV_N | B20: T_h2_hdv_t_lh | C20: T_annual_tkm_hdv_t_lh | D20: ON | E20: Argonne National Laboratory, Islam, E. S., Prada, D. N., Vijayagopal, R., Mansour, C., Philips, P., Kim, N., Alhajjar, M., & Rousseau, A. (2023, October). Detailed Simulation Study to Evaluate Future Transportation Decarbonization Potential. Vehicle & Mobility Systems Department - Argonne National Laboratory. https://vms.taps.anl.gov/research-highlights/vehicle-technologies/u-s-doe-vto-hfto-r-d-benefits/ | F20: 2023 | AB20: =$AA$11*BT21 -> 0.76041384 | AC20: =$AA$11*BU21 -> 0.78654248 | AD20: =$AA$11*BV21 -> 0.80552542 | AE20: =$AA$11*BW21 -> 0.83294502 | AF20: =$AA$11*BX21 -> 0.84351077 | AG20: =$AA$11*BY21 -> 0.85325596 | AH20: =$AA$11*BZ21 -> 0.86227259 | AJ20: [btkm/PJ] Vehicle class fuel efficiency aggregated from Islam et al. 2023 low uncertainty projections by Class 8 truck types. Aggregation was done with StatCan Table: 23-10-0219-01 shipment type shares (local vs. long distance). Values were harmonized using provincial load factors. Energy consumption based on drive cycle combinations as prescribed in the EPA final rule regulatory documents for MHDVs (EPA & NHTSA, 2016).AK5 | AK20: 3 | AL20: 1 | AM20: 1 | AN20: 3 | AO20: 1 | AT20: †2040-2045 are linearly interpolated. Energy consumption based on drive cycle combinations as prescribed in the EPA final rule regulatory documents for MHDVs - https://www.epa.gov/regulations-emissions-vehicles-and-engines/final-rule-phase-2-greenhouse-gas-emissions-standards | BS20: T_HDV_T_LH_BEV_ERDS5_N | BT20: =BF$17/'Payload capacity penalty'!C16 -> 2.2820156 | BU20: =BG$17/'Payload capacity penalty'!D16 -> 2.3044436 | BV20: =BH$17/'Payload capacity penalty'!E16 -> 2.3232288 | BW20: =BI$17/'Payload capacity penalty'!F16 -> 2.4048331 | BX20: =BJ$17/'Payload capacity penalty'!G16 -> 2.4168065 | BY20: =BK$17/'Payload capacity penalty'!H16 -> 2.4278499 | BZ20: =BL$17/'Payload capacity penalty'!I16 -> 2.4380678
A21: T_HDV_T_DSL_EX | B21: T_dsl | C21: T_D_tkm_hdv_t | D21: ON | E21: Natural Resources Canada. (2023b). Transportation Sector – Ontario. Government of Canada, Natural Resources Canada. https://oee.nrcan.gc.ca/corporate/statistics/neud/dpa/menus/trends/comprehensive/trends_tran_on.cfm | F21: 2023 | L21: =L$11 -> 0.60223669 | Q21: =Q$11 -> 0.55452089 | V21: =V$11 -> 0.701195 | AA21: =AA$11 -> 0.66666253 | AJ21: [btkm/PJ] Vehicle class fuel efficiency derived from provincial fleet fuel efficiency. Reported values are in L of gasoline eq. Values were harmonized using provincial load factors. Fuel HHVs were used for unit conversion. | AK21: 2 | AL21: 1 | AM21: 1 | AN21: 1 | AO21: 1 | BE21: †New technologies are indexed to deployed technologies. | BS21: T_HDV_T_LH_FCEV_N | BT21: =BF18/'Payload capacity penalty'!C17 -> 1.1406278 | BU21: =BG18/'Payload capacity penalty'!D17 -> 1.179821 | BV21: =BH18/'Payload capacity penalty'!E17 -> 1.2082956 | BW21: =BI18/'Payload capacity penalty'!F17 -> 1.2494253 | BX21: =BJ18/'Payload capacity penalty'!G17 -> 1.265274 | BY21: =BK18/'Payload capacity penalty'!H17 -> 1.2798919 | BZ21: =BL18/'Payload capacity penalty'!I17 -> 1.2934169
A22: T_HDV_T_DSL_N | B22: T_dsl | C22: T_D_tkm_hdv_t | D22: ON | E22: Argonne National Laboratory, Islam, E. S., Prada, D. N., Vijayagopal, R., Mansour, C., Philips, P., Kim, N., Alhajjar, M., & Rousseau, A. (2023, October). Detailed Simulation Study to Evaluate Future Transportation Decarbonization Potential. Vehicle & Mobility Systems Department - Argonne National Laboratory. https://vms.taps.anl.gov/research-highlights/vehicle-technologies/u-s-doe-vto-hfto-r-d-benefits/ | F22: 2023 | AB22: =$AA$21*BF7 -> 0.66666253 | AC22: =$AA$21*BG7 -> 0.72887386 | AD22: =$AA$21*BH7 -> 0.78834198 | AE22: =$AA$21*BI7 -> 0.8448586 | AF22: =$AA$21*BJ7 -> 0.86712266 | AG22: =$AA$21*BK7 -> 0.88938671 | AH22: =$AA$21*BL7 -> 0.91165076 | AJ22: Vehicle class fuel efficiency aggregated from Islam et al. 2023 low uncertainty projections by Class 8 truck types. Aggregation was done with StatCan Table: 23-10-0219-01 shipment type shares (local vs. long distance). Values were harmonized using provincial load factors. Energy consumption based on drive cycle combinations as prescribed in the EPA final rule regulatory documents for MHDVs (EPA & NHTSA, 2016). | AK22: 3 | AL22: 1 | AM22: 1 | AN22: 3 | AO22: 1
A23: T_HDV_T_DSL_HEV_N | B23: T_dsl | C23: T_D_tkm_hdv_t | D23: ON | E23: Argonne National Laboratory, Islam, E. S., Prada, D. N., Vijayagopal, R., Mansour, C., Philips, P., Kim, N., Alhajjar, M., & Rousseau, A. (2023, October). Detailed Simulation Study to Evaluate Future Transportation Decarbonization Potential. Vehicle & Mobility Systems Department - Argonne National Laboratory. https://vms.taps.anl.gov/research-highlights/vehicle-technologies/u-s-doe-vto-hfto-r-d-benefits/ | F23: 2023 | AB23: =$AA$21*BF8 -> 0.70105753 | AC23: =$AA$21*BG8 -> 0.71327193 | AD23: =$AA$21*BH8 -> 0.7215696 | AE23: =$AA$21*BI8 -> 0.73414112 | AF23: =$AA$21*BJ8 -> 0.73996091 | AG23: =$AA$21*BK8 -> 0.74548932 | AH23: =$AA$21*BL8 -> 0.75074771 | AJ23: Vehicle class fuel efficiency aggregated from Islam et al. 2023 low uncertainty projections by Class 8 truck types. Aggregation was done with StatCan Table: 23-10-0219-01 shipment type shares (local vs. long distance). Values were harmonized using provincial load factors. Energy consumption based on drive cycle combinations as prescribed in the EPA final rule regulatory documents for MHDVs (EPA & NHTSA, 2016). | AK23: 3 | AL23: 1 | AM23: 1 | AN23: 3 | AO23: 1
A24: T_HDV_T_DSL_PHEV_N | B24: T_dsl_elc_hdv | C24: T_D_tkm_hdv_t | D24: ON | E24: Argonne National Laboratory, Islam, E. S., Prada, D. N., Vijayagopal, R., Mansour, C., Philips, P., Kim, N., Alhajjar, M., & Rousseau, A. (2023, October). Detailed Simulation Study to Evaluate Future Transportation Decarbonization Potential. Vehicle & Mobility Systems Department - Argonne National Laboratory. https://vms.taps.anl.gov/research-highlights/vehicle-technologies/u-s-doe-vto-hfto-r-d-benefits/ | F24: 2023 | AB24: =$AA$21*BF9 -> 1.172835 | AC24: =$AA$21*BG9 -> 1.1881881 | AD24: =$AA$21*BH9 -> 1.2024507 | AE24: =$AA$21*BI9 -> 1.2383721 | AF24: =$AA$21*BJ9 -> 1.2559877 | AG24: =$AA$21*BK9 -> 1.2727214 | AH24: =$AA$21*BL9 -> 1.2886378 | AJ24: Vehicle class fuel efficiency aggregated from Islam et al. 2023 low uncertainty projections by Class 8 truck types. Aggregation was done with StatCan Table: 23-10-0219-01 shipment type shares (local vs. long distance). Values were harmonized using provincial load factors. Energy consumption based on drive cycle combinations as prescribed in the EPA final rule regulatory documents for MHDVs (EPA & NHTSA, 2016). | AK24: 3 | AL24: 1 | AM24: 1 | AN24: 3 | AO24: 1
A25: T_HDV_T_BEV_N | B25: T_elc_hdv_chrg | C25: T_D_tkm_hdv_t | D25: ON | E25: Argonne National Laboratory, Islam, E. S., Prada, D. N., Vijayagopal, R., Mansour, C., Philips, P., Kim, N., Alhajjar, M., & Rousseau, A. (2023, October). Detailed Simulation Study to Evaluate Future Transportation Decarbonization Potential. Vehicle & Mobility Systems Department - Argonne National Laboratory. https://vms.taps.anl.gov/research-highlights/vehicle-technologies/u-s-doe-vto-hfto-r-d-benefits/ | F25: 2023 | AB25: =$AA$21*BF10 -> 1.7351458 | AC25: =$AA$21*BG10 -> 1.751338 | AD25: =$AA$21*BH10 -> 1.7783808 | AE25: =$AA$21*BI10 -> 1.8389735 | AF25: =$AA$21*BJ10 -> 1.8687206 | AG25: =$AA$21*BK10 -> 1.8969784 | AH25: =$AA$21*BL10 -> 1.923856 | AJ25: Vehicle class fuel efficiency aggregated from Islam et al. 2023 low uncertainty projections by Class 8 truck types. Aggregation was done with StatCan Table: 23-10-0219-01 shipment type shares (local vs. long distance). Values were harmonized using provincial load factors. Energy consumption based on drive cycle combinations as prescribed in the EPA final rule regulatory documents for MHDVs (EPA & NHTSA, 2016). | AK25: 3 | AL25: 1 | AM25: 1 | AN25: 3 | AO25: 1 | AS25: Estimated Load Factors by vehicle mode in Ontario (passengers carried/tonnes carried) - based on NRCan fleet activity, stock and avg. distance travelled*
A26: T_HDV_T_FCEV_N | B26: T_h2_hdv | C26: T_D_tkm_hdv_t | D26: ON | E26: Argonne National Laboratory, Islam, E. S., Prada, D. N., Vijayagopal, R., Mansour, C., Philips, P., Kim, N., Alhajjar, M., & Rousseau, A. (2023, October). Detailed Simulation Study to Evaluate Future Transportation Decarbonization Potential. Vehicle & Mobility Systems Department - Argonne National Laboratory. https://vms.taps.anl.gov/research-highlights/vehicle-technologies/u-s-doe-vto-hfto-r-d-benefits/ | F26: 2023 | AB26: =$AA$21*BF11 -> 0.81707995 | AC26: =$AA$21*BG11 -> 0.84908465 | AD26: =$AA$21*BH11 -> 0.8814158 | AE26: =$AA$21*BI11 -> 0.9163672 | AF26: =$AA$21*BJ11 -> 0.94141745 | AG26: =$AA$21*BK11 -> 0.96521353 | AH26: =$AA$21*BL11 -> 0.98784733 | AJ26: Vehicle class fuel efficiency aggregated from Islam et al. 2023 low uncertainty projections by Class 8 truck types. Aggregation was done with StatCan Table: 23-10-0219-01 shipment type shares (local vs. long distance). Values were harmonized using provincial load factors. Energy consumption based on drive cycle combinations as prescribed in the EPA final rule regulatory documents for MHDVs (EPA & NHTSA, 2016). | AK26: 3 | AL26: 1 | AM26: 1 | AN26: 3 | AO26: 1 | AS26: Mode | AT26: 2000 | AU26: 2001 | AV26: 2002 | AW26: 2003 | AX26: 2004 | AY26: 2005 | AZ26: 2006 | BA26: 2007 | BB26: 2008 | BC26: 2009 | BD26: 2010 | BE26: 2011 | BF26: 2012 | BG26: 2013 | BH26: 2014 | BI26: 2015 | BJ26: 2016 | BK26: 2017 | BL26: 2018 | BM26: 2019 | BN26: 2020 | BO26: 2015-2019 Average
A27: T_HDV_T_FCHEV_N | B27: T_h2_hdv | C27: T_D_tkm_hdv_t | D27: ON | E27: Argonne National Laboratory, Islam, E. S., Prada, D. N., Vijayagopal, R., Mansour, C., Philips, P., Kim, N., Alhajjar, M., & Rousseau, A. (2023, October). Detailed Simulation Study to Evaluate Future Transportation Decarbonization Potential. Vehicle & Mobility Systems Department - Argonne National Laboratory. https://vms.taps.anl.gov/research-highlights/vehicle-technologies/u-s-doe-vto-hfto-r-d-benefits/ | F27: 2023 | AB27: =$AA$21*BF12 -> 0.79415683 | AC27: =$AA$21*BG12 -> 0.82234932 | AD27: =$AA$21*BH12 -> 0.85275353 | AE27: =$AA$21*BI12 -> 0.90840404 | AF27: =$AA$21*BJ12 -> 0.93437597 | AG27: =$AA$21*BK12 -> 0.95904758 | AH27: =$AA$21*BL12 -> 0.98251415 | AJ27: Vehicle class fuel efficiency aggregated from Islam et al. 2023 low uncertainty projections by Class 8 truck types. Aggregation was done with StatCan Table: 23-10-0219-01 shipment type shares (local vs. long distance). Values were harmonized using provincial load factors. Energy consumption based on drive cycle combinations as prescribed in the EPA final rule regulatory documents for MHDVs (EPA & NHTSA, 2016). | AK27: 3 | AL27: 1 | AM27: 1 | AN27: 3 | AO27: 1 | AS27: Cars (passengers) | BB27: ='Background Data'!K22/('Background Data'!K32*'Background Data'!K11) * 1000 -> 1.5836001 | BC27: ='Background Data'!L22/('Background Data'!L32*'Background Data'!L11) * 1000 -> 1.5837999 | BD27: ='Background Data'!M22/('Background Data'!M32*'Background Data'!M11) * 1000 -> 1.584 | BE27: ='Background Data'!N22/('Background Data'!N32*'Background Data'!N11) * 1000 -> 1.5842 | BF27: ='Background Data'!O22/('Background Data'!O32*'Background Data'!O11) * 1000 -> 1.5844 | BG27: ='Background Data'!P22/('Background Data'!P32*'Background Data'!P11) * 1000 -> 1.5846001 | BH27: ='Background Data'!Q22/('Background Data'!Q32*'Background Data'!Q11) * 1000 -> 1.5848 | BI27: ='Background Data'!R22/('Background Data'!R32*'Background Data'!R11) * 1000 -> 1.5850001 | ... BN27: ='Background Data'!W22/('Background Data'!W32*'Background Data'!W11) * 1000 -> 1.586 | BO27: =AVERAGE(BI27:BM27) -> 1.5854
A28: T_dummy_tkm_hdv_t_lh | B28: T_annual_tkm_hdv_t_lh | C28: T_D_tkm_hdv_t_lh | D28: ON | AB28: 1 | AC28: 1 | AD28: 1 | AE28: 1 | AF28: 1 | AG28: 1 | AH28: 1 | AJ28: [btkm/btkm] Dummy tech used to release non-profiled vehicles from charging demand distribution | AS28: Light Trucks (passengers) | AZ28: ='Background Data'!I23/('Background Data'!I33*'Background Data'!I12) * 1000 -> 1.7071003 | BA28: ='Background Data'!J23/('Background Data'!J33*'Background Data'!J12) * 1000 -> 1.7075003 | BB28: ='Background Data'!K23/('Background Data'!K33*'Background Data'!K12) * 1000 -> 1.7078998 | BC28: ='Background Data'!L23/('Background Data'!L33*'Background Data'!L12) * 1000 -> 1.7082997 | BD28: ='Background Data'!M23/('Background Data'!M33*'Background Data'!M12) * 1000 -> 1.7087003 | BE28: ='Background Data'!N23/('Background Data'!N33*'Background Data'!N12) * 1000 -> 1.7091001 | BF28: ='Background Data'!O23/('Background Data'!O33*'Background Data'!O12) * 1000 -> 1.7095002 | BG28: ='Background Data'!P23/('Background Data'!P33*'Background Data'!P12) * 1000 -> 1.7099002 | ... BN28: ='Background Data'!W23/('Background Data'!W33*'Background Data'!W12) * 1000 -> 1.7126999 | BO28: =AVERAGE(BI28:BM28) -> 1.7115
AS29: Light Trucks (tonnes) | AZ29: ='Background Data'!I24/('Background Data'!I34*'Background Data'!I13) * 1000 -> 0.55333296 | BA29: ='Background Data'!J24/('Background Data'!J34*'Background Data'!J13) * 1000 -> 0.55666627 | BB29: ='Background Data'!K24/('Background Data'!K34*'Background Data'!K13) * 1000 -> 0.55666695 | BC29: ='Background Data'!L24/('Background Data'!L34*'Background Data'!L13) * 1000 -> 0.55666703 | BD29: ='Background Data'!M24/('Background Data'!M34*'Background Data'!M13) * 1000 -> 0.55666635 | BE29: ='Background Data'!N24/('Background Data'!N34*'Background Data'!N13) * 1000 -> 0.55666649 | BF29: ='Background Data'!O24/('Background Data'!O34*'Background Data'!O13) * 1000 -> 0.55666645 | BG29: ='Background Data'!P24/('Background Data'!P34*'Background Data'!P13) * 1000 -> 0.55666644 | ... BN29: ='Background Data'!W24/('Background Data'!W34*'Background Data'!W13) * 1000 -> 0.55666681 | BO29: =AVERAGE(BI29:BM29) -> 0.5566667
AS30: Medium Trucks (tonnes) | AZ30: ='Background Data'!I25/('Background Data'!I35*'Background Data'!I14) * 1000 -> 1.2550021 | BA30: ='Background Data'!J25/('Background Data'!J35*'Background Data'!J14) * 1000 -> 1.260001 | BB30: ='Background Data'!K25/('Background Data'!K35*'Background Data'!K14) * 1000 -> 1.2600018 | BC30: ='Background Data'!L25/('Background Data'!L35*'Background Data'!L14) * 1000 -> 1.2600004 | BD30: ='Background Data'!M25/('Background Data'!M35*'Background Data'!M14) * 1000 -> 1.26 | BE30: ='Background Data'!N25/('Background Data'!N35*'Background Data'!N14) * 1000 -> 1.26 | BF30: ='Background Data'!O25/('Background Data'!O35*'Background Data'!O14) * 1000 -> 1.26 | BG30: ='Background Data'!P25/('Background Data'!P35*'Background Data'!P14) * 1000 -> 1.26 | ... BN30: ='Background Data'!W25/('Background Data'!W35*'Background Data'!W14) * 1000 -> 1.26 | BO30: =AVERAGE(BI30:BM30) -> 1.26
AS31: Heavy Trucks (tonnes) | AW31: ='Background Data'!F26/('Background Data'!F36*'Background Data'!F15) * 1000 -> 7.1986242 | AX31: ='Background Data'!G26/('Background Data'!G36*'Background Data'!G15) * 1000 -> 7.1986241 | AY31: ='Background Data'!H26/('Background Data'!H36*'Background Data'!H15) * 1000 -> 6.8997234 | AZ31: ='Background Data'!I26/('Background Data'!I36*'Background Data'!I15) * 1000 -> 6.8874689 | BA31: ='Background Data'!J26/('Background Data'!J36*'Background Data'!J15) * 1000 -> 6.6614371 | BB31: ='Background Data'!K26/('Background Data'!K36*'Background Data'!K15) * 1000 -> 6.6432925 | BC31: ='Background Data'!L26/('Background Data'!L36*'Background Data'!L15) * 1000 -> 5.9271787 | BD31: ='Background Data'!M26/('Background Data'!M36*'Background Data'!M15) * 1000 -> 6.176216 | ... BN31: ='Background Data'!W26/('Background Data'!W36*'Background Data'!W15) * 1000 -> 6.8635374 | BO31: =AVERAGE(BI31:BM31) -> 7.3922499
AS32: Motorcycles (passengers) | AY32: ='Background Data'!H27/('Background Data'!H37*'Background Data'!H16) * 1000 -> 1.27004 | AZ32: ='Background Data'!I27/('Background Data'!I37*'Background Data'!I16) * 1000 -> 1.270064 | BA32: ='Background Data'!J27/('Background Data'!J37*'Background Data'!J16) * 1000 -> 1.269951 | BB32: ='Background Data'!K27/('Background Data'!K37*'Background Data'!K16) * 1000 -> 1.270022 | BC32: ='Background Data'!L27/('Background Data'!L37*'Background Data'!L16) * 1000 -> 1.07713 | BD32: ='Background Data'!M27/('Background Data'!M37*'Background Data'!M16) * 1000 -> 1.077135 | BE32: ='Background Data'!N27/('Background Data'!N37*'Background Data'!N16) * 1000 -> 1.077122 | BF32: ='Background Data'!O27/('Background Data'!O37*'Background Data'!O16) * 1000 -> 1.07711 | ... BN32: ='Background Data'!W27/('Background Data'!W37*'Background Data'!W16) * 1000 -> 1.212587 | BO32: =AVERAGE(BI32:BM32) -> 1.141241
AS33: School Buses (passengers) | BC33: =('Background Data'!L28*1000)/('Background Data'!L38*'Background Data'!L17) -> 21.59 | BD33: =('Background Data'!M28*1000)/('Background Data'!M38*'Background Data'!M17) -> 21.82 | BE33: =('Background Data'!N28*1000)/('Background Data'!N38*'Background Data'!N17) -> 22.05 | BF33: =('Background Data'!O28*1000)/('Background Data'!O38*'Background Data'!O17) -> 22.28 | BG33: =('Background Data'!P28*1000)/('Background Data'!P38*'Background Data'!P17) -> 22.28 | BH33: =('Background Data'!Q28*1000)/('Background Data'!Q38*'Background Data'!Q17) -> 22.28 | BI33: =('Background Data'!R28*1000)/('Background Data'!R38*'Background Data'!R17) -> 22.28 | BJ33: =('Background Data'!S28*1000)/('Background Data'!S38*'Background Data'!S17) -> 22.28 | ... BN33: =('Background Data'!W28*1000)/('Background Data'!W38*'Background Data'!W17) -> 22.28 | BO33: =AVERAGE(BI33:BM33) -> 22.28
AS34: Transit Buses (passengers) | BC34: =('Background Data'!L29*1000)/('Background Data'!L39*'Background Data'!L18) -> 12.08 | BD34: =('Background Data'!M29*1000)/('Background Data'!M39*'Background Data'!M18) -> 12.18 | BE34: =('Background Data'!N29*1000)/('Background Data'!N39*'Background Data'!N18) -> 12.29 | BF34: =('Background Data'!O29*1000)/('Background Data'!O39*'Background Data'!O18) -> 12.39 | BG34: =('Background Data'!P29*1000)/('Background Data'!P39*'Background Data'!P18) -> 12.39 | BH34: =('Background Data'!Q29*1000)/('Background Data'!Q39*'Background Data'!Q18) -> 12.39 | BI34: =('Background Data'!R29*1000)/('Background Data'!R39*'Background Data'!R18) -> 12.39 | BJ34: =('Background Data'!S29*1000)/('Background Data'!S39*'Background Data'!S18) -> 12.39 | ... BN34: =('Background Data'!W29*1000)/('Background Data'!W39*'Background Data'!W18) -> 12.39 | BO34: =AVERAGE(BI34:BM34) -> 12.39
AS35: Inter-city Buses (passengers) | BC35: =('Background Data'!L30*1000)/('Background Data'!L40*'Background Data'!L19) -> 16.88 | BD35: =('Background Data'!M30*1000)/('Background Data'!M40*'Background Data'!M19) -> 16.88 | BE35: =('Background Data'!N30*1000)/('Background Data'!N40*'Background Data'!N19) -> 16.88 | BF35: =('Background Data'!O30*1000)/('Background Data'!O40*'Background Data'!O19) -> 16.88 | BG35: =('Background Data'!P30*1000)/('Background Data'!P40*'Background Data'!P19) -> 16.88 | BH35: =('Background Data'!Q30*1000)/('Background Data'!Q40*'Background Data'!Q19) -> 16.88 | BI35: =('Background Data'!R30*1000)/('Background Data'!R40*'Background Data'!R19) -> 16.88 | BJ35: =('Background Data'!S30*1000)/('Background Data'!S40*'Background Data'!S19) -> 16.88 | ... BN35: =('Background Data'!W30*1000)/('Background Data'!W40*'Background Data'!W19) -> 16.88 | BO35: =AVERAGE(BI35:BM35) -> 16.88
AS36: *Load factors were estimated by dividing mode activity by (distance travelled times fleet stock).

Sheet CapacityToActivity
A1: tech | B1: region | C1: Capacity Unit | D1: Activity Unit | E1: c2a | F1: notes
A2: T_HDV_T_LH_DSL_EX | B2: ON | C2: k units | D2: btkm | E2: =50*6500*10*1000/1000000000 -> 3.25 | F2: [btkm/k units] An estimate of how much activity a unit of capacity can deliver in a year. Assuming this vehicle class can be driven at an avg. speed of 50 km/h carrying 10 tonnes of payload for 6,500 hours each year.
A3: T_HDV_T_LH_DSL_N | B3: ON | C3: k units | D3: btkm | E3: =50*6500*10*1000/1000000000 -> 3.25 | F3: [btkm/k units] An estimate of how much activity a unit of capacity can deliver in a year. Assuming this vehicle class can be driven at an avg. speed of 50 km/h carrying 10 tonnes of payload for 6,500 hours each year.
A4: T_HDV_T_LH_FCEV_N | B4: ON | C4: k units | D4: btkm | E4: =50*6500*10*1000/1000000000 -> 3.25 | F4: [btkm/k units] An estimate of how much activity a unit of capacity can deliver in a year. Assuming this vehicle class can be driven at an avg. speed of 50 km/h carrying 10 tonnes of payload for 6,500 hours each year.
A5: T_HDV_T_LH_BEV_LRGBATT_N | B5: ON | C5: k units | D5: btkm | E5: =50*6500*10*1000/1000000000 -> 3.25 | F5: [btkm/k units] An estimate of how much activity a unit of capacity can deliver in a year. Assuming this vehicle class can be driven at an avg. speed of 50 km/h carrying 10 tonnes of payload for 6,500 hours each year.
A6: T_HDV_T_LH_BEV_FSTCHRG_N | B6: ON | C6: k units | D6: btkm | E6: =50*6500*10*1000/1000000000 -> 3.25 | F6: [btkm/k units] An estimate of how much activity a unit of capacity can deliver in a year. Assuming this vehicle class can be driven at an avg. speed of 50 km/h carrying 10 tonnes of payload for 6,500 hours each year.
A7: T_HDV_T_LH_BEV_ERDS1_N | B7: ON | C7: k units | D7: btkm | E7: =50*6500*10*1000/1000000000 -> 3.25 | F7: [btkm/k units] An estimate of how much activity a unit of capacity can deliver in a year. Assuming this vehicle class can be driven at an avg. speed of 50 km/h carrying 10 tonnes of payload for 6,500 hours each year.
A8: T_HDV_T_LH_BEV_ERDS2_N | B8: ON | C8: k units | D8: btkm | E8: =50*6500*10*1000/1000000000 -> 3.25 | F8: [btkm/k units] An estimate of how much activity a unit of capacity can deliver in a year. Assuming this vehicle class can be driven at an avg. speed of 50 km/h carrying 10 tonnes of payload for 6,500 hours each year.
A9: T_HDV_T_LH_BEV_ERDS3_N | B9: ON | C9: k units | D9: btkm | E9: =50*6500*10*1000/1000000000 -> 3.25 | F9: [btkm/k units] An estimate of how much activity a unit of capacity can deliver in a year. Assuming this vehicle class can be driven at an avg. speed of 50 km/h carrying 10 tonnes of payload for 6,500 hours each year.
A10: T_HDV_T_LH_BEV_ERDS4_N | B10: ON | C10: k units | D10: btkm | E10: =50*6500*10*1000/1000000000 -> 3.25 | F10: [btkm/k units] An estimate of how much activity a unit of capacity can deliver in a year. Assuming this vehicle class can be driven at an avg. speed of 50 km/h carrying 10 tonnes of payload for 6,500 hours each year.
A11: T_HDV_T_LH_BEV_ERDS5_N | B11: ON | C11: k units | D11: btkm | E11: =50*6500*10*1000/1000000000 -> 3.25 | F11: [btkm/k units] An estimate of how much activity a unit of capacity can deliver in a year. Assuming this vehicle class can be driven at an avg. speed of 50 km/h carrying 10 tonnes of payload for 6,500 hours each year.
A12: T_H2_HDV_T_LH_REFUEL | B12: ON | C12: stations | D12: PJ | E12: =1300*365*120/1000000000 -> 0.05694 | F12: [PJ/H2 station] total PJ of electricity/H2 a charger/H2 station can supply if running 24/7/365. Capacity 1,300 kgH2/day (from IEA Future of Hydrogen report via OEO 2022). LHV 120MJ/kgH2
A13: T_HDV_T_LH_CHRG_ERDS1 | B13: ON | C13: km | D13: PJ | E13: =0.097952 -> 0.097952 | F13: [PJ/km of eRoads] max theoretical AADTT*365*(kWh/km) converted to PJ
A14: T_HDV_T_LH_CHRG_ERDS2 | B14: ON | C14: km | D14: PJ | E14: =0.097952 -> 0.097952 | F14: [PJ/km of eRoads] max theoretical AADTT*365*(kWh/km) converted to PJ
A15: T_HDV_T_LH_CHRG_ERDS3 | B15: ON | C15: km | D15: PJ | E15: =0.097952 -> 0.097952 | F15: [PJ/km of eRoads] max theoretical AADTT*365*(kWh/km) converted to PJ
A16: T_HDV_T_LH_CHRG_ERDS4 | B16: ON | C16: km | D16: PJ | E16: =0.097952 -> 0.097952 | F16: [PJ/km of eRoads] max theoretical AADTT*365*(kWh/km) converted to PJ
A17: T_HDV_T_LH_CHRG_ERDS5 | B17: ON | C17: km | D17: PJ | E17: =0.097952 -> 0.097952 | F17: [PJ/km of eRoads] max theoretical AADTT*365*(kWh/km) converted to PJ
A18: T_HDV_T_LH_CHRG_FSTCHRG | B18: ON | C18: chargers | D18: PJ | E18: =0.094608 -> 0.094608 | F18: [PJ/charger] total PJ of electricity/H2 a charger/H2 station can supply if running 24/7/365. Power kW*60*60*24*365/1000000000000
A19: T_HDV_T_LH_CHRG_LRGBATT | B19: ON | C19: chargers | D19: PJ | E19: =0.011038 -> 0.011038 | F19: [PJ/charger] total PJ of electricity/H2 a charger/H2 station can supply if running 24/7/365. Power kW*60*60*24*365/1000000000000

Sheet MaxAnnualCapacityFactor
F1: period | N1: Model input | P1: Input calculations
A2: tech | B2: output_comm | C2: region | D2: reference | E2: data_year | F2: 2021 | G2: 2025 | H2: 2030 | I2: 2035 | J2: 2040 | K2: 2045 | L2: 2050 | M2: notes
A3: T_HDV_T_DSL_EX | B3: T_D_tkm_hdv_t | C3: ON | D3: Natural Resources Canada. (2023b). Transportation Sector – Ontario. Government of Canada, Natural Resources Canada. https://oee.nrcan.gc.ca/corporate/statistics/neud/dpa/menus/trends/comprehensive/trends_tran_on.cfm | E3: 2023 | F3: =$AM$15/CapacityToActivity!$E$2 -> 0.071509043 | G3: =AVERAGE(F3,H3) -> 0.077524837 | H3: =$AO$15 / CapacityToActivity!$E$2 -> 0.083540632 | I3: =$AO$15 / CapacityToActivity!$E$2 -> 0.083540632 | J3: =NA() -> #N/A | K3: =NA() -> #N/A | L3: =NA() -> #N/A | M3: First period is the ratio of the 2021 vehicle class reported activity over the activity the 2021 stock can deliver based on the CapacityToActivity factors. Subsequent periods are based on the average historical ratio between 2015-2019. | Q3: Activity over stock ratios (bn p-km or t-km/k vehicles)
A4: T_HDV_T_DSL_N | B4: T_D_tkm_hdv_t | C4: ON | D4: Natural Resources Canada. (2023b). Transportation Sector – Ontario. Government of Canada, Natural Resources Canada. https://oee.nrcan.gc.ca/corporate/statistics/neud/dpa/menus/trends/comprehensive/trends_tran_on.cfm | E4: 2023 | F4: =$F$3 -> 0.071509043 | G4: =$G$3 -> 0.077524837 | H4: =$H$3 -> 0.083540632 | I4: =$H$3 -> 0.083540632 | J4: =$H$3 -> 0.083540632 | K4: =$H$3 -> 0.083540632 | L4: =$H$3 -> 0.083540632 | M4: First period is the ratio of the 2021 vehicle class reported activity over the activity the 2021 stock can deliver based on the CapacityToActivity factors. Subsequent periods are based on the average historical ratio between 2015-2019. | Q4: Activity class | R4: 2000 | S4: 2001 | T4: 2002 | U4: 2003 | V4: 2004 | W4: 2005 | X4: 2006 | Y4: 2007 | Z4: 2008 | AA4: 2009 | AB4: 2010 | AC4: 2011 | AD4: 2012 | AE4: 2013 | AF4: 2014 | AG4: 2015 | AH4: 2016 | AI4: 2017 | AJ4: 2018 | AK4: 2019 | AL4: 2020 | AM4: 2021 | AN4: Max ratio | AO4: Avg ratio (2015-2019) | AP4: max/2019 | AQ4: max/2021 | AR4: 2019/2021 | AS4: avg/2021
A5: T_HDV_T_DSL_HEV_N | B5: T_D_tkm_hdv_t | C5: ON | D5: Natural Resources Canada. (2023b). Transportation Sector – Ontario. Government of Canada, Natural Resources Canada. https://oee.nrcan.gc.ca/corporate/statistics/neud/dpa/menus/trends/comprehensive/trends_tran_on.cfm | E5: 2023 | F5: =$F$3 -> 0.071509043 | G5: =$G$3 -> 0.077524837 | H5: =$H$3 -> 0.083540632 | I5: =$H$3 -> 0.083540632 | J5: =$H$3 -> 0.083540632 | K5: =$H$3 -> 0.083540632 | L5: =$H$3 -> 0.083540632 | M5: First period is the ratio of the 2021 vehicle class reported activity over the activity the 2021 stock can deliver based on the CapacityToActivity factors. Subsequent periods are based on the average historical ratio between 2015-2019. | Q5: Cars | R5: =('Background Data'!C22/1000)/'Background Data'!C11 -> 0.032344641 | S5: =('Background Data'!D22/1000)/'Background Data'!D11 -> 0.031053867 | T5: =('Background Data'!E22/1000)/'Background Data'!E11 -> 0.032578499 | U5: =('Background Data'!F22/1000)/'Background Data'!F11 -> 0.032538768 | V5: =('Background Data'!G22/1000)/'Background Data'!G11 -> 0.03264464 | W5: =('Background Data'!H22/1000)/'Background Data'!H11 -> 0.033091952 | X5: =('Background Data'!I22/1000)/'Background Data'!I11 -> 0.032283971 | Y5: =('Background Data'!J22/1000)/'Background Data'!J11 -> 0.032339642 | ... AM5: =('Background Data'!X22/1000)/'Background Data'!X11 -> 0.021703526 | AN5: =MAX(R5:AM5) -> 0.033091952 | AO5: =AVERAGE(AF5:AK5) -> 0.027337182 | AP5: =AN5/AK5 - 1 -> 0.2489863 | AQ5: =AN5/AM5 - 1 -> 0.52472701 | AR5: =AK5/AM5 - 1 -> 0.2207716 | AS5: =AO5/AM5 - 1 -> 0.25957334
A6: T_HDV_T_DSL_PHEV_N | B6: T_D_tkm_hdv_t | C6: ON | D6: Natural Resources Canada. (2023b). Transportation Sector – Ontario. Government of Canada, Natural Resources Canada. https://oee.nrcan.gc.ca/corporate/statistics/neud/dpa/menus/trends/comprehensive/trends_tran_on.cfm | E6: 2023 | F6: =$F$3 -> 0.071509043 | G6: =$G$3 -> 0.077524837 | H6: =$H$3 -> 0.083540632 | I6: =$H$3 -> 0.083540632 | J6: =$H$3 -> 0.083540632 | K6: =$H$3 -> 0.083540632 | L6: =$H$3 -> 0.083540632 | M6: First period is the ratio of the 2021 vehicle class reported activity over the activity the 2021 stock can deliver based on the CapacityToActivity factors. Subsequent periods are based on the average historical ratio between 2015-2019. | Q6: Light Passenger Trucks | R6: =('Background Data'!C23/1000)/'Background Data'!C12 -> 0.034571859 | S6: =('Background Data'!D23/1000)/'Background Data'!D12 -> 0.033331462 | T6: =('Background Data'!E23/1000)/'Background Data'!E12 -> 0.034808917 | U6: =('Background Data'!F23/1000)/'Background Data'!F12 -> 0.034676535 | V6: =('Background Data'!G23/1000)/'Background Data'!G12 -> 0.034888729 | W6: =('Background Data'!H23/1000)/'Background Data'!H12 -> 0.035452166 | X6: =('Background Data'!I23/1000)/'Background Data'!I12 -> 0.034617129 | Y6: =('Background Data'!J23/1000)/'Background Data'!J12 -> 0.034618994 | ... AM6: =('Background Data'!X23/1000)/'Background Data'!X12 -> 0.025008226 | AN6: =MAX(R6:AM6) -> 0.035452166 | AO6: =AVERAGE(AF6:AK6) -> 0.030480611 | AP6: =AN6/AK6 - 1 -> 0.18003651 | AQ6: =AN6/AM6 - 1 -> 0.41762019 | AR6: =AK6/AM6 - 1 -> 0.20133587 | AS6: =AO6/AM6 - 1 -> 0.21882343
A7: T_HDV_T_BEV_N | B7: T_D_tkm_hdv_t | C7: ON | D7: Natural Resources Canada. (2023b). Transportation Sector – Ontario. Government of Canada, Natural Resources Canada. https://oee.nrcan.gc.ca/corporate/statistics/neud/dpa/menus/trends/comprehensive/trends_tran_on.cfm | E7: 2023 | F7: =$F$3 -> 0.071509043 | G7: =$G$3 -> 0.077524837 | H7: =$H$3 -> 0.083540632 | I7: =$H$3 -> 0.083540632 | J7: =$H$3 -> 0.083540632 | K7: =$H$3 -> 0.083540632 | L7: =$H$3 -> 0.083540632 | M7: First period is the ratio of the 2021 vehicle class reported activity over the activity the 2021 stock can deliver based on the CapacityToActivity factors. Subsequent periods are based on the average historical ratio between 2015-2019. | Q7: Light Freight Trucks | R7: =('Background Data'!C24/1000)/'Background Data'!C13 -> 0.012739259 | S7: =('Background Data'!D24/1000)/'Background Data'!D13 -> 0.012464138 | T7: =('Background Data'!E24/1000)/'Background Data'!E13 -> 0.012885584 | U7: =('Background Data'!F24/1000)/'Background Data'!F13 -> 0.012987664 | V7: =('Background Data'!G24/1000)/'Background Data'!G13 -> 0.013205146 | W7: =('Background Data'!H24/1000)/'Background Data'!H13 -> 0.013458546 | X7: =('Background Data'!I24/1000)/'Background Data'!I13 -> 0.01350147 | Y7: =('Background Data'!J24/1000)/'Background Data'!J13 -> 0.013635512 | ... AM7: =('Background Data'!X24/1000)/'Background Data'!X13 -> 0.0097535331 | AN7: =MAX(R7:AM7) -> 0.013856566 | AO7: =AVERAGE(AF7:AK7) -> 0.011848737 | AP7: =AN7/AK7 - 1 -> 0.19485424 | AQ7: =AN7/AM7 - 1 -> 0.42067146 | AR7: =AK7/AM7 - 1 -> 0.18899144 | AS7: =AO7/AM7 - 1 -> 0.21481485
A8: T_HDV_T_FCEV_N | B8: T_D_tkm_hdv_t | C8: ON | D8: Natural Resources Canada. (2023b). Transportation Sector – Ontario. Government of Canada, Natural Resources Canada. https://oee.nrcan.gc.ca/corporate/statistics/neud/dpa/menus/trends/comprehensive/trends_tran_on.cfm | E8: 2023 | F8: =$F$3 -> 0.071509043 | G8: =$G$3 -> 0.077524837 | H8: =$H$3 -> 0.083540632 | I8: =$H$3 -> 0.083540632 | J8: =$H$3 -> 0.083540632 | K8: =$H$3 -> 0.083540632 | L8: =$H$3 -> 0.083540632 | M8: First period is the ratio of the 2021 vehicle class reported activity over the activity the 2021 stock can deliver based on the CapacityToActivity factors. Subsequent periods are based on the average historical ratio between 2015-2019. | Q8: Medium Trucks | R8: =('Background Data'!C25/1000)/'Background Data'!C14 -> 0.036410935 | S8: =('Background Data'!D25/1000)/'Background Data'!D14 -> 0.039172462 | T8: =('Background Data'!E25/1000)/'Background Data'!E14 -> 0.036749746 | U8: =('Background Data'!F25/1000)/'Background Data'!F14 -> 0.042012266 | V8: =('Background Data'!G25/1000)/'Background Data'!G14 -> 0.037878381 | W8: =('Background Data'!H25/1000)/'Background Data'!H14 -> 0.032192589 | X8: =('Background Data'!I25/1000)/'Background Data'!I14 -> 0.036849534 | Y8: =('Background Data'!J25/1000)/'Background Data'!J14 -> 0.037456594 | ... AM8: =('Background Data'!X25/1000)/'Background Data'!X14 -> 0.024183772 | AN8: =MAX(R8:AM8) -> 0.042012266 | AO8: =AVERAGE(AF8:AK8) -> 0.026988623 | AP8: =AN8/AK8 - 1 -> 0.57467694 | AQ8: =AN8/AM8 - 1 -> 0.73720899 | AR8: =AK8/AM8 - 1 -> 0.10321613 | AS8: =AO8/AM8 - 1 -> 0.11598072
A9: T_HDV_T_FCHEV_N | B9: T_D_tkm_hdv_t | C9: ON | D9: Natural Resources Canada. (2023b). Transportation Sector – Ontario. Government of Canada, Natural Resources Canada. https://oee.nrcan.gc.ca/corporate/statistics/neud/dpa/menus/trends/comprehensive/trends_tran_on.cfm | E9: 2023 | F9: =$F$3 -> 0.071509043 | G9: =$G$3 -> 0.077524837 | H9: =$H$3 -> 0.083540632 | I9: =$H$3 -> 0.083540632 | J9: =$H$3 -> 0.083540632 | K9: =$H$3 -> 0.083540632 | L9: =$H$3 -> 0.083540632 | M9: First period is the ratio of the 2021 vehicle class reported activity over the activity the 2021 stock can deliver based on the CapacityToActivity factors. Subsequent periods are based on the average historical ratio between 2015-2019. | Q9: Heavy Trucks | R9: =('Background Data'!C26/1000)/'Background Data'!C15 -> 0.7193665 | S9: =('Background Data'!D26/1000)/'Background Data'!D15 -> 0.65495568 | T9: =('Background Data'!E26/1000)/'Background Data'!E15 -> 0.64292607 | U9: =('Background Data'!F26/1000)/'Background Data'!F15 -> 0.67006731 | V9: =('Background Data'!G26/1000)/'Background Data'!G15 -> 0.70896051 | W9: =('Background Data'!H26/1000)/'Background Data'!H15 -> 0.74467628 | X9: =('Background Data'!I26/1000)/'Background Data'!I15 -> 0.65282638 | Y9: =('Background Data'!J26/1000)/'Background Data'!J15 -> 0.62843369 | ... AM9: =('Background Data'!X26/1000)/'Background Data'!X15 -> 0.62103082 | AN9: =MAX(R9:AM9) -> 0.76133285 | AO9: =AVERAGE(AF9:AK9) -> 0.72606131 | AP9: =AN9/AK9 - 1 -> 0.10325728 | AQ9: =AN9/AM9 - 1 -> 0.22591799 | AR9: =AK9/AM9 - 1 -> 0.11118052 | AS9: =AO9/AM9 - 1 -> 0.16912284
A10: T_HDV_T_LH_DSL_EX | B10: T_D_tkm_hdv_t_lh | C10: ON | D10: Natural Resources Canada. (2023b). Transportation Sector – Ontario. Government of Canada, Natural Resources Canada. https://oee.nrcan.gc.ca/corporate/statistics/neud/dpa/menus/trends/comprehensive/trends_tran_on.cfm | E10: 2023 | F10: =$AM$16/CapacityToActivity!$E$2 -> 0.40740051 | G10: =AVERAGE(F10,H10) -> 0.44167363 | H10: =$AO$16 / CapacityToActivity!$E$2 -> 0.47594674 | I10: =$AO$16 / CapacityToActivity!$E$2 -> 0.47594674 | J10: =NA() -> #N/A | K10: =NA() -> #N/A | L10: =NA() -> #N/A | M10: First period is the ratio of the 2021 vehicle class reported activity over the activity the 2021 stock can deliver based on the CapacityToActivity factors. Subsequent periods are based on the average historical ratio between 2015-2019. | Q10: Motorcycles | R10: =('Background Data'!C27/1000)/'Background Data'!C16 -> 0.0056167642 | S10: =('Background Data'!D27/1000)/'Background Data'!D16 -> 0.0060994816 | T10: =('Background Data'!E27/1000)/'Background Data'!E16 -> 0.0067619502 | U10: =('Background Data'!F27/1000)/'Background Data'!F16 -> 0.0067920696 | V10: =('Background Data'!G27/1000)/'Background Data'!G16 -> 0.0068999903 | W10: =('Background Data'!H27/1000)/'Background Data'!H16 -> 0.0070353958 | X10: =('Background Data'!I27/1000)/'Background Data'!I16 -> 0.0068536123 | Y10: =('Background Data'!J27/1000)/'Background Data'!J16 -> 0.0068671352 | ... AM10: =('Background Data'!X27/1000)/'Background Data'!X16 -> 0.0063204312 | AN10: =MAX(R10:AM10) -> 0.0070353958 | AO10: =AVERAGE(AF10:AK10) -> 0.0054414819 | AP10: =AN10/AK10 - 1 -> 0.28430934 | AQ10: =AN10/AM10 - 1 -> 0.1131196 | AR10: =AK10/AM10 - 1 -> -0.13329323 | AS10: =AO10/AM10 - 1 -> -0.13906477
A11: T_HDV_T_LH_DSL_N | B11: T_D_tkm_hdv_t_lh | C11: ON | D11: Natural Resources Canada. (2023b). Transportation Sector – Ontario. Government of Canada, Natural Resources Canada. https://oee.nrcan.gc.ca/corporate/statistics/neud/dpa/menus/trends/comprehensive/trends_tran_on.cfm | E11: 2023 | F11: =F$10 -> 0.40740051 | G11: =G$10 -> 0.44167363 | H11: =H$10 -> 0.47594674 | I11: =I$10 -> 0.47594674 | J11: =$AO$16 / CapacityToActivity!$E$2 -> 0.47594674 | K11: =$AO$16 / CapacityToActivity!$E$2 -> 0.47594674 | L11: =$AO$16 / CapacityToActivity!$E$2 -> 0.47594674 | M11: First period is the ratio of the 2021 vehicle class reported activity over the activity the 2021 stock can deliver based on the CapacityToActivity factors. Subsequent periods are based on the average historical ratio between 2015-2019. | Q11: School Buses | R11: =('Background Data'!C28/1000)/'Background Data'!C17 -> 0.46476837 | S11: =('Background Data'!D28/1000)/'Background Data'!D17 -> 0.4260989 | T11: =('Background Data'!E28/1000)/'Background Data'!E17 -> 0.44376564 | U11: =('Background Data'!F28/1000)/'Background Data'!F17 -> 0.50538225 | V11: =('Background Data'!G28/1000)/'Background Data'!G17 -> 0.48890973 | W11: =('Background Data'!H28/1000)/'Background Data'!H17 -> 0.57200744 | X11: =('Background Data'!I28/1000)/'Background Data'!I17 -> 0.60478189 | Y11: =('Background Data'!J28/1000)/'Background Data'!J17 -> 0.49740915 | ... AM11: =('Background Data'!X28/1000)/'Background Data'!X17 -> 0.41267241 | AN11: =MAX(R11:AM11) -> 0.76220385 | AO11: =AVERAGE(AF11:AK11) -> 0.55237928 | AP11: =AN11/AK11 - 1 -> 0.39458433 | AQ11: =AN11/AM11 - 1 -> 0.84699491 | AR11: =AK11/AM11 - 1 -> 0.32440533 | AS11: =AO11/AM11 - 1 -> 0.3385418
A12: T_HDV_T_LH_BEV_LRGBATT_N | B12: T_annual_tkm_hdv_t_lh | C12: ON | D12: Natural Resources Canada. (2023b). Transportation Sector – Ontario. Government of Canada, Natural Resources Canada. https://oee.nrcan.gc.ca/corporate/statistics/neud/dpa/menus/trends/comprehensive/trends_tran_on.cfm | E12: 2023 | F12: =F$11/'Payload capacity penalty'!C10 -> 0.40740051 | G12: =G$11/'Payload capacity penalty'!D10 -> 0.44167363 | H12: =H$11/'Payload capacity penalty'!E10 -> 0.47594674 | I12: =I$11/'Payload capacity penalty'!F10 -> 0.47594674 | J12: =J$11/'Payload capacity penalty'!G10 -> 0.47594674 | K12: =K$11/'Payload capacity penalty'!H10 -> 0.47594674 | L12: =L$11/'Payload capacity penalty'!I10 -> 0.47594674 | M12: First period is the ratio of the 2021 vehicle class reported activity over the activity the 2021 stock can deliver based on the CapacityToActivity factors. Subsequent periods are based on the average historical ratio between 2015-2019. MaxAnnualCapacityFactor adjusted to account for lost payload capacity. | Q12: Urban Transit Buses | R12: =('Background Data'!C29/1000)/'Background Data'!C18 -> 0.59423918 | S12: =('Background Data'!D29/1000)/'Background Data'!D18 -> 0.61946974 | T12: =('Background Data'!E29/1000)/'Background Data'!E18 -> 0.65920278 | U12: =('Background Data'!F29/1000)/'Background Data'!F18 -> 0.70666286 | V12: =('Background Data'!G29/1000)/'Background Data'!G18 -> 0.80120179 | W12: =('Background Data'!H29/1000)/'Background Data'!H18 -> 0.91363129 | X12: =('Background Data'!I29/1000)/'Background Data'!I18 -> 0.91902056 | Y12: =('Background Data'!J29/1000)/'Background Data'!J18 -> 0.67009588 | ... AM12: =('Background Data'!X29/1000)/'Background Data'!X18 -> 0.53103464 | AN12: =MAX(R12:AM12) -> 0.94684659 | AO12: =AVERAGE(AF12:AK12) -> 0.72470489 | AP12: =AN12/AK12 - 1 -> 0.3671187 | AQ12: =AN12/AM12 - 1 -> 0.78302226 | AR12: =AK12/AM12 - 1 -> 0.30421905 | AS12: =AO12/AM12 - 1 -> 0.36470361
A13: T_HDV_T_LH_BEV_FSTCHRG_N | B13: T_annual_tkm_hdv_t_lh | C13: ON | D13: Natural Resources Canada. (2023b). Transportation Sector – Ontario. Government of Canada, Natural Resources Canada. https://oee.nrcan.gc.ca/corporate/statistics/neud/dpa/menus/trends/comprehensive/trends_tran_on.cfm | E13: 2023 | F13: =F$11/'Payload capacity penalty'!C11 -> 0.40740051 | G13: =G$11/'Payload capacity penalty'!D11 -> 0.44167363 | H13: =H$11/'Payload capacity penalty'!E11 -> 0.47594674 | I13: =I$11/'Payload capacity penalty'!F11 -> 0.47594674 | J13: =J$11/'Payload capacity penalty'!G11 -> 0.47594674 | K13: =K$11/'Payload capacity penalty'!H11 -> 0.47594674 | L13: =L$11/'Payload capacity penalty'!I11 -> 0.47594674 | M13: First period is the ratio of the 2021 vehicle class reported activity over the activity the 2021 stock can deliver based on the CapacityToActivity factors. Subsequent periods are based on the average historical ratio between 2015-2019. MaxAnnualCapacityFactor adjusted to account for lost payload capacity. | Q13: Inter-city Buses | R13: =('Background Data'!C30/1000)/'Background Data'!C19 -> 1.1591245 | S13: =('Background Data'!D30/1000)/'Background Data'!D19 -> 0.92768097 | T13: =('Background Data'!E30/1000)/'Background Data'!E19 -> 1.0600822 | U13: =('Background Data'!F30/1000)/'Background Data'!F19 -> 0.99137253 | V13: =('Background Data'!G30/1000)/'Background Data'!G19 -> 1.0708795 | W13: =('Background Data'!H30/1000)/'Background Data'!H19 -> 1.1922902 | X13: =('Background Data'!I30/1000)/'Background Data'!I19 -> 0.87508077 | Y13: =('Background Data'!J30/1000)/'Background Data'!J19 -> 0.93620393 | ... AM13: =('Background Data'!X30/1000)/'Background Data'!X19 -> 0.57892416 | AN13: =MAX(R13:AM13) -> 1.1922902 | AO13: =AVERAGE(AF13:AK13) -> 0.76322579 | AP13: =AN13/AK13 - 1 -> 0.43487932 | AQ13: =AN13/AM13 - 1 -> 1.0594928 | AR13: =AK13/AM13 - 1 -> 0.43530736 | AS13: =AO13/AM13 - 1 -> 0.31835193
A14: T_HDV_T_LH_BEV_ERDS1_N | B14: T_annual_tkm_hdv_t_lh | C14: ON | D14: Natural Resources Canada. (2023b). Transportation Sector – Ontario. Government of Canada, Natural Resources Canada. https://oee.nrcan.gc.ca/corporate/statistics/neud/dpa/menus/trends/comprehensive/trends_tran_on.cfm | E14: 2023 | F14: =F$11/'Payload capacity penalty'!C12 -> 0.40740051 | G14: =G$11/'Payload capacity penalty'!D12 -> 0.44167363 | H14: =H$11/'Payload capacity penalty'!E12 -> 0.47594674 | I14: =I$11/'Payload capacity penalty'!F12 -> 0.47594674 | J14: =J$11/'Payload capacity penalty'!G12 -> 0.47594674 | K14: =K$11/'Payload capacity penalty'!H12 -> 0.47594674 | L14: =L$11/'Payload capacity penalty'!I12 -> 0.47594674 | M14: First period is the ratio of the 2021 vehicle class reported activity over the activity the 2021 stock can deliver based on the CapacityToActivity factors. Subsequent periods are based on the average historical ratio between 2015-2019. MaxAnnualCapacityFactor adjusted to account for lost payload capacity.
A15: T_HDV_T_LH_BEV_ERDS2_N | B15: T_annual_tkm_hdv_t_lh | C15: ON | D15: Natural Resources Canada. (2023b). Transportation Sector – Ontario. Government of Canada, Natural Resources Canada. https://oee.nrcan.gc.ca/corporate/statistics/neud/dpa/menus/trends/comprehensive/trends_tran_on.cfm | E15: 2023 | F15: =F$11/'Payload capacity penalty'!C13 -> 0.40740051 | G15: =G$11/'Payload capacity penalty'!D13 -> 0.44167363 | H15: =H$11/'Payload capacity penalty'!E13 -> 0.47594674 | I15: =I$11/'Payload capacity penalty'!F13 -> 0.47594674 | J15: =J$11/'Payload capacity penalty'!G13 -> 0.47594674 | K15: =K$11/'Payload capacity penalty'!H13 -> 0.47594674 | L15: =L$11/'Payload capacity penalty'!I13 -> 0.47594674 | M15: First period is the ratio of the 2021 vehicle class reported activity over the activity the 2021 stock can deliver based on the CapacityToActivity factors. Subsequent periods are based on the average historical ratio between 2015-2019. MaxAnnualCapacityFactor adjusted to account for lost payload capacity. | Q15: Heavy Trucks - non long-haul | AG15: =((1-CFAF!$E$4)*'Background Data'!R26/1000)/((1-CFAF!$E$3)*'Background Data'!R15) -> 0.27706196 | AH15: =((1-CFAF!$E$4)*'Background Data'!S26/1000)/((1-CFAF!$E$3)*'Background Data'!S15) -> 0.28145411 | AI15: =((1-CFAF!$E$4)*'Background Data'!T26/1000)/((1-CFAF!$E$3)*'Background Data'!T15) -> 0.28490872 | AJ15: =((1-CFAF!$E$4)*'Background Data'!U26/1000)/((1-CFAF!$E$3)*'Background Data'!U15) -> 0.25586725 | AK15: =((1-CFAF!$E$4)*'Background Data'!V26/1000)/((1-CFAF!$E$3)*'Background Data'!V15) -> 0.25824323 | AL15: =((1-CFAF!$E$4)*'Background Data'!W26/1000)/((1-CFAF!$E$3)*'Background Data'!W15) -> 0.22652592 | AM15: =((1-CFAF!$E$4)*'Background Data'!X26/1000)/((1-CFAF!$E$3)*'Background Data'!X15) -> 0.23240439 | AN15: =MAX(R15:AM15) -> 0.28490872 | AO15: =AVERAGE(AF15:AK15) -> 0.27150705 | AP15: =AN15/AK15 - 1 -> 0.10325728 | AQ15: =AN15/AM15 - 1 -> 0.22591799 | AR15: =AK15/AM15 - 1 -> 0.11118052 | AS15: =AO15/AM15 - 1 -> 0.16825269
A16: T_HDV_T_LH_BEV_ERDS3_N | B16: T_annual_tkm_hdv_t_lh | C16: ON | D16: Natural Resources Canada. (2023b). Transportation Sector – Ontario. Government of Canada, Natural Resources Canada. https://oee.nrcan.gc.ca/corporate/statistics/neud/dpa/menus/trends/comprehensive/trends_tran_on.cfm | E16: 2023 | F16: =F$11/'Payload capacity penalty'!C14 -> 0.40740051 | G16: =G$11/'Payload capacity penalty'!D14 -> 0.44167363 | H16: =H$11/'Payload capacity penalty'!E14 -> 0.47594674 | I16: =I$11/'Payload capacity penalty'!F14 -> 0.47594674 | J16: =J$11/'Payload capacity penalty'!G14 -> 0.47594674 | K16: =K$11/'Payload capacity penalty'!H14 -> 0.47594674 | L16: =L$11/'Payload capacity penalty'!I14 -> 0.47594674 | M16: First period is the ratio of the 2021 vehicle class reported activity over the activity the 2021 stock can deliver based on the CapacityToActivity factors. Subsequent periods are based on the average historical ratio between 2015-2019. MaxAnnualCapacityFactor adjusted to account for lost payload capacity. | Q16: Heavy Trucks - long-haul | AG16: =((CFAF!$E$4)*'Background Data'!R26/1000)/((CFAF!$E$3)*'Background Data'!R15) -> 1.5784743 | AH16: =((CFAF!$E$4)*'Background Data'!S26/1000)/((CFAF!$E$3)*'Background Data'!S15) -> 1.6034972 | AI16: =((CFAF!$E$4)*'Background Data'!T26/1000)/((CFAF!$E$3)*'Background Data'!T15) -> 1.6231787 | AJ16: =((CFAF!$E$4)*'Background Data'!U26/1000)/((CFAF!$E$3)*'Background Data'!U15) -> 1.457724 | AK16: =((CFAF!$E$4)*'Background Data'!V26/1000)/((CFAF!$E$3)*'Background Data'!V15) -> 1.4712604 | AL16: =((CFAF!$E$4)*'Background Data'!W26/1000)/((CFAF!$E$3)*'Background Data'!W15) -> 1.2905609 | AM16: =((CFAF!$E$4)*'Background Data'!X26/1000)/((CFAF!$E$3)*'Background Data'!X15) -> 1.3240517 | AN16: =MAX(R16:AM16) -> 1.6231787 | AO16: =AVERAGE(AF16:AK16) -> 1.5468269 | AP16: =AN16/AK16 - 1 -> 0.10325728 | AQ16: =AN16/AM16 - 1 -> 0.22591799 | AR16: =AK16/AM16 - 1 -> 0.11118052 | AS16: =AO16/AM16 - 1 -> 0.16825269
A17: T_HDV_T_LH_BEV_ERDS4_N | B17: T_annual_tkm_hdv_t_lh | C17: ON | D17: Natural Resources Canada. (2023b). Transportation Sector – Ontario. Government of Canada, Natural Resources Canada. https://oee.nrcan.gc.ca/corporate/statistics/neud/dpa/menus/trends/comprehensive/trends_tran_on.cfm | E17: 2023 | F17: =F$11/'Payload capacity penalty'!C15 -> 0.40740051 | G17: =G$11/'Payload capacity penalty'!D15 -> 0.44167363 | H17: =H$11/'Payload capacity penalty'!E15 -> 0.47594674 | I17: =I$11/'Payload capacity penalty'!F15 -> 0.47594674 | J17: =J$11/'Payload capacity penalty'!G15 -> 0.47594674 | K17: =K$11/'Payload capacity penalty'!H15 -> 0.47594674 | L17: =L$11/'Payload capacity penalty'!I15 -> 0.47594674 | M17: First period is the ratio of the 2021 vehicle class reported activity over the activity the 2021 stock can deliver based on the CapacityToActivity factors. Subsequent periods are based on the average historical ratio between 2015-2019. MaxAnnualCapacityFactor adjusted to account for lost payload capacity.
A18: T_HDV_T_LH_BEV_ERDS5_N | B18: T_annual_tkm_hdv_t_lh | C18: ON | D18: Natural Resources Canada. (2023b). Transportation Sector – Ontario. Government of Canada, Natural Resources Canada. https://oee.nrcan.gc.ca/corporate/statistics/neud/dpa/menus/trends/comprehensive/trends_tran_on.cfm | E18: 2023 | F18: =F$11/'Payload capacity penalty'!C16 -> 0.40740051 | G18: =G$11/'Payload capacity penalty'!D16 -> 0.44167363 | H18: =H$11/'Payload capacity penalty'!E16 -> 0.47594674 | I18: =I$11/'Payload capacity penalty'!F16 -> 0.47594674 | J18: =J$11/'Payload capacity penalty'!G16 -> 0.47594674 | K18: =K$11/'Payload capacity penalty'!H16 -> 0.47594674 | L18: =L$11/'Payload capacity penalty'!I16 -> 0.47594674 | M18: First period is the ratio of the 2021 vehicle class reported activity over the activity the 2021 stock can deliver based on the CapacityToActivity factors. Subsequent periods are based on the average historical ratio between 2015-2019. MaxAnnualCapacityFactor adjusted to account for lost payload capacity.
A19: T_HDV_T_LH_FCEV_N | B19: T_annual_tkm_hdv_t_lh | C19: ON | D19: Natural Resources Canada. (2023b). Transportation Sector – Ontario. Government of Canada, Natural Resources Canada. https://oee.nrcan.gc.ca/corporate/statistics/neud/dpa/menus/trends/comprehensive/trends_tran_on.cfm | E19: 2023 | F19: =F$11/'Payload capacity penalty'!C17 -> 0.40740051 | G19: =G$11/'Payload capacity penalty'!D17 -> 0.44167363 | H19: =H$11/'Payload capacity penalty'!E17 -> 0.47594674 | I19: =I$11/'Payload capacity penalty'!F17 -> 0.47594674 | J19: =J$11/'Payload capacity penalty'!G17 -> 0.47594674 | K19: =K$11/'Payload capacity penalty'!H17 -> 0.47594674 | L19: =L$11/'Payload capacity penalty'!I17 -> 0.47594674 | M19: First period is the ratio of the 2021 vehicle class reported activity over the activity the 2021 stock can deliver based on the CapacityToActivity factors. Subsequent periods are based on the average historical ratio between 2015-2019. MaxAnnualCapacityFactor adjusted to account for lost payload capacity.

Sheet MinAnnualCapacityFactor
F1: period | N1: Model input | P1: Input calculations
A2: tech | B2: output_comm | C2: region | D2: reference | E2: data_year | F2: 2021 | G2: 2025 | H2: 2030 | I2: 2035 | J2: 2040 | K2: 2045 | L2: 2050 | M2: notes
A3: T_HDV_T_DSL_EX | B3: T_D_tkm_hdv_t | C3: ON | D3: Natural Resources Canada. (2023b). Transportation Sector – Ontario. Government of Canada, Natural Resources Canada. https://oee.nrcan.gc.ca/corporate/statistics/neud/dpa/menus/trends/comprehensive/trends_tran_on.cfm | E3: 2023 | F3: {=0.99*MaxAnnualCapacityFactor!F3:L19} -> 0.070793952 | G3: 0.076749589 | H3: 0.082705226 | I3: 0.082705226 | J3: #N/A | K3: #N/A | L3: #N/A | M3: First period is the ratio of the 2021 vehicle class reported activity over the activity the 2021 stock can deliver based on the CapacityToActivity factors. Subsequent periods are based on the average historical ratio between 2015-2019. | Q3: Activity over stock ratios (bn p-km or t-km/k vehicles)
A4: T_HDV_T_DSL_N | B4: T_D_tkm_hdv_t | C4: ON | D4: Natural Resources Canada. (2023b). Transportation Sector – Ontario. Government of Canada, Natural Resources Canada. https://oee.nrcan.gc.ca/corporate/statistics/neud/dpa/menus/trends/comprehensive/trends_tran_on.cfm | E4: 2023 | F4: 0.070793952 | G4: 0.076749589 | H4: 0.082705226 | I4: 0.082705226 | J4: 0.082705226 | K4: 0.082705226 | L4: 0.082705226 | M4: First period is the ratio of the 2021 vehicle class reported activity over the activity the 2021 stock can deliver based on the CapacityToActivity factors. Subsequent periods are based on the average historical ratio between 2015-2019. | Q4: Activity class | R4: 2000 | S4: 2001 | T4: 2002 | U4: 2003 | V4: 2004 | W4: 2005 | X4: 2006 | Y4: 2007 | Z4: 2008 | AA4: 2009 | AB4: 2010 | AC4: 2011 | AD4: 2012 | AE4: 2013 | AF4: 2014 | AG4: 2015 | AH4: 2016 | AI4: 2017 | AJ4: 2018 | AK4: 2019 | AL4: 2020 | AM4: 2021 | AN4: Max ratio | AO4: Avg ratio (2015-2019) | AP4: max/2019 | AQ4: max/2021 | AR4: 2019/2021 | AS4: avg/2021
A5: T_HDV_T_DSL_HEV_N | B5: T_D_tkm_hdv_t | C5: ON | D5: Natural Resources Canada. (2023b). Transportation Sector – Ontario. Government of Canada, Natural Resources Canada. https://oee.nrcan.gc.ca/corporate/statistics/neud/dpa/menus/trends/comprehensive/trends_tran_on.cfm | E5: 2023 | F5: 0.070793952 | G5: 0.076749589 | H5: 0.082705226 | I5: 0.082705226 | J5: 0.082705226 | K5: 0.082705226 | L5: 0.082705226 | M5: First period is the ratio of the 2021 vehicle class reported activity over the activity the 2021 stock can deliver based on the CapacityToActivity factors. Subsequent periods are based on the average historical ratio between 2015-2019. | Q5: Cars | R5: =('Background Data'!C22/1000)/'Background Data'!C11 -> 0.032344641 | S5: =('Background Data'!D22/1000)/'Background Data'!D11 -> 0.031053867 | T5: =('Background Data'!E22/1000)/'Background Data'!E11 -> 0.032578499 | U5: =('Background Data'!F22/1000)/'Background Data'!F11 -> 0.032538768 | V5: =('Background Data'!G22/1000)/'Background Data'!G11 -> 0.03264464 | W5: =('Background Data'!H22/1000)/'Background Data'!H11 -> 0.033091952 | X5: =('Background Data'!I22/1000)/'Background Data'!I11 -> 0.032283971 | Y5: =('Background Data'!J22/1000)/'Background Data'!J11 -> 0.032339642 | ... AM5: =('Background Data'!X22/1000)/'Background Data'!X11 -> 0.021703526 | AN5: =MAX(R5:AM5) -> 0.033091952 | AO5: =AVERAGE(AF5:AK5) -> 0.027337182 | AP5: =AN5/AK5 - 1 -> 0.2489863 | AQ5: =AN5/AM5 - 1 -> 0.52472701 | AR5: =AK5/AM5 - 1 -> 0.2207716 | AS5: =AO5/AM5 - 1 -> 0.25957334
A6: T_HDV_T_DSL_PHEV_N | B6: T_D_tkm_hdv_t | C6: ON | D6: Natural Resources Canada. (2023b). Transportation Sector – Ontario. Government of Canada, Natural Resources Canada. https://oee.nrcan.gc.ca/corporate/statistics/neud/dpa/menus/trends/comprehensive/trends_tran_on.cfm | E6: 2023 | F6: 0.070793952 | G6: 0.076749589 | H6: 0.082705226 | I6: 0.082705226 | J6: 0.082705226 | K6: 0.082705226 | L6: 0.082705226 | M6: First period is the ratio of the 2021 vehicle class reported activity over the activity the 2021 stock can deliver based on the CapacityToActivity factors. Subsequent periods are based on the average historical ratio between 2015-2019. | Q6: Light Passenger Trucks | R6: =('Background Data'!C23/1000)/'Background Data'!C12 -> 0.034571859 | S6: =('Background Data'!D23/1000)/'Background Data'!D12 -> 0.033331462 | T6: =('Background Data'!E23/1000)/'Background Data'!E12 -> 0.034808917 | U6: =('Background Data'!F23/1000)/'Background Data'!F12 -> 0.034676535 | V6: =('Background Data'!G23/1000)/'Background Data'!G12 -> 0.034888729 | W6: =('Background Data'!H23/1000)/'Background Data'!H12 -> 0.035452166 | X6: =('Background Data'!I23/1000)/'Background Data'!I12 -> 0.034617129 | Y6: =('Background Data'!J23/1000)/'Background Data'!J12 -> 0.034618994 | ... AM6: =('Background Data'!X23/1000)/'Background Data'!X12 -> 0.025008226 | AN6: =MAX(R6:AM6) -> 0.035452166 | AO6: =AVERAGE(AF6:AK6) -> 0.030480611 | AP6: =AN6/AK6 - 1 -> 0.18003651 | AQ6: =AN6/AM6 - 1 -> 0.41762019 | AR6: =AK6/AM6 - 1 -> 0.20133587 | AS6: =AO6/AM6 - 1 -> 0.21882343
A7: T_HDV_T_BEV_N | B7: T_D_tkm_hdv_t | C7: ON | D7: Natural Resources Canada. (2023b). Transportation Sector – Ontario. Government of Canada, Natural Resources Canada. https://oee.nrcan.gc.ca/corporate/statistics/neud/dpa/menus/trends/comprehensive/trends_tran_on.cfm | E7: 2023 | F7: 0.070793952 | G7: 0.076749589 | H7: 0.082705226 | I7: 0.082705226 | J7: 0.082705226 | K7: 0.082705226 | L7: 0.082705226 | M7: First period is the ratio of the 2021 vehicle class reported activity over the activity the 2021 stock can deliver based on the CapacityToActivity factors. Subsequent periods are based on the average historical ratio between 2015-2019. | Q7: Light Freight Trucks | R7: =('Background Data'!C24/1000)/'Background Data'!C13 -> 0.012739259 | S7: =('Background Data'!D24/1000)/'Background Data'!D13 -> 0.012464138 | T7: =('Background Data'!E24/1000)/'Background Data'!E13 -> 0.012885584 | U7: =('Background Data'!F24/1000)/'Background Data'!F13 -> 0.012987664 | V7: =('Background Data'!G24/1000)/'Background Data'!G13 -> 0.013205146 | W7: =('Background Data'!H24/1000)/'Background Data'!H13 -> 0.013458546 | X7: =('Background Data'!I24/1000)/'Background Data'!I13 -> 0.01350147 | Y7: =('Background Data'!J24/1000)/'Background Data'!J13 -> 0.013635512 | ... AM7: =('Background Data'!X24/1000)/'Background Data'!X13 -> 0.0097535331 | AN7: =MAX(R7:AM7) -> 0.013856566 | AO7: =AVERAGE(AF7:AK7) -> 0.011848737 | AP7: =AN7/AK7 - 1 -> 0.19485424 | AQ7: =AN7/AM7 - 1 -> 0.42067146 | AR7: =AK7/AM7 - 1 -> 0.18899144 | AS7: =AO7/AM7 - 1 -> 0.21481485
A8: T_HDV_T_FCEV_N | B8: T_D_tkm_hdv_t | C8: ON | D8: Natural Resources Canada. (2023b). Transportation Sector – Ontario. Government of Canada, Natural Resources Canada. https://oee.nrcan.gc.ca/corporate/statistics/neud/dpa/menus/trends/comprehensive/trends_tran_on.cfm | E8: 2023 | F8: 0.070793952 | G8: 0.076749589 | H8: 0.082705226 | I8: 0.082705226 | J8: 0.082705226 | K8: 0.082705226 | L8: 0.082705226 | M8: First period is the ratio of the 2021 vehicle class reported activity over the activity the 2021 stock can deliver based on the CapacityToActivity factors. Subsequent periods are based on the average historical ratio between 2015-2019. | Q8: Medium Trucks | R8: =('Background Data'!C25/1000)/'Background Data'!C14 -> 0.036410935 | S8: =('Background Data'!D25/1000)/'Background Data'!D14 -> 0.039172462 | T8: =('Background Data'!E25/1000)/'Background Data'!E14 -> 0.036749746 | U8: =('Background Data'!F25/1000)/'Background Data'!F14 -> 0.042012266 | V8: =('Background Data'!G25/1000)/'Background Data'!G14 -> 0.037878381 | W8: =('Background Data'!H25/1000)/'Background Data'!H14 -> 0.032192589 | X8: =('Background Data'!I25/1000)/'Background Data'!I14 -> 0.036849534 | Y8: =('Background Data'!J25/1000)/'Background Data'!J14 -> 0.037456594 | ... AM8: =('Background Data'!X25/1000)/'Background Data'!X14 -> 0.024183772 | AN8: =MAX(R8:AM8) -> 0.042012266 | AO8: =AVERAGE(AF8:AK8) -> 0.026988623 | AP8: =AN8/AK8 - 1 -> 0.57467694 | AQ8: =AN8/AM8 - 1 -> 0.73720899 | AR8: =AK8/AM8 - 1 -> 0.10321613 | AS8: =AO8/AM8 - 1 -> 0.11598072
A9: T_HDV_T_FCHEV_N | B9: T_D_tkm_hdv_t | C9: ON | D9: Natural Resources Canada. (2023b). Transportation Sector – Ontario. Government of Canada, Natural Resources Canada. https://oee.nrcan.gc.ca/corporate/statistics/neud/dpa/menus/trends/comprehensive/trends_tran_on.cfm | E9: 2023 | F9: 0.070793952 | G9: 0.076749589 | H9: 0.082705226 | I9: 0.082705226 | J9: 0.082705226 | K9: 0.082705226 | L9: 0.082705226 | M9: First period is the ratio of the 2021 vehicle class reported activity over the activity the 2021 stock can deliver based on the CapacityToActivity factors. Subsequent periods are based on the average historical ratio between 2015-2019. | Q9: Heavy Trucks | R9: =('Background Data'!C26/1000)/'Background Data'!C15 -> 0.7193665 | S9: =('Background Data'!D26/1000)/'Background Data'!D15 -> 0.65495568 | T9: =('Background Data'!E26/1000)/'Background Data'!E15 -> 0.64292607 | U9: =('Background Data'!F26/1000)/'Background Data'!F15 -> 0.67006731 | V9: =('Background Data'!G26/1000)/'Background Data'!G15 -> 0.70896051 | W9: =('Background Data'!H26/1000)/'Background Data'!H15 -> 0.74467628 | X9: =('Background Data'!I26/1000)/'Background Data'!I15 -> 0.65282638 | Y9: =('Background Data'!J26/1000)/'Background Data'!J15 -> 0.62843369 | ... AM9: =('Background Data'!X26/1000)/'Background Data'!X15 -> 0.62103082 | AN9: =MAX(R9:AM9) -> 0.76133285 | AO9: =AVERAGE(AF9:AK9) -> 0.72606131 | AP9: =AN9/AK9 - 1 -> 0.10325728 | AQ9: =AN9/AM9 - 1 -> 0.22591799 | AR9: =AK9/AM9 - 1 -> 0.11118052 | AS9: =AO9/AM9 - 1 -> 0.16912284
A10: T_HDV_T_LH_DSL_EX | B10: T_D_tkm_hdv_t_lh | C10: ON | D10: Natural Resources Canada. (2023b). Transportation Sector – Ontario. Government of Canada, Natural Resources Canada. https://oee.nrcan.gc.ca/corporate/statistics/neud/dpa/menus/trends/comprehensive/trends_tran_on.cfm | E10: 2023 | F10: 0.4033265 | G10: 0.43725689 | H10: 0.47118728 | I10: 0.47118728 | J10: #N/A | K10: #N/A | L10: #N/A | M10: First period is the ratio of the 2021 vehicle class reported activity over the activity the 2021 stock can deliver based on the CapacityToActivity factors. Subsequent periods are based on the average historical ratio between 2015-2019. | Q10: Motorcycles | R10: =('Background Data'!C27/1000)/'Background Data'!C16 -> 0.0056167642 | S10: =('Background Data'!D27/1000)/'Background Data'!D16 -> 0.0060994816 | T10: =('Background Data'!E27/1000)/'Background Data'!E16 -> 0.0067619502 | U10: =('Background Data'!F27/1000)/'Background Data'!F16 -> 0.0067920696 | V10: =('Background Data'!G27/1000)/'Background Data'!G16 -> 0.0068999903 | W10: =('Background Data'!H27/1000)/'Background Data'!H16 -> 0.0070353958 | X10: =('Background Data'!I27/1000)/'Background Data'!I16 -> 0.0068536123 | Y10: =('Background Data'!J27/1000)/'Background Data'!J16 -> 0.0068671352 | ... AM10: =('Background Data'!X27/1000)/'Background Data'!X16 -> 0.0063204312 | AN10: =MAX(R10:AM10) -> 0.0070353958 | AO10: =AVERAGE(AF10:AK10) -> 0.0054414819 | AP10: =AN10/AK10 - 1 -> 0.28430934 | AQ10: =AN10/AM10 - 1 -> 0.1131196 | AR10: =AK10/AM10 - 1 -> -0.13329323 | AS10: =AO10/AM10 - 1 -> -0.13906477
A11: T_HDV_T_LH_DSL_N | B11: T_D_tkm_hdv_t_lh | C11: ON | D11: Natural Resources Canada. (2023b). Transportation Sector – Ontario. Government of Canada, Natural Resources Canada. https://oee.nrcan.gc.ca/corporate/statistics/neud/dpa/menus/trends/comprehensive/trends_tran_on.cfm | E11: 2023 | F11: 0.4033265 | G11: 0.43725689 | H11: 0.47118728 | I11: 0.47118728 | J11: 0.47118728 | K11: 0.47118728 | L11: 0.47118728 | M11: First period is the ratio of the 2021 vehicle class reported activity over the activity the 2021 stock can deliver based on the CapacityToActivity factors. Subsequent periods are based on the average historical ratio between 2015-2019. | Q11: School Buses | R11: =('Background Data'!C28/1000)/'Background Data'!C17 -> 0.46476837 | S11: =('Background Data'!D28/1000)/'Background Data'!D17 -> 0.4260989 | T11: =('Background Data'!E28/1000)/'Background Data'!E17 -> 0.44376564 | U11: =('Background Data'!F28/1000)/'Background Data'!F17 -> 0.50538225 | V11: =('Background Data'!G28/1000)/'Background Data'!G17 -> 0.48890973 | W11: =('Background Data'!H28/1000)/'Background Data'!H17 -> 0.57200744 | X11: =('Background Data'!I28/1000)/'Background Data'!I17 -> 0.60478189 | Y11: =('Background Data'!J28/1000)/'Background Data'!J17 -> 0.49740915 | ... AM11: =('Background Data'!X28/1000)/'Background Data'!X17 -> 0.41267241 | AN11: =MAX(R11:AM11) -> 0.76220385 | AO11: =AVERAGE(AF11:AK11) -> 0.55237928 | AP11: =AN11/AK11 - 1 -> 0.39458433 | AQ11: =AN11/AM11 - 1 -> 0.84699491 | AR11: =AK11/AM11 - 1 -> 0.32440533 | AS11: =AO11/AM11 - 1 -> 0.3385418
A12: T_HDV_T_LH_BEV_LRGBATT_N | B12: T_annual_tkm_hdv_t_lh | C12: ON | D12: Natural Resources Canada. (2023b). Transportation Sector – Ontario. Government of Canada, Natural Resources Canada. https://oee.nrcan.gc.ca/corporate/statistics/neud/dpa/menus/trends/comprehensive/trends_tran_on.cfm | E12: 2023 | F12: 0.4033265 | G12: 0.43725689 | H12: 0.47118728 | I12: 0.47118728 | J12: 0.47118728 | K12: 0.47118728 | L12: 0.47118728 | M12: First period is the ratio of the 2021 vehicle class reported activity over the activity the 2021 stock can deliver based on the CapacityToActivity factors. Subsequent periods are based on the average historical ratio between 2015-2019. MaxAnnualCapacityFactor adjusted to account for lost payload capacity. | Q12: Urban Transit Buses | R12: =('Background Data'!C29/1000)/'Background Data'!C18 -> 0.59423918 | S12: =('Background Data'!D29/1000)/'Background Data'!D18 -> 0.61946974 | T12: =('Background Data'!E29/1000)/'Background Data'!E18 -> 0.65920278 | U12: =('Background Data'!F29/1000)/'Background Data'!F18 -> 0.70666286 | V12: =('Background Data'!G29/1000)/'Background Data'!G18 -> 0.80120179 | W12: =('Background Data'!H29/1000)/'Background Data'!H18 -> 0.91363129 | X12: =('Background Data'!I29/1000)/'Background Data'!I18 -> 0.91902056 | Y12: =('Background Data'!J29/1000)/'Background Data'!J18 -> 0.67009588 | ... AM12: =('Background Data'!X29/1000)/'Background Data'!X18 -> 0.53103464 | AN12: =MAX(R12:AM12) -> 0.94684659 | AO12: =AVERAGE(AF12:AK12) -> 0.72470489 | AP12: =AN12/AK12 - 1 -> 0.3671187 | AQ12: =AN12/AM12 - 1 -> 0.78302226 | AR12: =AK12/AM12 - 1 -> 0.30421905 | AS12: =AO12/AM12 - 1 -> 0.36470361
A13: T_HDV_T_LH_BEV_FSTCHRG_N | B13: T_annual_tkm_hdv_t_lh | C13: ON | D13: Natural Resources Canada. (2023b). Transportation Sector – Ontario. Government of Canada, Natural Resources Canada. https://oee.nrcan.gc.ca/corporate/statistics/neud/dpa/menus/trends/comprehensive/trends_tran_on.cfm | E13: 2023 | F13: 0.4033265 | G13: 0.43725689 | H13: 0.47118728 | I13: 0.47118728 | J13: 0.47118728 | K13: 0.47118728 | L13: 0.47118728 | M13: First period is the ratio of the 2021 vehicle class reported activity over the activity the 2021 stock can deliver based on the CapacityToActivity factors. Subsequent periods are based on the average historical ratio between 2015-2019. MaxAnnualCapacityFactor adjusted to account for lost payload capacity. | Q13: Inter-city Buses | R13: =('Background Data'!C30/1000)/'Background Data'!C19 -> 1.1591245 | S13: =('Background Data'!D30/1000)/'Background Data'!D19 -> 0.92768097 | T13: =('Background Data'!E30/1000)/'Background Data'!E19 -> 1.0600822 | U13: =('Background Data'!F30/1000)/'Background Data'!F19 -> 0.99137253 | V13: =('Background Data'!G30/1000)/'Background Data'!G19 -> 1.0708795 | W13: =('Background Data'!H30/1000)/'Background Data'!H19 -> 1.1922902 | X13: =('Background Data'!I30/1000)/'Background Data'!I19 -> 0.87508077 | Y13: =('Background Data'!J30/1000)/'Background Data'!J19 -> 0.93620393 | ... AM13: =('Background Data'!X30/1000)/'Background Data'!X19 -> 0.57892416 | AN13: =MAX(R13:AM13) -> 1.1922902 | AO13: =AVERAGE(AF13:AK13) -> 0.76322579 | AP13: =AN13/AK13 - 1 -> 0.43487932 | AQ13: =AN13/AM13 - 1 -> 1.0594928 | AR13: =AK13/AM13 - 1 -> 0.43530736 | AS13: =AO13/AM13 - 1 -> 0.31835193
A14: T_HDV_T_LH_BEV_ERDS1_N | B14: T_annual_tkm_hdv_t_lh | C14: ON | D14: Natural Resources Canada. (2023b). Transportation Sector – Ontario. Government of Canada, Natural Resources Canada. https://oee.nrcan.gc.ca/corporate/statistics/neud/dpa/menus/trends/comprehensive/trends_tran_on.cfm | E14: 2023 | F14: 0.4033265 | G14: 0.43725689 | H14: 0.47118728 | I14: 0.47118728 | J14: 0.47118728 | K14: 0.47118728 | L14: 0.47118728 | M14: First period is the ratio of the 2021 vehicle class reported activity over the activity the 2021 stock can deliver based on the CapacityToActivity factors. Subsequent periods are based on the average historical ratio between 2015-2019. MaxAnnualCapacityFactor adjusted to account for lost payload capacity.
A15: T_HDV_T_LH_BEV_ERDS2_N | B15: T_annual_tkm_hdv_t_lh | C15: ON | D15: Natural Resources Canada. (2023b). Transportation Sector – Ontario. Government of Canada, Natural Resources Canada. https://oee.nrcan.gc.ca/corporate/statistics/neud/dpa/menus/trends/comprehensive/trends_tran_on.cfm | E15: 2023 | F15: 0.4033265 | G15: 0.43725689 | H15: 0.47118728 | I15: 0.47118728 | J15: 0.47118728 | K15: 0.47118728 | L15: 0.47118728 | M15: First period is the ratio of the 2021 vehicle class reported activity over the activity the 2021 stock can deliver based on the CapacityToActivity factors. Subsequent periods are based on the average historical ratio between 2015-2019. MaxAnnualCapacityFactor adjusted to account for lost payload capacity. | Q15: Heavy Trucks - non long-haul | AG15: =((1-CFAF!$E$4)*'Background Data'!R26/1000)/((1-CFAF!$E$3)*'Background Data'!R15) -> 0.27706196 | AH15: =((1-CFAF!$E$4)*'Background Data'!S26/1000)/((1-CFAF!$E$3)*'Background Data'!S15) -> 0.28145411 | AI15: =((1-CFAF!$E$4)*'Background Data'!T26/1000)/((1-CFAF!$E$3)*'Background Data'!T15) -> 0.28490872 | AJ15: =((1-CFAF!$E$4)*'Background Data'!U26/1000)/((1-CFAF!$E$3)*'Background Data'!U15) -> 0.25586725 | AK15: =((1-CFAF!$E$4)*'Background Data'!V26/1000)/((1-CFAF!$E$3)*'Background Data'!V15) -> 0.25824323 | AL15: =((1-CFAF!$E$4)*'Background Data'!W26/1000)/((1-CFAF!$E$3)*'Background Data'!W15) -> 0.22652592 | AM15: =((1-CFAF!$E$4)*'Background Data'!X26/1000)/((1-CFAF!$E$3)*'Background Data'!X15) -> 0.23240439 | AN15: =MAX(R15:AM15) -> 0.28490872 | AO15: =AVERAGE(AF15:AK15) -> 0.27150705 | AP15: =AN15/AK15 - 1 -> 0.10325728 | AQ15: =AN15/AM15 - 1 -> 0.22591799 | AR15: =AK15/AM15 - 1 -> 0.11118052 | AS15: =AO15/AM15 - 1 -> 0.16825269
A16: T_HDV_T_LH_BEV_ERDS3_N | B16: T_annual_tkm_hdv_t_lh | C16: ON | D16: Natural Resources Canada. (2023b). Transportation Sector – Ontario. Government of Canada, Natural Resources Canada. https://oee.nrcan.gc.ca/corporate/statistics/neud/dpa/menus/trends/comprehensive/trends_tran_on.cfm | E16: 2023 | F16: 0.4033265 | G16: 0.43725689 | H16: 0.47118728 | I16: 0.47118728 | J16: 0.47118728 | K16: 0.47118728 | L16: 0.47118728 | M16: First period is the ratio of the 2021 vehicle class reported activity over the activity the 2021 stock can deliver based on the CapacityToActivity factors. Subsequent periods are based on the average historical ratio between 2015-2019. MaxAnnualCapacityFactor adjusted to account for lost payload capacity. | Q16: Heavy Trucks - long-haul | AG16: =((CFAF!$E$4)*'Background Data'!R26/1000)/((CFAF!$E$3)*'Background Data'!R15) -> 1.5784743 | AH16: =((CFAF!$E$4)*'Background Data'!S26/1000)/((CFAF!$E$3)*'Background Data'!S15) -> 1.6034972 | AI16: =((CFAF!$E$4)*'Background Data'!T26/1000)/((CFAF!$E$3)*'Background Data'!T15) -> 1.6231787 | AJ16: =((CFAF!$E$4)*'Background Data'!U26/1000)/((CFAF!$E$3)*'Background Data'!U15) -> 1.457724 | AK16: =((CFAF!$E$4)*'Background Data'!V26/1000)/((CFAF!$E$3)*'Background Data'!V15) -> 1.4712604 | AL16: =((CFAF!$E$4)*'Background Data'!W26/1000)/((CFAF!$E$3)*'Background Data'!W15) -> 1.2905609 | AM16: =((CFAF!$E$4)*'Background Data'!X26/1000)/((CFAF!$E$3)*'Background Data'!X15) -> 1.3240517 | AN16: =MAX(R16:AM16) -> 1.6231787 | AO16: =AVERAGE(AF16:AK16) -> 1.5468269 | AP16: =AN16/AK16 - 1 -> 0.10325728 | AQ16: =AN16/AM16 - 1 -> 0.22591799 | AR16: =AK16/AM16 - 1 -> 0.11118052 | AS16: =AO16/AM16 - 1 -> 0.16825269
A17: T_HDV_T_LH_BEV_ERDS4_N | B17: T_annual_tkm_hdv_t_lh | C17: ON | D17: Natural Resources Canada. (2023b). Transportation Sector – Ontario. Government of Canada, Natural Resources Canada. https://oee.nrcan.gc.ca/corporate/statistics/neud/dpa/menus/trends/comprehensive/trends_tran_on.cfm | E17: 2023 | F17: 0.4033265 | G17: 0.43725689 | H17: 0.47118728 | I17: 0.47118728 | J17: 0.47118728 | K17: 0.47118728 | L17: 0.47118728 | M17: First period is the ratio of the 2021 vehicle class reported activity over the activity the 2021 stock can deliver based on the CapacityToActivity factors. Subsequent periods are based on the average historical ratio between 2015-2019. MaxAnnualCapacityFactor adjusted to account for lost payload capacity.
A18: T_HDV_T_LH_BEV_ERDS5_N | B18: T_annual_tkm_hdv_t_lh | C18: ON | D18: Natural Resources Canada. (2023b). Transportation Sector – Ontario. Government of Canada, Natural Resources Canada. https://oee.nrcan.gc.ca/corporate/statistics/neud/dpa/menus/trends/comprehensive/trends_tran_on.cfm | E18: 2023 | F18: 0.4033265 | G18: 0.43725689 | H18: 0.47118728 | I18: 0.47118728 | J18: 0.47118728 | K18: 0.47118728 | L18: 0.47118728 | M18: First period is the ratio of the 2021 vehicle class reported activity over the activity the 2021 stock can deliver based on the CapacityToActivity factors. Subsequent periods are based on the average historical ratio between 2015-2019. MaxAnnualCapacityFactor adjusted to account for lost payload capacity.
A19: T_HDV_T_LH_FCEV_N | B19: T_annual_tkm_hdv_t_lh | C19: ON | D19: Natural Resources Canada. (2023b). Transportation Sector – Ontario. Government of Canada, Natural Resources Canada. https://oee.nrcan.gc.ca/corporate/statistics/neud/dpa/menus/trends/comprehensive/trends_tran_on.cfm | E19: 2023 | F19: 0.4033265 | G19: 0.43725689 | H19: 0.47118728 | I19: 0.47118728 | J19: 0.47118728 | K19: 0.47118728 | L19: 0.47118728 | M19: First period is the ratio of the 2021 vehicle class reported activity over the activity the 2021 stock can deliver based on the CapacityToActivity factors. Subsequent periods are based on the average historical ratio between 2015-2019. MaxAnnualCapacityFactor adjusted to account for lost payload capacity.

Sheet MaxCapacity
A1: tech | B1: region | C1: period | D1: max_cap | E1: units | F1: notes
A2: T_HDV_T_LH_CHRG_ERDS1 | B2: ON | C2: 2021 | D2: 838.85 | E2: km | F2: Maximum length of eRoads in each bin
A3: T_HDV_T_LH_CHRG_ERDS1 | B3: ON | C3: 2025 | D3: 838.85 | E3: km | F3: Maximum length of eRoads in each bin
A4: T_HDV_T_LH_CHRG_ERDS1 | B4: ON | C4: 2030 | D4: 838.85 | E4: km | F4: Maximum length of eRoads in each bin
